{"p": {"msgId": "221887", "id": "25444", "rnds": [{"n": "1", "holes": [{"n": "1", "cNum": "1", "sc": "3", "pDay": "-1", "pTot": "-1", "shots": [{"n": "1", "pid": "0", "time": "", "putt": "", "t": "S", "prv": "n", "tee": "y", "cup": "n", "from": "OTB", "to": "ELF", "asc": "1", "dist": "10278", "left": "3973", "x": "8783.950", "y": "11706.215", "z": "1002.912", "club": "CFW", "con": "", "shotText": "Shot 1 286 yds to left fairway, 110 yds to hole"}, {"n": "2", "pid": "0", "time": "", "putt": "", "t": "S", "prv": "n", "tee": "n", "cup": "n", "from": "OFW", "to": "OGR", "asc": "1", "dist": "4014", "left": "180", "x": "8568.533", "y": "11962.107", "z": "1004.748", "club": "CUK", "con": "", "shotText": "Shot 2 112 yds to green, 15 ft to hole"}, {"n": "3", "pid": "0", "time": "", "putt": "1", "t": "S", "prv": "n", "tee": "n", "cup": "y", "from": "OGR", "to": "hole", "asc": "1", "dist": "180", "left": "0", "x": "0", "y": "0", "z": "0", "club": "CUK", "con": "", "shotText": "Shot 3 in the hole"}]}, {"n": "2", "cNum": "2", "sc": "3", "pDay": "-2", "pTot": "-2", "shots": [{"n": "1", "pid": "0", "time": "", "putt": "", "t": "S", "prv": "n", "tee": "y", "cup": "n", "from": "OTB", "to": "ELF", "asc": "1", "dist": "10790", "left": "4255", "x": "8750.132", "y": "11205.409", "z": "995.163", "club": "CDR", "con": "", "shotText": "Shot 1 300 yds to left fairway, 118 yds to hole"}, {"n": "2", "pid": "0", "time": "", "putt": "", "t": "S", "prv": "n", "tee": "n", "cup": "n", "from": "OFW", "to": "OGR", "asc": "1", "dist": "4199", "left": "108", "x": "8881.391", "y": "10881.110", "z": "988.558", "club": "CUK", "con": "", "shotText": "Shot 2 117 yds to green, 9 ft to hole"}, {"n": "3", "pid": "0", "time": "", "putt": "1", "t": "S", "prv": "n", "tee": "n", "cup": "y", "from": "OGR", "to": "hole", "asc": "1", "dist": "108", "left": "0", "x": "0", "y": "0", "z": "0", "club": "CUK", "con": "", "shotText": "Shot 3 in the hole"}]}, {"n": "3", "cNum": "3", "sc": "5", "pDay": "-2", "pTot": "-2", "shots": [{"n": "1", "pid": "0", "time": "", "putt": "", "t": "S", "prv": "n", "tee": "y", "cup": "n", "from": "OTB", "to": "ERI", "asc": "1", "dist": "11295", "left": "8107", "x": "7719.429", "y": "11157.700", "z": "985.066", "club": "CDR", "con": "", "shotText": "Shot 1 314 yds to right intermediate, 225 yds to hole"}, {"n": "2", "pid": "0", "time": "", "putt": "", "t": "S", "prv": "n", "tee": "n", "cup": "n", "from": "OIR", "to": "ERF", "asc": "1", "dist": "7440", "left": "810", "x": "7135.863", "y": "11367.058", "z": "987.824", "club": "CUK", "con": "", "shotText": "Shot 2 207 yds to right fairway, 68 ft to hole"}, {"n": "3", "pid": "0", "time": "", "putt": "", "t": "S", "prv": "n", "tee": "n", "cup": "n", "from": "OFW", "to": "OGR", "asc": "1", "dist": "929", "left": "117", "x": "7061.070", "y": "11347.498", "z": "991.760", "club": "CUK", "con": "", "shotText": "Shot 3 77 ft to green, 10 ft to hole"}, {"n": "4", "pid": "0", "time": "", "putt": "1", "t": "S", "prv": "n", "tee": "n", "cup": "n", "from": "OGR", "to": "OGR", "asc": "1", "dist": "136", "left": "23", "x": "7072.358", "y": "11346.253", "z": "991.542", "club": "CUK", "con": "", "shotText": "Shot 4 putt 11 ft 4 in., 23 in. to hole"}, {"n": "5", "pid": "0", "time": "", "putt": "2", "t": "S", "prv": "n", "tee": "n", "cup": "y", "from": "OGR", "to": "hole", "asc": "1", "dist": "23", "left": "0", "x": "0", "y": "0", "z": "0", "club": "CUK", "con": "", "shotText": "Shot 5 in the hole"}]}, {"n": "4", "cNum": "4", "sc": "3", "pDay": "-2", "pTot": "-2", "shots": [{"n": "1", "pid": "0", "time": "", "putt": "", "t": "S", "prv": "n", "tee": "y", "cup": "n", "from": "OTB", "to": "OGR", "asc": "1", "dist": "6001", "left": "359", "x": "6881.581", "y": "11910.658", "z": "998.134", "club": "CUK", "con": "", "shotText": "Shot 1 167 yds to green, 30 ft to hole"}, {"n": "2", "pid": "0", "time": "", "putt": "1", "t": "S", "prv": "n", "tee": "n", "cup": "n", "from": "OGR", "to": "OGR", "asc": "1", "dist": "346", "left": "15", "x": "6872.164", "y": "11883.431", "z": "997.352", "club": "CUK", "con": "", "shotText": "Shot 2 putt 28 ft 10 in., 15 in. to hole"}, {"n": "3", "pid": "0", "time": "", "putt": "2", "t": "S", "prv": "n", "tee": "n", "cup": "y", "from": "OGR", "to": "hole", "asc": "1", "dist": "15", "left": "0", "x": "0", "y": "0", "z": "0", "club": "CUK", "con": "", "shotText": "Shot 3 in the hole"}]}, {"n": "5", "cNum": "5", "sc": "4", "pDay": "-2", "pTot": "-2", "shots": [{"n": "1", "pid": "0", "time": "", "putt": "", "t": "S", "prv": "n", "tee": "y", "cup": "n", "from": "OTB", "to": "ERF", "asc": "1", "dist": "10901", "left": "5640", "x": "6119.843", "y": "11709.691", "z": "992.977", "club": "CDR", "con": "", "shotText": "Shot 1 303 yds to right fairway, 157 yds to hole"}, {"n": "2", "pid": "0", "time": "", "putt": "", "t": "S", "prv": "n", "tee": "n", "cup": "n", "from": "OFW", "to": "OGR", "asc": "1", "dist": "5642", "left": "238", "x": "5733.624", "y": "11441.562", "z": "992.575", "club": "CUK", "con": "", "shotText": "Shot 2 157 yds to green, 20 ft to hole"}, {"n": "3", "pid": "0", "time": "", "putt": "1", "t": "S", "prv": "n", "tee": "n", "cup": "n", "from": "OGR", "to": "OGR", "asc": "1", "dist": "286", "left": "43", "x": "5721.050", "y": "11461.763", "z": "992.247", "club": "CUK", "con": "", "shotText": "Shot 3 putt 23 ft 10 in., 3 ft 7 in. to hole"}, {"n": "4", "pid": "0", "time": "", "putt": "2", "t": "S", "prv": "n", "tee": "n", "cup": "y", "from": "OGR", "to": "hole", "asc": "1", "dist": "43", "left": "0", "x": "0", "y": "0", "z": "0", "club": "CUK", "con": "", "shotText": "Shot 4 in the hole"}]}, {"n": "6", "cNum": "6", "sc": "5", "pDay": "-1", "pTot": "-1", "shots": [{"n": "1", "pid": "0", "time": "", "putt": "", "t": "S", "prv": "n", "tee": "y", "cup": "n", "from": "OTB", "to": "ELF", "asc": "1", "dist": "10437", "left": "5207", "x": "6185.741", "y": "10855.728", "z": "982.049", "club": "CDR", "con": "", "shotText": "Shot 1 290 yds to left fairway, 145 yds to hole"}, {"n": "2", "pid": "0", "time": "", "putt": "", "t": "S", "prv": "n", "tee": "n", "cup": "n", "from": "OFW", "to": "OGR", "asc": "1", "dist": "5398", "left": "278", "x": "6630.539", "y": "10788.846", "z": "985.221", "club": "CUK", "con": "", "shotText": "Shot 2 150 yds to green, 23 ft to hole"}, {"n": "3", "pid": "0", "time": "", "putt": "1", "t": "S", "prv": "n", "tee": "n", "cup": "n", "from": "OGR", "to": "OGR", "asc": "1", "dist": "339", "left": "58", "x": "6613.240", "y": "10811.151", "z": "985.326", "club": "CUK", "con": "", "shotText": "Shot 3 putt 28 ft 3 in., 4 ft 10 in. to hole"}, {"n": "4", "pid": "0", "time": "", "putt": "2", "t": "S", "prv": "n", "tee": "n", "cup": "n", "from": "OGR", "to": "OGR", "asc": "1", "dist": "115", "left": "53", "x": "6619.816", "y": "10804.155", "z": "985.325", "club": "CUK", "con": "", "shotText": "Shot 4 putt 9 ft 7 in., 4 ft 5 in. to hole"}, {"n": "5", "pid": "0", "time": "", "putt": "3", "t": "S", "prv": "n", "tee": "n", "cup": "y", "from": "OGR", "to": "hole", "asc": "1", "dist": "53", "left": "0", "x": "0", "y": "0", "z": "0", "club": "CUK", "con": "", "shotText": "Shot 5 in the hole"}]}, {"n": "7", "cNum": "7", "sc": "3", "pDay": "-1", "pTot": "-1", "shots": [{"n": "1", "pid": "0", "time": "", "putt": "", "t": "S", "prv": "n", "tee": "y", "cup": "n", "from": "OTB", "to": "OGR", "asc": "1", "dist": "7104", "left": "652", "x": "6307.611", "y": "11418.052", "z": "989.232", "club": "CUK", "con": "", "shotText": "Shot 1 197 yds to green, 54 ft to hole"}, {"n": "2", "pid": "0", "time": "", "putt": "1", "t": "S", "prv": "n", "tee": "n", "cup": "n", "from": "OGR", "to": "OGR", "asc": "1", "dist": "561", "left": "104", "x": "6345.207", "y": "11445.831", "z": "989.555", "club": "CUK", "con": "", "shotText": "Shot 2 putt 46 ft 9 in., 8 ft 8 in. to hole"}, {"n": "3", "pid": "0", "time": "", "putt": "2", "t": "S", "prv": "n", "tee": "n", "cup": "y", "from": "OGR", "to": "hole", "asc": "1", "dist": "104", "left": "0", "x": "0", "y": "0", "z": "0", "club": "CUK", "con": "", "shotText": "Shot 3 in the hole"}]}, {"n": "8", "cNum": "8", "sc": "4", "pDay": "-1", "pTot": "-1", "shots": [{"n": "1", "pid": "0", "time": "", "putt": "", "t": "S", "prv": "n", "tee": "y", "cup": "n", "from": "OTB", "to": "ELI", "asc": "1", "dist": "10777", "left": "5987", "x": "7061.507", "y": "11009.222", "z": "979.845", "club": "CDR", "con": "", "shotText": "Shot 1 299 yds to left intermediate, 166 yds to hole"}, {"n": "2", "pid": "0", "time": "", "putt": "", "t": "S", "prv": "n", "tee": "n", "cup": "n", "from": "OIR", "to": "OGR", "asc": "1", "dist": "5481", "left": "583", "x": "7431.662", "y": "10741.689", "z": "980.177", "club": "CUK", "con": "", "shotText": "Shot 2 152 yds to green, 49 ft to hole"}, {"n": "3", "pid": "0", "time": "", "putt": "1", "t": "S", "prv": "n", "tee": "n", "cup": "n", "from": "OGR", "to": "OGR", "asc": "1", "dist": "622", "left": "35", "x": "7483.360", "y": "10738.013", "z": "981.195", "club": "CUK", "con": "", "shotText": "Shot 3 putt 51 ft 10 in., 2 ft 11 in. to hole"}, {"n": "4", "pid": "0", "time": "", "putt": "2", "t": "S", "prv": "n", "tee": "n", "cup": "y", "from": "OGR", "to": "hole", "asc": "1", "dist": "35", "left": "0", "x": "0", "y": "0", "z": "0", "club": "CUK", "con": "", "shotText": "Shot 4 in the hole"}]}, {"n": "9", "cNum": "9", "sc": "4", "pDay": "-1", "pTot": "-1", "shots": [{"n": "1", "pid": "0", "time": "", "putt": "", "t": "S", "prv": "n", "tee": "y", "cup": "n", "from": "OTB", "to": "ELF", "asc": "1", "dist": "10865", "left": "5659", "x": "8340.109", "y": "10791.840", "z": "986.373", "club": "CDR", "con": "", "shotText": "Shot 1 302 yds to left fairway, 157 yds to hole"}, {"n": "2", "pid": "0", "time": "", "putt": "", "t": "S", "prv": "n", "tee": "n", "cup": "n", "from": "OFW", "to": "OGR", "asc": "1", "dist": "5611", "left": "143", "x": "8770.518", "y": "10609.136", "z": "987.429", "club": "CUK", "con": "", "shotText": "Shot 2 156 yds to green, 12 ft to hole"}, {"n": "3", "pid": "0", "time": "", "putt": "1", "t": "S", "prv": "n", "tee": "n", "cup": "n", "from": "OGR", "to": "OGR", "asc": "1", "dist": "160", "left": "19", "x": "8768.265", "y": "10595.964", "z": "987.349", "club": "CUK", "con": "", "shotText": "Shot 3 putt 13 ft 4 in., 19 in. to hole"}, {"n": "4", "pid": "0", "time": "", "putt": "2", "t": "S", "prv": "n", "tee": "n", "cup": "y", "from": "OGR", "to": "hole", "asc": "1", "dist": "19", "left": "0", "x": "0", "y": "0", "z": "0", "club": "CUK", "con": "", "shotText": "Shot 4 in the hole"}]}, {"n": "10", "cNum": "10", "sc": "4", "pDay": "-1", "pTot": "-1", "shots": [{"n": "1", "pid": "0", "time": "", "putt": "", "t": "S", "prv": "n", "tee": "y", "cup": "n", "from": "OTB", "to": "ERF", "asc": "1", "dist": "9547", "left": "4594", "x": "8793.986", "y": "9827.522", "z": "980.003", "club": "CFW", "con": "", "shotText": "Shot 1 265 yds to right fairway, 128 yds to hole"}, {"n": "2", "pid": "0", "time": "", "putt": "", "t": "S", "prv": "n", "tee": "n", "cup": "n", "from": "OFW", "to": "OGR", "asc": "1", "dist": "4784", "left": "185", "x": "8396.672", "y": "9794.968", "z": "984.209", "club": "CUK", "con": "", "shotText": "Shot 2 133 yds to green, 15 ft to hole"}, {"n": "3", "pid": "0", "time": "", "putt": "1", "t": "S", "prv": "n", "tee": "n", "cup": "n", "from": "OGR", "to": "OGR", "asc": "1", "dist": "186", "left": "10", "x": "8412.079", "y": "9796.329", "z": "983.972", "club": "CUK", "con": "", "shotText": "Shot 3 putt 15 ft 6 in., 10 in. to hole"}, {"n": "4", "pid": "0", "time": "", "putt": "2", "t": "S", "prv": "n", "tee": "n", "cup": "y", "from": "OGR", "to": "hole", "asc": "1", "dist": "10", "left": "0", "x": "0", "y": "0", "z": "0", "club": "CUK", "con": "", "shotText": "Shot 4 in the hole"}]}, {"n": "11", "cNum": "11", "sc": "5", "pDay": "0", "pTot": "0", "shots": [{"n": "1", "pid": "0", "time": "", "putt": "", "t": "S", "prv": "n", "tee": "y", "cup": "n", "from": "OTB", "to": "ELR", "asc": "1", "dist": "9798", "left": "7917", "x": "7530.595", "y": "10194.319", "z": "979.311", "club": "CDR", "con": "", "shotText": "Shot 1 272 yds to left rough, 220 yds to hole"}, {"n": "2", "pid": "0", "time": "", "putt": "", "t": "S", "prv": "n", "tee": "n", "cup": "n", "from": "ORO", "to": "ERF", "asc": "1", "dist": "7110", "left": "818", "x": "7123.018", "y": "10624.355", "z": "982.274", "club": "CUK", "con": "", "shotText": "Shot 2 198 yds to right fairway, 68 ft to hole"}, {"n": "3", "pid": "0", "time": "", "putt": "", "t": "S", "prv": "n", "tee": "n", "cup": "n", "from": "OFW", "to": "OGR", "asc": "1", "dist": "872", "left": "63", "x": "7062.707", "y": "10664.926", "z": "982.768", "club": "CUK", "con": "", "shotText": "Shot 3 73 ft to green, 5 ft to hole"}, {"n": "4", "pid": "0", "time": "", "putt": "1", "t": "S", "prv": "n", "tee": "n", "cup": "n", "from": "OGR", "to": "OGR", "asc": "1", "dist": "94", "left": "26", "x": "7070.499", "y": "10665.218", "z": "982.643", "club": "CUK", "con": "", "shotText": "Shot 4 putt 7 ft 10 in., 2 ft 2 in. to hole"}, {"n": "5", "pid": "0", "time": "", "putt": "2", "t": "S", "prv": "n", "tee": "n", "cup": "y", "from": "OGR", "to": "hole", "asc": "1", "dist": "26", "left": "0", "x": "0", "y": "0", "z": "0", "club": "CUK", "con": "", "shotText": "Shot 5 in the hole"}]}, {"n": "12", "cNum": "12", "sc": "2", "pDay": "-1", "pTot": "-1", "shots": [{"n": "1", "pid": "0", "time": "", "putt": "", "t": "S", "prv": "n", "tee": "y", "cup": "n", "from": "OTB", "to": "OGR", "asc": "1", "dist": "6301", "left": "143", "x": "6529.465", "y": "10334.796", "z": "979.644", "club": "CUK", "con": "", "shotText": "Shot 1 175 yds to green, 12 ft to hole"}, {"n": "2", "pid": "0", "time": "", "putt": "1", "t": "S", "prv": "n", "tee": "n", "cup": "y", "from": "OGR", "to": "hole", "asc": "1", "dist": "143", "left": "0", "x": "0", "y": "0", "z": "0", "club": "CUK", "con": "", "shotText": "Shot 2 in the hole"}]}, {"n": "13", "cNum": "13", "sc": "4", "pDay": "-2", "pTot": "-2", "shots": [{"n": "1", "pid": "0", "time": "", "putt": "", "t": "S", "prv": "n", "tee": "y", "cup": "n", "from": "OTB", "to": "ERF", "asc": "1", "dist": "10742", "left": "8895", "x": "5657.948", "y": "10956.392", "z": "981.616", "club": "CDR", "con": "", "shotText": "Shot 1 298 yds to right fairway, 247 yds to hole"}, {"n": "2", "pid": "0", "time": "", "putt": "", "t": "S", "prv": "n", "tee": "n", "cup": "n", "from": "OFW", "to": "ELR", "asc": "1", "dist": "9361", "left": "1191", "x": "5110.209", "y": "11511.767", "z": "985.932", "club": "CUK", "con": "", "shotText": "Shot 2 260 yds to left rough, 99 ft to hole"}, {"n": "3", "pid": "0", "time": "", "putt": "", "t": "S", "prv": "n", "tee": "n", "cup": "n", "from": "ORO", "to": "OGR", "asc": "1", "dist": "1100", "left": "92", "x": "5197.048", "y": "11541.012", "z": "987.510", "club": "CUK", "con": "", "shotText": "Shot 3 92 ft to green, 8 ft to hole"}, {"n": "4", "pid": "0", "time": "", "putt": "1", "t": "S", "prv": "n", "tee": "n", "cup": "y", "from": "OGR", "to": "hole", "asc": "1", "dist": "92", "left": "0", "x": "0", "y": "0", "z": "0", "club": "CUK", "con": "", "shotText": "Shot 4 in the hole"}]}, {"n": "14", "cNum": "14", "sc": "4", "pDay": "-2", "pTot": "-2", "shots": [{"n": "1", "pid": "0", "time": "", "putt": "", "t": "S", "prv": "n", "tee": "y", "cup": "n", "from": "OTB", "to": "ERF", "asc": "1", "dist": "10527", "left": "5911", "x": "5398.443", "y": "10575.841", "z": "987.635", "club": "CDR", "con": "", "shotText": "Shot 1 292 yds to right fairway, 164 yds to hole"}, {"n": "2", "pid": "0", "time": "", "putt": "", "t": "S", "prv": "n", "tee": "n", "cup": "n", "from": "OFW", "to": "OGR", "asc": "1", "dist": "5788", "left": "625", "x": "5785.045", "y": "10287.399", "z": "986.539", "club": "CUK", "con": "", "shotText": "Shot 2 161 yds to green, 52 ft to hole"}, {"n": "3", "pid": "0", "time": "", "putt": "1", "t": "S", "prv": "n", "tee": "n", "cup": "n", "from": "OGR", "to": "OGR", "asc": "1", "dist": "659", "left": "36", "x": "5825.382", "y": "10324.638", "z": "986.583", "club": "CUK", "con": "", "shotText": "Shot 3 putt 54 ft 11 in., 3 ft 0 in. to hole"}, {"n": "4", "pid": "0", "time": "", "putt": "2", "t": "S", "prv": "n", "tee": "n", "cup": "y", "from": "OGR", "to": "hole", "asc": "1", "dist": "36", "left": "0", "x": "0", "y": "0", "z": "0", "club": "CUK", "con": "", "shotText": "Shot 4 in the hole"}]}, {"n": "15", "cNum": "15", "sc": "5", "pDay": "-2", "pTot": "-2", "shots": [{"n": "1", "pid": "0", "time": "", "putt": "", "t": "S", "prv": "n", "tee": "y", "cup": "n", "from": "OTB", "to": "ELF", "asc": "1", "dist": "10876", "left": "9335", "x": "6853.428", "y": "10070.981", "z": "979.666", "club": "CDR", "con": "", "shotText": "Shot 1 302 yds to left fairway, 259 yds to hole"}, {"n": "2", "pid": "0", "time": "", "putt": "", "t": "S", "prv": "n", "tee": "n", "cup": "n", "from": "OFW", "to": "ERF", "asc": "1", "dist": "6535", "left": "2819", "x": "7392.717", "y": "9995.456", "z": "977.164", "club": "CUK", "con": "", "shotText": "Shot 2 182 yds to right fairway, 78 yds to hole"}, {"n": "3", "pid": "0", "time": "", "putt": "", "t": "S", "prv": "n", "tee": "n", "cup": "n", "from": "OFW", "to": "OGR", "asc": "1", "dist": "2790", "left": "154", "x": "7624.851", "y": "10007.281", "z": "980.787", "club": "CUK", "con": "", "shotText": "Shot 3 78 yds to green, 13 ft to hole"}, {"n": "4", "pid": "0", "time": "", "putt": "1", "t": "S", "prv": "n", "tee": "n", "cup": "n", "from": "OGR", "to": "OGR", "asc": "1", "dist": "151", "left": "3", "x": "7627.629", "y": "9995.043", "z": "980.763", "club": "CUK", "con": "", "shotText": "Shot 4 putt 12 ft 7 in., 3 in. to hole"}, {"n": "5", "pid": "0", "time": "", "putt": "2", "t": "S", "prv": "n", "tee": "n", "cup": "y", "from": "OGR", "to": "hole", "asc": "1", "dist": "3", "left": "0", "x": "0", "y": "0", "z": "0", "club": "CUK", "con": "", "shotText": "Shot 5 in the hole"}]}, {"n": "16", "cNum": "16", "sc": "3", "pDay": "-2", "pTot": "-2", "shots": [{"n": "1", "pid": "0", "time": "", "putt": "", "t": "S", "prv": "n", "tee": "y", "cup": "n", "from": "OTB", "to": "ELF", "asc": "1", "dist": "6736", "left": "308", "x": "8196.182", "y": "9810.600", "z": "984.536", "club": "CUK", "con": "", "shotText": "Shot 1 187 yds to left fairway, 26 ft to hole"}, {"n": "2", "pid": "0", "time": "", "putt": "", "t": "S", "prv": "n", "tee": "n", "cup": "n", "from": "OFW", "to": "OGR", "asc": "1", "dist": "324", "left": "25", "x": "8169.626", "y": "9815.236", "z": "985.255", "club": "CUK", "con": "", "shotText": "Shot 2 27 ft to green, 2 ft to hole"}, {"n": "3", "pid": "0", "time": "", "putt": "1", "t": "S", "prv": "n", "tee": "n", "cup": "y", "from": "OGR", "to": "hole", "asc": "1", "dist": "25", "left": "0", "x": "0", "y": "0", "z": "0", "club": "CUK", "con": "", "shotText": "Shot 3 in the hole"}]}, {"n": "17", "cNum": "17", "sc": "4", "pDay": "-2", "pTot": "-2", "shots": [{"n": "1", "pid": "0", "time": "", "putt": "", "t": "S", "prv": "n", "tee": "y", "cup": "n", "from": "OTB", "to": "ELR", "asc": "1", "dist": "10531", "left": "1560", "x": "8984.226", "y": "9666.928", "z": "977.097", "club": "CDR", "con": "", "shotText": "Shot 1 293 yds to left rough, 43 yds to hole"}, {"n": "2", "pid": "0", "time": "", "putt": "", "t": "S", "prv": "n", "tee": "n", "cup": "n", "from": "ORO", "to": "OGR", "asc": "1", "dist": "1742", "left": "209", "x": "9075.150", "y": "9553.876", "z": "980.953", "club": "CUK", "con": "", "shotText": "Shot 2 48 yds to green, 17 ft to hole"}, {"n": "3", "pid": "0", "time": "", "putt": "1", "t": "S", "prv": "n", "tee": "n", "cup": "n", "from": "OGR", "to": "OGR", "asc": "1", "dist": "249", "left": "36", "x": "9055.917", "y": "9561.743", "z": "980.790", "club": "CUK", "con": "", "shotText": "Shot 3 putt 20 ft 9 in., 3 ft 0 in. to hole"}, {"n": "4", "pid": "0", "time": "", "putt": "2", "t": "S", "prv": "n", "tee": "n", "cup": "y", "from": "OGR", "to": "hole", "asc": "1", "dist": "36", "left": "0", "x": "0", "y": "0", "z": "0", "club": "CUK", "con": "", "shotText": "Shot 4 in the hole"}]}, {"n": "18", "cNum": "18", "sc": "6", "pDay": "0", "pTot": "0", "shots": [{"n": "1", "pid": "0", "time": "", "putt": "", "t": "S", "prv": "n", "tee": "y", "cup": "n", "from": "OTB", "to": "OWA", "asc": "1", "dist": "8563", "left": "7151", "x": "9462.59", "y": "10008.80", "z": "975.00", "club": "CDR", "con": "", "shotText": "Shot 1 238 yds to water, 199 yds to hole"}, {"n": "2", "pid": "0", "time": "", "putt": "", "t": "P", "prv": "n", "tee": "n", "cup": "n", "from": "OUK", "to": "OUK", "asc": "1", "dist": "0", "left": "0", "x": "0", "y": "0", "z": "0", "club": "CUK", "con": "", "shotText": "Shot 2 Penalty"}, {"n": "2", "pid": "0", "time": "", "putt": "", "t": "D", "prv": "n", "tee": "n", "cup": "n", "from": "OUK", "to": "ELR", "asc": "0", "dist": "202", "left": "7142", "x": "9479.095", "y": "10008.468", "z": "978.232", "club": "CUK", "con": "", "shotText": "Drop in left rough, 198 yds to hole"}, {"n": "3", "pid": "0", "time": "", "putt": "", "t": "S", "prv": "n", "tee": "n", "cup": "n", "from": "ORO", "to": "ERF", "asc": "1", "dist": "6161", "left": "1329", "x": "9571.663", "y": "10513.446", "z": "979.979", "club": "CUK", "con": "", "shotText": "Shot 3 171 yds to right fairway, 37 yds to hole"}, {"n": "4", "pid": "0", "time": "", "putt": "", "t": "S", "prv": "n", "tee": "n", "cup": "n", "from": "OFW", "to": "OGR", "asc": "1", "dist": "1119", "left": "213", "x": "9519.546", "y": "10590.653", "z": "984.882", "club": "CUK", "con": "", "shotText": "Shot 4 93 ft to green, 18 ft to hole"}, {"n": "5", "pid": "0", "time": "", "putt": "1", "t": "S", "prv": "n", "tee": "n", "cup": "n", "from": "OGR", "to": "OGR", "asc": "1", "dist": "204", "left": "14", "x": "9506.802", "y": "10601.871", "z": "984.987", "club": "CUK", "con": "", "shotText": "Shot 5 putt 17 ft 0 in., 14 in. to hole"}, {"n": "6", "pid": "0", "time": "", "putt": "2", "t": "S", "prv": "n", "tee": "n", "cup": "y", "from": "OGR", "to": "hole", "asc": "1", "dist": "14", "left": "0", "x": "0", "y": "0", "z": "0", "club": "CUK", "con": "", "shotText": "Shot 6 in the hole"}]}]}, {"n": "2", "holes": [{"n": "1", "cNum": "10", "sc": "4", "pDay": "0", "pTot": "0", "shots": [{"n": "1", "pid": "0", "time": "", "putt": "", "t": "S", "prv": "n", "tee": "y", "cup": "n", "from": "OTB", "to": "ERF", "asc": "1", "dist": "10068", "left": "4636", "x": "8748.111", "y": "9813.581", "z": "979.642", "club": "CFW", "con": "", "shotText": "Shot 1 280 yds to right fairway, 129 yds to hole"}, {"n": "2", "pid": "0", "time": "", "putt": "", "t": "S", "prv": "n", "tee": "n", "cup": "n", "from": "OFW", "to": "OGR", "asc": "1", "dist": "4101", "left": "535", "x": "8406.569", "y": "9825.144", "z": "983.753", "club": "CUK", "con": "", "shotText": "Shot 2 114 yds to green, 45 ft to hole"}, {"n": "3", "pid": "0", "time": "", "putt": "1", "t": "S", "prv": "n", "tee": "n", "cup": "n", "from": "OGR", "to": "OGR", "asc": "1", "dist": "564", "left": "25", "x": "8359.639", "y": "9827.619", "z": "984.071", "club": "CUK", "con": "", "shotText": "Shot 3 putt 47 ft 0 in., 2 ft 1 in. to hole"}, {"n": "4", "pid": "0", "time": "", "putt": "2", "t": "S", "prv": "n", "tee": "n", "cup": "y", "from": "OGR", "to": "hole", "asc": "1", "dist": "25", "left": "0", "x": "0", "y": "0", "z": "0", "club": "CUK", "con": "", "shotText": "Shot 4 in the hole"}]}, {"n": "2", "cNum": "11", "sc": "4", "pDay": "0", "pTot": "0", "shots": [{"n": "1", "pid": "0", "time": "", "putt": "", "t": "S", "prv": "n", "tee": "y", "cup": "n", "from": "OTB", "to": "ERF", "asc": "1", "dist": "9766", "left": "6906", "x": "7572.626", "y": "10295.938", "z": "980.181", "club": "CDR", "con": "", "shotText": "Shot 1 271 yds to right fairway, 192 yds to hole"}, {"n": "2", "pid": "0", "time": "", "putt": "", "t": "S", "prv": "n", "tee": "n", "cup": "n", "from": "OFW", "to": "OGR", "asc": "1", "dist": "7569", "left": "767", "x": "7060.418", "y": "10663.964", "z": "982.823", "club": "CUK", "con": "", "shotText": "Shot 2 210 yds to green, 64 ft to hole"}, {"n": "3", "pid": "0", "time": "", "putt": "1", "t": "S", "prv": "n", "tee": "n", "cup": "n", "from": "OGR", "to": "OGR", "asc": "1", "dist": "718", "left": "63", "x": "7082.672", "y": "10608.448", "z": "981.976", "club": "CUK", "con": "", "shotText": "Shot 3 putt 59 ft 10 in., 5 ft 3 in. to hole"}, {"n": "4", "pid": "0", "time": "", "putt": "2", "t": "S", "prv": "n", "tee": "n", "cup": "y", "from": "OGR", "to": "hole", "asc": "1", "dist": "63", "left": "0", "x": "0", "y": "0", "z": "0", "club": "CUK", "con": "", "shotText": "Shot 4 in the hole"}]}, {"n": "3", "cNum": "12", "sc": "4", "pDay": "1", "pTot": "1", "shots": [{"n": "1", "pid": "0", "time": "", "putt": "", "t": "S", "prv": "n", "tee": "y", "cup": "n", "from": "OTB", "to": "OGR", "asc": "1", "dist": "7238", "left": "519", "x": "6469.559", "y": "10318.359", "z": "979.121", "club": "CUK", "con": "", "shotText": "Shot 1 201 yds to green, 43 ft to hole"}, {"n": "2", "pid": "0", "time": "", "putt": "1", "t": "S", "prv": "n", "tee": "n", "cup": "n", "from": "OGR", "to": "OGR", "asc": "1", "dist": "473", "left": "53", "x": "6457.828", "y": "10280.754", "z": "979.722", "club": "CUK", "con": "", "shotText": "Shot 2 putt 39 ft 5 in., 4 ft 5 in. to hole"}, {"n": "3", "pid": "0", "time": "", "putt": "2", "t": "S", "prv": "n", "tee": "n", "cup": "n", "from": "OGR", "to": "OGR", "asc": "1", "dist": "86", "left": "28", "x": "6459.667", "y": "10273.838", "z": "979.928", "club": "CUK", "con": "", "shotText": "Shot 3 putt 7 ft 2 in., 2 ft 4 in. to hole"}, {"n": "4", "pid": "0", "time": "", "putt": "3", "t": "S", "prv": "n", "tee": "n", "cup": "y", "from": "OGR", "to": "hole", "asc": "1", "dist": "28", "left": "0", "x": "0", "y": "0", "z": "0", "club": "CUK", "con": "", "shotText": "Shot 4 in the hole"}]}, {"n": "4", "cNum": "13", "sc": "4", "pDay": "0", "pTot": "0", "shots": [{"n": "1", "pid": "0", "time": "", "putt": "", "t": "S", "prv": "n", "tee": "y", "cup": "n", "from": "OTB", "to": "ERF", "asc": "1", "dist": "10088", "left": "10058", "x": "5735.298", "y": "10952.489", "z": "981.392", "club": "CDR", "con": "", "shotText": "Shot 1 280 yds to right fairway, 279 yds to hole"}, {"n": "2", "pid": "0", "time": "", "putt": "", "t": "S", "prv": "n", "tee": "n", "cup": "n", "from": "OFW", "to": "EG5", "asc": "1", "dist": "8556", "left": "1605", "x": "5202.649", "y": "11426.526", "z": "981.939", "club": "CUK", "con": "", "shotText": "Shot 2 238 yds to front left green side bunker, 45 yds to hole"}, {"n": "3", "pid": "0", "time": "", "putt": "", "t": "S", "prv": "n", "tee": "n", "cup": "n", "from": "OGS", "to": "OGR", "asc": "1", "dist": "1452", "left": "261", "x": "5165.270", "y": "11541.471", "z": "987.469", "club": "CUK", "con": "", "shotText": "Shot 3 40 yds to green, 22 ft to hole"}, {"n": "4", "pid": "0", "time": "", "putt": "1", "t": "S", "prv": "n", "tee": "n", "cup": "y", "from": "OGR", "to": "hole", "asc": "1", "dist": "261", "left": "0", "x": "0", "y": "0", "z": "0", "club": "CUK", "con": "", "shotText": "Shot 4 in the hole"}]}, {"n": "5", "cNum": "14", "sc": "4", "pDay": "0", "pTot": "0", "shots": [{"n": "1", "pid": "0", "time": "", "putt": "", "t": "S", "prv": "n", "tee": "y", "cup": "n", "from": "OTB", "to": "ELF", "asc": "1", "dist": "10924", "left": "4737", "x": "5481.699", "y": "10577.738", "z": "984.679", "club": "CDR", "con": "", "shotText": "Shot 1 303 yds to left fairway, 132 yds to hole"}, {"n": "2", "pid": "0", "time": "", "putt": "", "t": "S", "prv": "n", "tee": "n", "cup": "n", "from": "OFW", "to": "OGR", "asc": "1", "dist": "4497", "left": "368", "x": "5763.423", "y": "10330.641", "z": "985.827", "club": "CUK", "con": "", "shotText": "Shot 2 125 yds to green, 31 ft to hole"}, {"n": "3", "pid": "0", "time": "", "putt": "1", "t": "S", "prv": "n", "tee": "n", "cup": "n", "from": "OGR", "to": "OGR", "asc": "1", "dist": "398", "left": "25", "x": "5762.336", "y": "10297.507", "z": "986.313", "club": "CUK", "con": "", "shotText": "Shot 3 putt 33 ft 2 in., 2 ft 1 in. to hole"}, {"n": "4", "pid": "0", "time": "", "putt": "2", "t": "S", "prv": "n", "tee": "n", "cup": "y", "from": "OGR", "to": "hole", "asc": "1", "dist": "25", "left": "0", "x": "0", "y": "0", "z": "0", "club": "CUK", "con": "", "shotText": "Shot 4 in the hole"}]}, {"n": "6", "cNum": "15", "sc": "4", "pDay": "-1", "pTot": "-1", "shots": [{"n": "1", "pid": "0", "time": "", "putt": "", "t": "S", "prv": "n", "tee": "y", "cup": "n", "from": "OTB", "to": "ERF", "asc": "1", "dist": "12130", "left": "7467", "x": "6976.025", "y": "10020.385", "z": "979.747", "club": "CDR", "con": "", "shotText": "Shot 1 337 yds to right fairway, 207 yds to hole"}, {"n": "2", "pid": "0", "time": "", "putt": "", "t": "S", "prv": "n", "tee": "n", "cup": "n", "from": "OFW", "to": "OGR", "asc": "1", "dist": "7882", "left": "453", "x": "7632.777", "y": "10012.334", "z": "981.083", "club": "CUK", "con": "", "shotText": "Shot 2 219 yds to green, 38 ft to hole"}, {"n": "3", "pid": "0", "time": "", "putt": "1", "t": "S", "prv": "n", "tee": "n", "cup": "n", "from": "OGR", "to": "OGR", "asc": "1", "dist": "483", "left": "25", "x": "7596.199", "y": "10029.047", "z": "980.021", "club": "CUK", "con": "", "shotText": "Shot 3 putt 40 ft 3 in., 2 ft 1 in. to hole"}, {"n": "4", "pid": "0", "time": "", "putt": "2", "t": "S", "prv": "n", "tee": "n", "cup": "y", "from": "OGR", "to": "hole", "asc": "1", "dist": "25", "left": "0", "x": "0", "y": "0", "z": "0", "club": "CUK", "con": "", "shotText": "Shot 4 in the hole"}]}, {"n": "7", "cNum": "16", "sc": "4", "pDay": "0", "pTot": "0", "shots": [{"n": "1", "pid": "0", "time": "", "putt": "", "t": "S", "prv": "n", "tee": "y", "cup": "n", "from": "OTB", "to": "OGR", "asc": "1", "dist": "6092", "left": "666", "x": "8163.823", "y": "9809.917", "z": "985.088", "club": "CUK", "con": "", "shotText": "Shot 1 169 yds to green, 56 ft to hole"}, {"n": "2", "pid": "0", "time": "", "putt": "1", "t": "S", "prv": "n", "tee": "n", "cup": "n", "from": "OGR", "to": "OGR", "asc": "1", "dist": "716", "left": "45", "x": "8126.931", "y": "9762.998", "z": "984.587", "club": "CUK", "con": "", "shotText": "Shot 2 putt 59 ft 8 in., 3 ft 9 in. to hole"}, {"n": "3", "pid": "0", "time": "", "putt": "2", "t": "S", "prv": "n", "tee": "n", "cup": "n", "from": "OGR", "to": "OGR", "asc": "1", "dist": "70", "left": "20", "x": "8131.070", "y": "9767.073", "z": "984.546", "club": "CUK", "con": "", "shotText": "Shot 3 putt 5 ft 10 in., 20 in. to hole"}, {"n": "4", "pid": "0", "time": "", "putt": "3", "t": "S", "prv": "n", "tee": "n", "cup": "y", "from": "OGR", "to": "hole", "asc": "1", "dist": "20", "left": "0", "x": "0", "y": "0", "z": "0", "club": "CUK", "con": "", "shotText": "Shot 4 in the hole"}]}, {"n": "8", "cNum": "17", "sc": "3", "pDay": "-1", "pTot": "-1", "shots": [{"n": "1", "pid": "0", "time": "", "putt": "", "t": "S", "prv": "n", "tee": "y", "cup": "n", "from": "OTB", "to": "ELR", "asc": "1", "dist": "10780", "left": "878", "x": "9003.989", "y": "9636.841", "z": "977.535", "club": "CDR", "con": "", "shotText": "Shot 1 299 yds to left rough, 73 ft to hole"}, {"n": "2", "pid": "0", "time": "", "putt": "", "t": "S", "prv": "n", "tee": "n", "cup": "n", "from": "ORO", "to": "OGR", "asc": "1", "dist": "990", "left": "187", "x": "9079.020", "y": "9602.708", "z": "980.422", "club": "CUK", "con": "", "shotText": "Shot 2 83 ft to green, 16 ft to hole"}, {"n": "3", "pid": "0", "time": "", "putt": "1", "t": "S", "prv": "n", "tee": "n", "cup": "y", "from": "OGR", "to": "hole", "asc": "1", "dist": "187", "left": "0", "x": "0", "y": "0", "z": "0", "club": "CUK", "con": "", "shotText": "Shot 3 in the hole"}]}, {"n": "9", "cNum": "18", "sc": "3", "pDay": "-2", "pTot": "-2", "shots": [{"n": "1", "pid": "0", "time": "", "putt": "", "t": "S", "prv": "n", "tee": "y", "cup": "n", "from": "OTB", "to": "ELF", "asc": "1", "dist": "10242", "left": "5508", "x": "9577.835", "y": "10126.434", "z": "981.026", "club": "CFW", "con": "", "shotText": "Shot 1 285 yds to left fairway, 153 yds to hole"}, {"n": "2", "pid": "0", "time": "", "putt": "", "t": "S", "prv": "n", "tee": "n", "cup": "n", "from": "OFW", "to": "OGR", "asc": "1", "dist": "5415", "left": "318", "x": "9513.632", "y": "10573.043", "z": "984.493", "club": "CUK", "con": "", "shotText": "Shot 2 150 yds to green, 27 ft to hole"}, {"n": "3", "pid": "0", "time": "", "putt": "1", "t": "S", "prv": "n", "tee": "n", "cup": "y", "from": "OGR", "to": "hole", "asc": "1", "dist": "318", "left": "0", "x": "0", "y": "0", "z": "0", "club": "CUK", "con": "", "shotText": "Shot 3 in the hole"}]}, {"n": "10", "cNum": "1", "sc": "4", "pDay": "-2", "pTot": "-2", "shots": [{"n": "1", "pid": "0", "time": "", "putt": "", "t": "S", "prv": "n", "tee": "y", "cup": "n", "from": "OTB", "to": "ERR", "asc": "1", "dist": "9438", "left": "5946", "x": "8885.678", "y": "11661.697", "z": "1003.641", "club": "CFW", "con": "", "shotText": "Shot 1 262 yds to right rough, 165 yds to hole"}, {"n": "2", "pid": "0", "time": "", "putt": "", "t": "S", "prv": "n", "tee": "n", "cup": "n", "from": "ORO", "to": "ELF", "asc": "1", "dist": "5894", "left": "918", "x": "8524.044", "y": "11994.066", "z": "1001.588", "club": "CUK", "con": "", "shotText": "Shot 2 164 yds to left fairway, 77 ft to hole"}, {"n": "3", "pid": "0", "time": "", "putt": "", "t": "S", "prv": "n", "tee": "n", "cup": "n", "from": "OFW", "to": "OGR", "asc": "1", "dist": "883", "left": "38", "x": "8573.869", "y": "12047.992", "z": "1005.974", "club": "CUK", "con": "", "shotText": "Shot 3 74 ft to green, 3 ft to hole"}, {"n": "4", "pid": "0", "time": "", "putt": "1", "t": "S", "prv": "n", "tee": "n", "cup": "y", "from": "OGR", "to": "hole", "asc": "1", "dist": "38", "left": "0", "x": "0", "y": "0", "z": "0", "club": "CUK", "con": "", "shotText": "Shot 4 in the hole"}]}, {"n": "11", "cNum": "2", "sc": "4", "pDay": "-2", "pTot": "-2", "shots": [{"n": "1", "pid": "0", "time": "", "putt": "", "t": "S", "prv": "n", "tee": "y", "cup": "n", "from": "OTB", "to": "ELF", "asc": "1", "dist": "11401", "left": "3077", "x": "8767.024", "y": "11160.316", "z": "992.095", "club": "CDR", "con": "", "shotText": "Shot 1 317 yds to left fairway, 85 yds to hole"}, {"n": "2", "pid": "0", "time": "", "putt": "", "t": "S", "prv": "n", "tee": "n", "cup": "n", "from": "OFW", "to": "OGR", "asc": "1", "dist": "2883", "left": "216", "x": "8861.223", "y": "10939.333", "z": "988.763", "club": "CUK", "con": "", "shotText": "Shot 2 80 yds to green, 18 ft to hole"}, {"n": "3", "pid": "0", "time": "", "putt": "1", "t": "S", "prv": "n", "tee": "n", "cup": "n", "from": "OGR", "to": "OGR", "asc": "1", "dist": "235", "left": "18", "x": "8876.786", "y": "10927.469", "z": "988.412", "club": "CUK", "con": "", "shotText": "Shot 3 putt 19 ft 7 in., 18 in. to hole"}, {"n": "4", "pid": "0", "time": "", "putt": "2", "t": "S", "prv": "n", "tee": "n", "cup": "y", "from": "OGR", "to": "hole", "asc": "1", "dist": "18", "left": "0", "x": "0", "y": "0", "z": "0", "club": "CUK", "con": "", "shotText": "Shot 4 in the hole"}]}, {"n": "12", "cNum": "3", "sc": "5", "pDay": "-2", "pTot": "-2", "shots": [{"n": "1", "pid": "0", "time": "", "putt": "", "t": "S", "prv": "n", "tee": "y", "cup": "n", "from": "OTB", "to": "ERR", "asc": "1", "dist": "8981", "left": "10985", "x": "7903.250", "y": "11118.921", "z": "987.025", "club": "CDR", "con": "", "shotText": "Shot 1 249 yds to right rough, 305 yds to hole"}, {"n": "2", "pid": "0", "time": "", "putt": "", "t": "S", "prv": "n", "tee": "n", "cup": "n", "from": "ORO", "to": "ERF", "asc": "1", "dist": "5643", "left": "5376", "x": "7442.602", "y": "11213.403", "z": "987.050", "club": "CUK", "con": "", "shotText": "Shot 2 157 yds to right fairway, 149 yds to hole"}, {"n": "3", "pid": "0", "time": "", "putt": "", "t": "S", "prv": "n", "tee": "n", "cup": "n", "from": "OFW", "to": "OGR", "asc": "1", "dist": "5444", "left": "104", "x": "7020.423", "y": "11379.423", "z": "993.869", "club": "CUK", "con": "", "shotText": "Shot 3 151 yds to green, 9 ft to hole"}, {"n": "4", "pid": "0", "time": "", "putt": "1", "t": "S", "prv": "n", "tee": "n", "cup": "n", "from": "OGR", "to": "OGR", "asc": "1", "dist": "143", "left": "34", "x": "7024.273", "y": "11368.151", "z": "993.748", "club": "CUK", "con": "", "shotText": "Shot 4 putt 11 ft 11 in., 2 ft 10 in. to hole"}, {"n": "5", "pid": "0", "time": "", "putt": "2", "t": "S", "prv": "n", "tee": "n", "cup": "y", "from": "OGR", "to": "hole", "asc": "1", "dist": "34", "left": "0", "x": "0", "y": "0", "z": "0", "club": "CUK", "con": "", "shotText": "Shot 5 in the hole"}]}, {"n": "13", "cNum": "4", "sc": "3", "pDay": "-2", "pTot": "-2", "shots": [{"n": "1", "pid": "0", "time": "", "putt": "", "t": "S", "prv": "n", "tee": "y", "cup": "n", "from": "OTB", "to": "OGR", "asc": "1", "dist": "6680", "left": "249", "x": "6898.876", "y": "11955.850", "z": "998.583", "club": "CUK", "con": "", "shotText": "Shot 1 186 yds to green, 21 ft to hole"}, {"n": "2", "pid": "0", "time": "", "putt": "1", "t": "S", "prv": "n", "tee": "n", "cup": "n", "from": "OGR", "to": "OGR", "asc": "1", "dist": "283", "left": "37", "x": "6887.965", "y": "11934.924", "z": "998.452", "club": "CUK", "con": "", "shotText": "Shot 2 putt 23 ft 7 in., 3 ft 1 in. to hole"}, {"n": "3", "pid": "0", "time": "", "putt": "2", "t": "S", "prv": "n", "tee": "n", "cup": "y", "from": "OGR", "to": "hole", "asc": "1", "dist": "37", "left": "0", "x": "0", "y": "0", "z": "0", "club": "CUK", "con": "", "shotText": "Shot 3 in the hole"}]}, {"n": "14", "cNum": "5", "sc": "5", "pDay": "-1", "pTot": "-1", "shots": [{"n": "1", "pid": "0", "time": "", "putt": "", "t": "S", "prv": "n", "tee": "y", "cup": "n", "from": "OTB", "to": "ELR", "asc": "1", "dist": "9535", "left": "6667", "x": "6251.482", "y": "11718.335", "z": "995.505", "club": "CDR", "con": "", "shotText": "Shot 1 265 yds to left rough, 185 yds to hole"}, {"n": "2", "pid": "0", "time": "", "putt": "", "t": "S", "prv": "n", "tee": "n", "cup": "n", "from": "ORO", "to": "ELF", "asc": "1", "dist": "5728", "left": "959", "x": "5835.324", "y": "11484.634", "z": "989.485", "club": "CUK", "con": "", "shotText": "Shot 2 159 yds to left fairway, 80 ft to hole"}, {"n": "3", "pid": "0", "time": "", "putt": "", "t": "S", "prv": "n", "tee": "n", "cup": "n", "from": "OFW", "to": "OGR", "asc": "1", "dist": "852", "left": "113", "x": "5780.622", "y": "11439.424", "z": "992.008", "club": "CUK", "con": "", "shotText": "Shot 3 71 ft to green, 9 ft to hole"}, {"n": "4", "pid": "0", "time": "", "putt": "1", "t": "S", "prv": "n", "tee": "n", "cup": "n", "from": "OGR", "to": "OGR", "asc": "1", "dist": "147", "left": "29", "x": "5773.708", "y": "11429.346", "z": "992.031", "club": "CUK", "con": "", "shotText": "Shot 4 putt 12 ft 3 in., 2 ft 5 in. to hole"}, {"n": "5", "pid": "0", "time": "", "putt": "2", "t": "S", "prv": "n", "tee": "n", "cup": "y", "from": "OGR", "to": "hole", "asc": "1", "dist": "29", "left": "0", "x": "0", "y": "0", "z": "0", "club": "CUK", "con": "", "shotText": "Shot 5 in the hole"}]}, {"n": "15", "cNum": "6", "sc": "4", "pDay": "-1", "pTot": "-1", "shots": [{"n": "1", "pid": "0", "time": "", "putt": "", "t": "S", "prv": "n", "tee": "y", "cup": "n", "from": "OTB", "to": "ELF", "asc": "1", "dist": "11663", "left": "3454", "x": "6288.855", "y": "10808.596", "z": "982.147", "club": "CDR", "con": "", "shotText": "Shot 1 324 yds to left fairway, 96 yds to hole"}, {"n": "2", "pid": "0", "time": "", "putt": "", "t": "S", "prv": "n", "tee": "n", "cup": "n", "from": "OFW", "to": "OGR", "asc": "1", "dist": "3559", "left": "145", "x": "6574.314", "y": "10728.024", "z": "983.739", "club": "CUK", "con": "", "shotText": "Shot 2 99 yds to green, 12 ft to hole"}, {"n": "3", "pid": "0", "time": "", "putt": "1", "t": "S", "prv": "n", "tee": "n", "cup": "n", "from": "OGR", "to": "OGR", "asc": "1", "dist": "191", "left": "41", "x": "6566.532", "y": "10741.938", "z": "983.400", "club": "CUK", "con": "", "shotText": "Shot 3 putt 15 ft 11 in., 3 ft 5 in. to hole"}, {"n": "4", "pid": "0", "time": "", "putt": "2", "t": "S", "prv": "n", "tee": "n", "cup": "y", "from": "OGR", "to": "hole", "asc": "1", "dist": "41", "left": "0", "x": "0", "y": "0", "z": "0", "club": "CUK", "con": "", "shotText": "Shot 4 in the hole"}]}, {"n": "16", "cNum": "7", "sc": "3", "pDay": "-1", "pTot": "-1", "shots": [{"n": "1", "pid": "0", "time": "", "putt": "", "t": "S", "prv": "n", "tee": "y", "cup": "n", "from": "OTB", "to": "OGR", "asc": "1", "dist": "7339", "left": "607", "x": "6344.992", "y": "11463.611", "z": "989.810", "club": "CUK", "con": "", "shotText": "Shot 1 204 yds to green, 51 ft to hole"}, {"n": "2", "pid": "0", "time": "", "putt": "1", "t": "S", "prv": "n", "tee": "n", "cup": "n", "from": "OGR", "to": "OGR", "asc": "1", "dist": "592", "left": "17", "x": "6323.943", "y": "11418.996", "z": "989.169", "club": "CUK", "con": "", "shotText": "Shot 2 putt 49 ft 4 in., 17 in. to hole"}, {"n": "3", "pid": "0", "time": "", "putt": "2", "t": "S", "prv": "n", "tee": "n", "cup": "y", "from": "OGR", "to": "hole", "asc": "1", "dist": "17", "left": "0", "x": "0", "y": "0", "z": "0", "club": "CUK", "con": "", "shotText": "Shot 3 in the hole"}]}, {"n": "17", "cNum": "8", "sc": "4", "pDay": "-1", "pTot": "-1", "shots": [{"n": "1", "pid": "0", "time": "", "putt": "", "t": "S", "prv": "n", "tee": "y", "cup": "n", "from": "OTB", "to": "ERR", "asc": "1", "dist": "11014", "left": "6290", "x": "6998.864", "y": "10929.769", "z": "985.236", "club": "CDR", "con": "", "shotText": "Shot 1 306 yds to right rough, 175 yds to hole"}, {"n": "2", "pid": "0", "time": "", "putt": "", "t": "S", "prv": "n", "tee": "n", "cup": "n", "from": "ORO", "to": "ELR", "asc": "1", "dist": "6242", "left": "845", "x": "7493.093", "y": "10767.501", "z": "983.350", "club": "CUK", "con": "", "shotText": "Shot 2 173 yds to left rough, 70 ft to hole"}, {"n": "3", "pid": "0", "time": "", "putt": "", "t": "S", "prv": "n", "tee": "n", "cup": "n", "from": "ORO", "to": "OGR", "asc": "1", "dist": "811", "left": "56", "x": "7475.015", "y": "10702.424", "z": "981.210", "club": "CUK", "con": "", "shotText": "Shot 3 68 ft to green, 5 ft to hole"}, {"n": "4", "pid": "0", "time": "", "putt": "1", "t": "S", "prv": "n", "tee": "n", "cup": "y", "from": "OGR", "to": "hole", "asc": "1", "dist": "56", "left": "0", "x": "0", "y": "0", "z": "0", "club": "CUK", "con": "", "shotText": "Shot 4 in the hole"}]}, {"n": "18", "cNum": "9", "sc": "4", "pDay": "-1", "pTot": "-1", "shots": [{"n": "1", "pid": "0", "time": "", "putt": "", "t": "S", "prv": "n", "tee": "y", "cup": "n", "from": "OTB", "to": "ELF", "asc": "1", "dist": "11510", "left": "5126", "x": "8397.585", "y": "10769.753", "z": "985.937", "club": "CDR", "con": "", "shotText": "Shot 1 320 yds to left fairway, 142 yds to hole"}, {"n": "2", "pid": "0", "time": "", "putt": "", "t": "S", "prv": "n", "tee": "n", "cup": "n", "from": "OFW", "to": "ELF", "asc": "1", "dist": "5586", "left": "457", "x": "8845.320", "y": "10642.527", "z": "984.055", "club": "CUK", "con": "", "shotText": "Shot 2 155 yds to left fairway, 38 ft to hole"}, {"n": "3", "pid": "0", "time": "", "putt": "", "t": "S", "prv": "n", "tee": "n", "cup": "n", "from": "OFW", "to": "OGR", "asc": "1", "dist": "342", "left": "124", "x": "8817.459", "y": "10647.207", "z": "987.854", "club": "CUK", "con": "", "shotText": "Shot 3 29 ft to green, 10 ft to hole"}, {"n": "4", "pid": "0", "time": "", "putt": "1", "t": "S", "prv": "n", "tee": "n", "cup": "y", "from": "OGR", "to": "hole", "asc": "1", "dist": "124", "left": "0", "x": "0", "y": "0", "z": "0", "club": "CUK", "con": "", "shotText": "Shot 4 in the hole"}]}]}, {"n": "3", "holes": [{"n": "1", "cNum": "10", "sc": "4", "pDay": "0", "pTot": "-1", "shots": [{"n": "1", "pid": "0", "time": "", "putt": "", "t": "S", "prv": "n", "tee": "y", "cup": "n", "from": "OTB", "to": "ELF", "asc": "1", "dist": "9860", "left": "5248", "x": "8810.385", "y": "9787.054", "z": "980.964", "club": "CFW", "con": "", "shotText": "Shot 1 274 yds to left fairway, 146 yds to hole"}, {"n": "2", "pid": "0", "time": "", "putt": "", "t": "S", "prv": "n", "tee": "n", "cup": "n", "from": "OFW", "to": "OGR", "asc": "1", "dist": "5408", "left": "351", "x": "8359.937", "y": "9800.594", "z": "984.378", "club": "CUK", "con": "", "shotText": "Shot 2 150 yds to green, 29 ft to hole"}, {"n": "3", "pid": "0", "time": "", "putt": "1", "t": "S", "prv": "n", "tee": "n", "cup": "n", "from": "OGR", "to": "OGR", "asc": "1", "dist": "294", "left": "58", "x": "8370.320", "y": "9778.435", "z": "984.224", "club": "CUK", "con": "", "shotText": "Shot 3 putt 24 ft 6 in., 4 ft 10 in. to hole"}, {"n": "4", "pid": "0", "time": "", "putt": "2", "t": "S", "prv": "n", "tee": "n", "cup": "y", "from": "OGR", "to": "hole", "asc": "1", "dist": "58", "left": "0", "x": "0", "y": "0", "z": "0", "club": "CUK", "con": "", "shotText": "Shot 4 in the hole"}]}, {"n": "2", "cNum": "11", "sc": "4", "pDay": "0", "pTot": "-1", "shots": [{"n": "1", "pid": "0", "time": "", "putt": "", "t": "S", "prv": "n", "tee": "y", "cup": "n", "from": "OTB", "to": "ELF", "asc": "1", "dist": "11104", "left": "5305", "x": "7381.979", "y": "10318.588", "z": "979.098", "club": "CFW", "con": "", "shotText": "Shot 1 308 yds to left fairway, 147 yds to hole"}, {"n": "2", "pid": "0", "time": "", "putt": "", "t": "S", "prv": "n", "tee": "n", "cup": "n", "from": "OFW", "to": "OGR", "asc": "1", "dist": "5310", "left": "79", "x": "7083.707", "y": "10645.448", "z": "982.366", "club": "CUK", "con": "", "shotText": "Shot 2 148 yds to green, 7 ft to hole"}, {"n": "3", "pid": "0", "time": "", "putt": "1", "t": "S", "prv": "n", "tee": "n", "cup": "n", "from": "OGR", "to": "OGR", "asc": "1", "dist": "95", "left": "11", "x": "7089.959", "y": "10650.278", "z": "982.505", "club": "CUK", "con": "", "shotText": "Shot 3 putt 7 ft 11 in., 11 in. to hole"}, {"n": "4", "pid": "0", "time": "", "putt": "2", "t": "S", "prv": "n", "tee": "n", "cup": "y", "from": "OGR", "to": "hole", "asc": "1", "dist": "11", "left": "0", "x": "0", "y": "0", "z": "0", "club": "CUK", "con": "", "shotText": "Shot 4 in the hole"}]}, {"n": "3", "cNum": "12", "sc": "4", "pDay": "1", "pTot": "0", "shots": [{"n": "1", "pid": "0", "time": "", "putt": "", "t": "S", "prv": "n", "tee": "y", "cup": "n", "from": "OTB", "to": "OGR", "asc": "1", "dist": "7084", "left": "488", "x": "6470.029", "y": "10301.650", "z": "979.796", "club": "CUK", "con": "", "shotText": "Shot 1 197 yds to green, 41 ft to hole"}, {"n": "2", "pid": "0", "time": "", "putt": "1", "t": "S", "prv": "n", "tee": "n", "cup": "n", "from": "OGR", "to": "OGR", "asc": "1", "dist": "546", "left": "58", "x": "6513.251", "y": "10287.496", "z": "980.337", "club": "CUK", "con": "", "shotText": "Shot 2 putt 45 ft 6 in., 4 ft 10 in. to hole"}, {"n": "3", "pid": "0", "time": "", "putt": "2", "t": "S", "prv": "n", "tee": "n", "cup": "n", "from": "OGR", "to": "OGR", "asc": "1", "dist": "79", "left": "17", "x": "6508.677", "y": "10292.238", "z": "980.278", "club": "CUK", "con": "", "shotText": "Shot 3 putt 6 ft 7 in., 17 in. to hole"}, {"n": "4", "pid": "0", "time": "", "putt": "3", "t": "S", "prv": "n", "tee": "n", "cup": "y", "from": "OGR", "to": "hole", "asc": "1", "dist": "17", "left": "0", "x": "0", "y": "0", "z": "0", "club": "CUK", "con": "", "shotText": "Shot 4 in the hole"}]}, {"n": "4", "cNum": "13", "sc": "3", "pDay": "-1", "pTot": "-2", "shots": [{"n": "1", "pid": "0", "time": "", "putt": "", "t": "S", "prv": "n", "tee": "y", "cup": "n", "from": "OTB", "to": "ERF", "asc": "1", "dist": "10033", "left": "9892", "x": "5720.106", "y": "10930.736", "z": "981.891", "club": "CDR", "con": "", "shotText": "Shot 1 279 yds to right fairway, 275 yds to hole"}, {"n": "2", "pid": "0", "time": "", "putt": "", "t": "S", "prv": "n", "tee": "n", "cup": "n", "from": "OFW", "to": "OGR", "asc": "1", "dist": "9961", "left": "123", "x": "5188.586", "y": "11568.280", "z": "987.934", "club": "CUK", "con": "", "shotText": "Shot 2 277 yds to green, 10 ft to hole"}, {"n": "3", "pid": "0", "time": "", "putt": "1", "t": "S", "prv": "n", "tee": "n", "cup": "y", "from": "OGR", "to": "hole", "asc": "1", "dist": "123", "left": "0", "x": "0", "y": "0", "z": "0", "club": "CUK", "con": "", "shotText": "Shot 3 in the hole"}]}, {"n": "5", "cNum": "14", "sc": "4", "pDay": "-1", "pTot": "-2", "shots": [{"n": "1", "pid": "0", "time": "", "putt": "", "t": "S", "prv": "n", "tee": "y", "cup": "n", "from": "OTB", "to": "ELF", "asc": "1", "dist": "10805", "left": "4684", "x": "5470.703", "y": "10579.397", "z": "984.842", "club": "CDR", "con": "", "shotText": "Shot 1 300 yds to left fairway, 130 yds to hole"}, {"n": "2", "pid": "0", "time": "", "putt": "", "t": "S", "prv": "n", "tee": "n", "cup": "n", "from": "OFW", "to": "OGR", "asc": "1", "dist": "4901", "left": "357", "x": "5774.873", "y": "10306.858", "z": "986.327", "club": "CUK", "con": "", "shotText": "Shot 2 136 yds to green, 30 ft to hole"}, {"n": "3", "pid": "0", "time": "", "putt": "1", "t": "S", "prv": "n", "tee": "n", "cup": "n", "from": "OGR", "to": "OGR", "asc": "1", "dist": "369", "left": "7", "x": "5776.429", "y": "10337.593", "z": "986.082", "club": "CUK", "con": "", "shotText": "Shot 3 putt 30 ft 9 in., 7 in. to hole"}, {"n": "4", "pid": "0", "time": "", "putt": "2", "t": "S", "prv": "n", "tee": "n", "cup": "y", "from": "OGR", "to": "hole", "asc": "1", "dist": "7", "left": "0", "x": "0", "y": "0", "z": "0", "club": "CUK", "con": "", "shotText": "Shot 4 in the hole"}]}, {"n": "6", "cNum": "15", "sc": "5", "pDay": "-1", "pTot": "-2", "shots": [{"n": "1", "pid": "0", "time": "", "putt": "", "t": "S", "prv": "n", "tee": "y", "cup": "n", "from": "OTB", "to": "ELR", "asc": "1", "dist": "10793", "left": "9961", "x": "6856.876", "y": "10144.487", "z": "977.811", "club": "CDR", "con": "", "shotText": "Shot 1 300 yds to left rough, 277 yds to hole"}, {"n": "2", "pid": "0", "time": "", "putt": "", "t": "S", "prv": "n", "tee": "n", "cup": "n", "from": "ORO", "to": "ERF", "asc": "1", "dist": "6510", "left": "3579", "x": "7375.346", "y": "9984.771", "z": "977.348", "club": "CUK", "con": "", "shotText": "Shot 2 181 yds to right fairway, 99 yds to hole"}, {"n": "3", "pid": "0", "time": "", "putt": "", "t": "S", "prv": "n", "tee": "n", "cup": "n", "from": "OFW", "to": "ERF", "asc": "1", "dist": "3988", "left": "404", "x": "7707.443", "y": "9996.042", "z": "979.400", "club": "CUK", "con": "", "shotText": "Shot 3 111 yds to right fairway, 34 ft to hole"}, {"n": "4", "pid": "0", "time": "", "putt": "", "t": "S", "prv": "n", "tee": "n", "cup": "n", "from": "OFW", "to": "OGR", "asc": "1", "dist": "278", "left": "129", "x": "7684.493", "y": "9993.746", "z": "981.357", "club": "CUK", "con": "", "shotText": "Shot 4 23 ft to green, 11 ft to hole"}, {"n": "5", "pid": "0", "time": "", "putt": "1", "t": "S", "prv": "n", "tee": "n", "cup": "y", "from": "OGR", "to": "hole", "asc": "1", "dist": "129", "left": "0", "x": "0", "y": "0", "z": "0", "club": "CUK", "con": "", "shotText": "Shot 5 in the hole"}]}, {"n": "7", "cNum": "16", "sc": "3", "pDay": "-1", "pTot": "-2", "shots": [{"n": "1", "pid": "0", "time": "", "putt": "", "t": "S", "prv": "n", "tee": "y", "cup": "n", "from": "OTB", "to": "OGR", "asc": "1", "dist": "4528", "left": "171", "x": "8106.079", "y": "9802.956", "z": "984.028", "club": "CUK", "con": "", "shotText": "Shot 1 126 yds to green, 14 ft to hole"}, {"n": "2", "pid": "0", "time": "", "putt": "1", "t": "S", "prv": "n", "tee": "n", "cup": "n", "from": "OGR", "to": "OGR", "asc": "1", "dist": "211", "left": "35", "x": "8119.375", "y": "9791.487", "z": "984.577", "club": "CUK", "con": "", "shotText": "Shot 2 putt 17 ft 7 in., 2 ft 11 in. to hole"}, {"n": "3", "pid": "0", "time": "", "putt": "2", "t": "S", "prv": "n", "tee": "n", "cup": "y", "from": "OGR", "to": "hole", "asc": "1", "dist": "35", "left": "0", "x": "0", "y": "0", "z": "0", "club": "CUK", "con": "", "shotText": "Shot 3 in the hole"}]}, {"n": "8", "cNum": "17", "sc": "3", "pDay": "-2", "pTot": "-3", "shots": [{"n": "1", "pid": "0", "time": "", "putt": "", "t": "S", "prv": "n", "tee": "y", "cup": "n", "from": "OTB", "to": "ELF", "asc": "1", "dist": "11104", "left": "1229", "x": "9037.288", "y": "9614.464", "z": "978.880", "club": "CDR", "con": "", "shotText": "Shot 1 308 yds to left fairway, 34 yds to hole"}, {"n": "2", "pid": "0", "time": "", "putt": "", "t": "S", "prv": "n", "tee": "n", "cup": "n", "from": "OFW", "to": "OGR", "asc": "1", "dist": "1090", "left": "140", "x": "9112.183", "y": "9563.131", "z": "982.231", "club": "CUK", "con": "", "shotText": "Shot 2 91 ft to green, 12 ft to hole"}, {"n": "3", "pid": "0", "time": "", "putt": "1", "t": "S", "prv": "n", "tee": "n", "cup": "y", "from": "OGR", "to": "hole", "asc": "1", "dist": "140", "left": "0", "x": "0", "y": "0", "z": "0", "club": "CUK", "con": "", "shotText": "Shot 3 in the hole"}]}, {"n": "9", "cNum": "18", "sc": "5", "pDay": "-1", "pTot": "-2", "shots": [{"n": "1", "pid": "0", "time": "", "putt": "", "t": "S", "prv": "n", "tee": "y", "cup": "n", "from": "OTB", "to": "OST", "asc": "1", "dist": "9420", "left": "6475", "x": "9647.708", "y": "10028.667", "z": "983.410", "club": "CFW", "con": "", "shotText": "Shot 1 262 yds to fairway bunker, 180 yds to hole"}, {"n": "2", "pid": "0", "time": "", "putt": "", "t": "S", "prv": "n", "tee": "n", "cup": "n", "from": "OST", "to": "ELF", "asc": "1", "dist": "6024", "left": "575", "x": "9507.338", "y": "10510.622", "z": "979.722", "club": "CUK", "con": "", "shotText": "Shot 2 167 yds to left fairway, 48 ft to hole"}, {"n": "3", "pid": "0", "time": "", "putt": "", "t": "S", "prv": "n", "tee": "n", "cup": "n", "from": "OFW", "to": "OGR", "asc": "1", "dist": "325", "left": "256", "x": "9514.894", "y": "10536.380", "z": "983.351", "club": "CUK", "con": "", "shotText": "Shot 3 27 ft to green, 21 ft to hole"}, {"n": "4", "pid": "0", "time": "", "putt": "1", "t": "S", "prv": "n", "tee": "n", "cup": "n", "from": "OGR", "to": "OGR", "asc": "1", "dist": "284", "left": "24", "x": "9526.898", "y": "10556.803", "z": "984.258", "club": "CUK", "con": "", "shotText": "Shot 4 putt 23 ft 8 in., 2 ft 0 in. to hole"}, {"n": "5", "pid": "0", "time": "", "putt": "2", "t": "S", "prv": "n", "tee": "n", "cup": "y", "from": "OGR", "to": "hole", "asc": "1", "dist": "24", "left": "0", "x": "0", "y": "0", "z": "0", "club": "CUK", "con": "", "shotText": "Shot 5 in the hole"}]}, {"n": "10", "cNum": "1", "sc": "4", "pDay": "-1", "pTot": "-2", "shots": [{"n": "1", "pid": "0", "time": "", "putt": "", "t": "S", "prv": "n", "tee": "y", "cup": "n", "from": "OTB", "to": "ERR", "asc": "1", "dist": "9589", "left": "6071", "x": "8883.958", "y": "11670.123", "z": "1003.784", "club": "CFW", "con": "", "shotText": "Shot 1 266 yds to right rough, 169 yds to hole"}, {"n": "2", "pid": "0", "time": "", "putt": "", "t": "S", "prv": "n", "tee": "n", "cup": "n", "from": "ORO", "to": "OGR", "asc": "1", "dist": "5834", "left": "410", "x": "8537.564", "y": "12011.277", "z": "1004.222", "club": "CUK", "con": "", "shotText": "Shot 2 162 yds to green, 34 ft to hole"}, {"n": "3", "pid": "0", "time": "", "putt": "1", "t": "S", "prv": "n", "tee": "n", "cup": "n", "from": "OGR", "to": "OGR", "asc": "1", "dist": "420", "left": "11", "x": "8543.102", "y": "12045.802", "z": "1005.825", "club": "CUK", "con": "", "shotText": "Shot 3 putt 35 ft 0 in., 11 in. to hole"}, {"n": "4", "pid": "0", "time": "", "putt": "2", "t": "S", "prv": "n", "tee": "n", "cup": "y", "from": "OGR", "to": "hole", "asc": "1", "dist": "11", "left": "0", "x": "0", "y": "0", "z": "0", "club": "CUK", "con": "", "shotText": "Shot 4 in the hole"}]}, {"n": "11", "cNum": "2", "sc": "4", "pDay": "-1", "pTot": "-2", "shots": [{"n": "1", "pid": "0", "time": "", "putt": "", "t": "S", "prv": "n", "tee": "y", "cup": "n", "from": "OTB", "to": "ELR", "asc": "1", "dist": "10095", "left": "4815", "x": "8756.657", "y": "11277.207", "z": "1002.370", "club": "CDR", "con": "", "shotText": "Shot 1 280 yds to left rough, 134 yds to hole"}, {"n": "2", "pid": "0", "time": "", "putt": "", "t": "S", "prv": "n", "tee": "n", "cup": "n", "from": "ORO", "to": "OGR", "asc": "1", "dist": "4360", "left": "553", "x": "8870.284", "y": "10932.388", "z": "988.485", "club": "CUK", "con": "", "shotText": "Shot 2 121 yds to green, 46 ft to hole"}, {"n": "3", "pid": "0", "time": "", "putt": "1", "t": "S", "prv": "n", "tee": "n", "cup": "n", "from": "OGR", "to": "OGR", "asc": "1", "dist": "490", "left": "66", "x": "8858.864", "y": "10893.161", "z": "988.907", "club": "CUK", "con": "", "shotText": "Shot 3 putt 40 ft 10 in., 5 ft 6 in. to hole"}, {"n": "4", "pid": "0", "time": "", "putt": "2", "t": "S", "prv": "n", "tee": "n", "cup": "y", "from": "OGR", "to": "hole", "asc": "1", "dist": "66", "left": "0", "x": "0", "y": "0", "z": "0", "club": "CUK", "con": "", "shotText": "Shot 4 in the hole"}]}, {"n": "12", "cNum": "3", "sc": "4", "pDay": "-2", "pTot": "-3", "shots": [{"n": "1", "pid": "0", "time": "", "putt": "", "t": "S", "prv": "n", "tee": "y", "cup": "n", "from": "OTB", "to": "ELR", "asc": "1", "dist": "10253", "left": "9332", "x": "7776.120", "y": "11031.117", "z": "987.432", "club": "CDR", "con": "", "shotText": "Shot 1 285 yds to left rough, 259 yds to hole"}, {"n": "2", "pid": "0", "time": "", "putt": "", "t": "S", "prv": "n", "tee": "n", "cup": "n", "from": "ORO", "to": "ELI", "asc": "1", "dist": "4759", "left": "4639", "x": "7401.047", "y": "11159.871", "z": "987.979", "club": "CUK", "con": "", "shotText": "Shot 2 132 yds to left intermediate, 129 yds to hole"}, {"n": "3", "pid": "0", "time": "", "putt": "", "t": "S", "prv": "n", "tee": "n", "cup": "n", "from": "OIR", "to": "OGR", "asc": "1", "dist": "4733", "left": "135", "x": "7063.646", "y": "11364.177", "z": "991.928", "club": "CUK", "con": "", "shotText": "Shot 3 131 yds to green, 11 ft to hole"}, {"n": "4", "pid": "0", "time": "", "putt": "1", "t": "S", "prv": "n", "tee": "n", "cup": "y", "from": "OGR", "to": "hole", "asc": "1", "dist": "135", "left": "0", "x": "0", "y": "0", "z": "0", "club": "CUK", "con": "", "shotText": "Shot 4 in the hole"}]}, {"n": "13", "cNum": "4", "sc": "3", "pDay": "-2", "pTot": "-3", "shots": [{"n": "1", "pid": "0", "time": "", "putt": "", "t": "S", "prv": "n", "tee": "y", "cup": "n", "from": "OTB", "to": "OGR", "asc": "1", "dist": "6037", "left": "377", "x": "6878.267", "y": "11917.734", "z": "998.350", "club": "CUK", "con": "", "shotText": "Shot 1 168 yds to green, 31 ft to hole"}, {"n": "2", "pid": "0", "time": "", "putt": "1", "t": "S", "prv": "n", "tee": "n", "cup": "n", "from": "OGR", "to": "OGR", "asc": "1", "dist": "351", "left": "29", "x": "6855.417", "y": "11935.922", "z": "999.297", "club": "CUK", "con": "", "shotText": "Shot 2 putt 29 ft 3 in., 2 ft 5 in. to hole"}, {"n": "3", "pid": "0", "time": "", "putt": "2", "t": "S", "prv": "n", "tee": "n", "cup": "y", "from": "OGR", "to": "hole", "asc": "1", "dist": "29", "left": "0", "x": "0", "y": "0", "z": "0", "club": "CUK", "con": "", "shotText": "Shot 3 in the hole"}]}, {"n": "14", "cNum": "5", "sc": "4", "pDay": "-2", "pTot": "-3", "shots": [{"n": "1", "pid": "0", "time": "", "putt": "", "t": "S", "prv": "n", "tee": "y", "cup": "n", "from": "OTB", "to": "ELF", "asc": "1", "dist": "11109", "left": "4884", "x": "6147.041", "y": "11667.648", "z": "992.955", "club": "CDR", "con": "", "shotText": "Shot 1 309 yds to left fairway, 136 yds to hole"}, {"n": "2", "pid": "0", "time": "", "putt": "", "t": "S", "prv": "n", "tee": "n", "cup": "n", "from": "OFW", "to": "OGR", "asc": "1", "dist": "4967", "left": "218", "x": "5786.310", "y": "11464.620", "z": "991.724", "club": "CUK", "con": "", "shotText": "Shot 2 138 yds to green, 18 ft to hole"}, {"n": "3", "pid": "0", "time": "", "putt": "1", "t": "S", "prv": "n", "tee": "n", "cup": "n", "from": "OGR", "to": "OGR", "asc": "1", "dist": "285", "left": "62", "x": "5784.464", "y": "11488.304", "z": "991.575", "club": "CUK", "con": "", "shotText": "Shot 3 putt 23 ft 9 in., 5 ft 2 in. to hole"}, {"n": "4", "pid": "0", "time": "", "putt": "2", "t": "S", "prv": "n", "tee": "n", "cup": "y", "from": "OGR", "to": "hole", "asc": "1", "dist": "62", "left": "0", "x": "0", "y": "0", "z": "0", "club": "CUK", "con": "", "shotText": "Shot 4 in the hole"}]}, {"n": "15", "cNum": "6", "sc": "4", "pDay": "-2", "pTot": "-3", "shots": [{"n": "1", "pid": "0", "time": "", "putt": "", "t": "S", "prv": "n", "tee": "y", "cup": "n", "from": "OTB", "to": "ELF", "asc": "1", "dist": "12122", "left": "3271", "x": "6339.838", "y": "10791.703", "z": "983.110", "club": "CDR", "con": "", "shotText": "Shot 1 337 yds to left fairway, 91 yds to hole"}, {"n": "2", "pid": "0", "time": "", "putt": "", "t": "S", "prv": "n", "tee": "n", "cup": "n", "from": "OFW", "to": "OGR", "asc": "1", "dist": "3070", "left": "368", "x": "6593.759", "y": "10760.682", "z": "984.017", "club": "CUK", "con": "", "shotText": "Shot 2 85 yds to green, 31 ft to hole"}, {"n": "3", "pid": "0", "time": "", "putt": "1", "t": "S", "prv": "n", "tee": "n", "cup": "n", "from": "OGR", "to": "OGR", "asc": "1", "dist": "324", "left": "44", "x": "6604.834", "y": "10736.062", "z": "985.099", "club": "CUK", "con": "", "shotText": "Shot 3 putt 27 ft 0 in., 3 ft 8 in. to hole"}, {"n": "4", "pid": "0", "time": "", "putt": "2", "t": "S", "prv": "n", "tee": "n", "cup": "y", "from": "OGR", "to": "hole", "asc": "1", "dist": "44", "left": "0", "x": "0", "y": "0", "z": "0", "club": "CUK", "con": "", "shotText": "Shot 4 in the hole"}]}, {"n": "16", "cNum": "7", "sc": "3", "pDay": "-2", "pTot": "-3", "shots": [{"n": "1", "pid": "0", "time": "", "putt": "", "t": "S", "prv": "n", "tee": "y", "cup": "n", "from": "OTB", "to": "EG2", "asc": "1", "dist": "7528", "left": "1190", "x": "6390.868", "y": "11454.668", "z": "985.671", "club": "CUK", "con": "", "shotText": "Shot 1 209 yds to right green side bunker, 99 ft to hole"}, {"n": "2", "pid": "0", "time": "", "putt": "", "t": "S", "prv": "n", "tee": "n", "cup": "n", "from": "OGS", "to": "OGR", "asc": "1", "dist": "1176", "left": "14", "x": "6293.680", "y": "11442.792", "z": "989.639", "club": "CUK", "con": "", "shotText": "Shot 2 98 ft to green, 14 in. to hole"}, {"n": "3", "pid": "0", "time": "", "putt": "1", "t": "S", "prv": "n", "tee": "n", "cup": "y", "from": "OGR", "to": "hole", "asc": "1", "dist": "14", "left": "0", "x": "0", "y": "0", "z": "0", "club": "CUK", "con": "", "shotText": "Shot 3 in the hole"}]}, {"n": "17", "cNum": "8", "sc": "4", "pDay": "-2", "pTot": "-3", "shots": [{"n": "1", "pid": "0", "time": "", "putt": "", "t": "S", "prv": "n", "tee": "y", "cup": "n", "from": "OTB", "to": "ELR", "asc": "1", "dist": "10710", "left": "5709", "x": "7069.274", "y": "11034.451", "z": "979.503", "club": "CDR", "con": "", "shotText": "Shot 1 298 yds to left rough, 159 yds to hole"}, {"n": "2", "pid": "0", "time": "", "putt": "", "t": "S", "prv": "n", "tee": "n", "cup": "n", "from": "ORO", "to": "ELR", "asc": "1", "dist": "5953", "left": "564", "x": "7486.797", "y": "10766.567", "z": "982.419", "club": "CUK", "con": "", "shotText": "Shot 2 165 yds to left rough, 47 ft to hole"}, {"n": "3", "pid": "0", "time": "", "putt": "", "t": "S", "prv": "n", "tee": "n", "cup": "n", "from": "ORO", "to": "OGR", "asc": "1", "dist": "699", "left": "131", "x": "7436.710", "y": "10736.839", "z": "980.279", "club": "CUK", "con": "", "shotText": "Shot 3 58 ft to green, 11 ft to hole"}, {"n": "4", "pid": "0", "time": "", "putt": "1", "t": "S", "prv": "n", "tee": "n", "cup": "y", "from": "OGR", "to": "hole", "asc": "1", "dist": "131", "left": "0", "x": "0", "y": "0", "z": "0", "club": "CUK", "con": "", "shotText": "Shot 4 in the hole"}]}, {"n": "18", "cNum": "9", "sc": "4", "pDay": "-2", "pTot": "-3", "shots": [{"n": "1", "pid": "0", "time": "", "putt": "", "t": "S", "prv": "n", "tee": "y", "cup": "n", "from": "OTB", "to": "ELF", "asc": "1", "dist": "11643", "left": "5117", "x": "8402.659", "y": "10794.279", "z": "986.527", "club": "CDR", "con": "", "shotText": "Shot 1 323 yds to left fairway, 142 yds to hole"}, {"n": "2", "pid": "0", "time": "", "putt": "", "t": "S", "prv": "n", "tee": "n", "cup": "n", "from": "OFW", "to": "OGR", "asc": "1", "dist": "4934", "left": "260", "x": "8774.337", "y": "10618.427", "z": "987.585", "club": "CUK", "con": "", "shotText": "Shot 2 137 yds to green, 22 ft to hole"}, {"n": "3", "pid": "0", "time": "", "putt": "1", "t": "S", "prv": "n", "tee": "n", "cup": "n", "from": "OGR", "to": "OGR", "asc": "1", "dist": "276", "left": "11", "x": "8781.947", "y": "10596.713", "z": "987.513", "club": "CUK", "con": "", "shotText": "Shot 3 putt 23 ft 0 in., 11 in. to hole"}, {"n": "4", "pid": "0", "time": "", "putt": "2", "t": "S", "prv": "n", "tee": "n", "cup": "y", "from": "OGR", "to": "hole", "asc": "1", "dist": "11", "left": "0", "x": "0", "y": "0", "z": "0", "club": "CUK", "con": "", "shotText": "Shot 4 in the hole"}]}]}, {"n": "4", "holes": [{"n": "1", "cNum": "10", "sc": "3", "pDay": "-1", "pTot": "-4", "shots": [{"n": "1", "pid": "0", "time": "", "putt": "", "t": "S", "prv": "n", "tee": "y", "cup": "n", "from": "OTB", "to": "ELF", "asc": "1", "dist": "9781", "left": "5572", "x": "8809.883", "y": "9783.326", "z": "980.967", "club": "CFW", "con": "", "shotText": "Shot 1 272 yds to left fairway, 155 yds to hole"}, {"n": "2", "pid": "0", "time": "", "putt": "", "t": "S", "prv": "n", "tee": "n", "cup": "n", "from": "OFW", "to": "OGR", "asc": "1", "dist": "5503", "left": "96", "x": "8351.404", "y": "9790.602", "z": "984.126", "club": "CUK", "con": "", "shotText": "Shot 2 153 yds to green, 8 ft to hole"}, {"n": "3", "pid": "0", "time": "", "putt": "1", "t": "S", "prv": "n", "tee": "n", "cup": "y", "from": "OGR", "to": "hole", "asc": "1", "dist": "96", "left": "0", "x": "0", "y": "0", "z": "0", "club": "CUK", "con": "", "shotText": "Shot 3 in the hole"}]}, {"n": "2", "cNum": "11", "sc": "4", "pDay": "-1", "pTot": "-4", "shots": [{"n": "1", "pid": "0", "time": "", "putt": "", "t": "S", "prv": "n", "tee": "y", "cup": "n", "from": "OTB", "to": "ERF", "asc": "1", "dist": "10644", "left": "6273", "x": "7498.080", "y": "10320.567", "z": "980.590", "club": "CDR", "con": "", "shotText": "Shot 1 296 yds to right fairway, 174 yds to hole"}, {"n": "2", "pid": "0", "time": "", "putt": "", "t": "S", "prv": "n", "tee": "n", "cup": "n", "from": "OFW", "to": "OGR", "asc": "1", "dist": "6415", "left": "515", "x": "7075.614", "y": "10648.178", "z": "982.347", "club": "CUK", "con": "", "shotText": "Shot 2 178 yds to green, 43 ft to hole"}, {"n": "3", "pid": "0", "time": "", "putt": "1", "t": "S", "prv": "n", "tee": "n", "cup": "n", "from": "OGR", "to": "OGR", "asc": "1", "dist": "502", "left": "19", "x": "7060.293", "y": "10609.259", "z": "981.755", "club": "CUK", "con": "", "shotText": "Shot 3 putt 41 ft 10 in., 19 in. to hole"}, {"n": "4", "pid": "0", "time": "", "putt": "2", "t": "S", "prv": "n", "tee": "n", "cup": "y", "from": "OGR", "to": "hole", "asc": "1", "dist": "19", "left": "0", "x": "0", "y": "0", "z": "0", "club": "CUK", "con": "", "shotText": "Shot 4 in the hole"}]}, {"n": "3", "cNum": "12", "sc": "3", "pDay": "-1", "pTot": "-4", "shots": [{"n": "1", "pid": "0", "time": "", "putt": "", "t": "S", "prv": "n", "tee": "y", "cup": "n", "from": "OTB", "to": "OGR", "asc": "1", "dist": "6979", "left": "386", "x": "6497.127", "y": "10298.094", "z": "980.155", "club": "CUK", "con": "", "shotText": "Shot 1 194 yds to green, 32 ft to hole"}, {"n": "2", "pid": "0", "time": "", "putt": "1", "t": "S", "prv": "n", "tee": "n", "cup": "n", "from": "OGR", "to": "OGR", "asc": "1", "dist": "406", "left": "23", "x": "6493.031", "y": "10331.639", "z": "979.818", "club": "CUK", "con": "", "shotText": "Shot 2 putt 33 ft 10 in., 23 in. to hole"}, {"n": "3", "pid": "0", "time": "", "putt": "2", "t": "S", "prv": "n", "tee": "n", "cup": "y", "from": "OGR", "to": "hole", "asc": "1", "dist": "23", "left": "0", "x": "0", "y": "0", "z": "0", "club": "CUK", "con": "", "shotText": "Shot 3 in the hole"}]}, {"n": "4", "cNum": "13", "sc": "5", "pDay": "-1", "pTot": "-4", "shots": [{"n": "1", "pid": "0", "time": "", "putt": "", "t": "S", "prv": "n", "tee": "y", "cup": "n", "from": "OTB", "to": "ONA", "asc": "1", "dist": "11029", "left": "8680", "x": "5628.354", "y": "10951.233", "z": "981.591", "club": "CDR", "con": "", "shotText": "Shot 1 306 yds to native area, 241 yds to hole"}, {"n": "2", "pid": "0", "time": "", "putt": "", "t": "S", "prv": "n", "tee": "n", "cup": "n", "from": "ONA", "to": "ELR", "asc": "1", "dist": "4109", "left": "4571", "x": "5413.117", "y": "11217.593", "z": "982.672", "club": "CUK", "con": "", "shotText": "Shot 2 114 yds to left rough, 127 yds to hole"}, {"n": "3", "pid": "0", "time": "", "putt": "", "t": "S", "prv": "n", "tee": "n", "cup": "n", "from": "ORO", "to": "OGR", "asc": "1", "dist": "5113", "left": "540", "x": "5149.269", "y": "11552.119", "z": "987.664", "club": "CUK", "con": "", "shotText": "Shot 3 142 yds to green, 45 ft to hole"}, {"n": "4", "pid": "0", "time": "", "putt": "1", "t": "S", "prv": "n", "tee": "n", "cup": "n", "from": "OGR", "to": "OGR", "asc": "1", "dist": "517", "left": "28", "x": "5171.143", "y": "11515.024", "z": "987.044", "club": "CUK", "con": "", "shotText": "Shot 4 putt 43 ft 1 in., 2 ft 4 in. to hole"}, {"n": "5", "pid": "0", "time": "", "putt": "2", "t": "S", "prv": "n", "tee": "n", "cup": "y", "from": "OGR", "to": "hole", "asc": "1", "dist": "28", "left": "0", "x": "0", "y": "0", "z": "0", "club": "CUK", "con": "", "shotText": "Shot 5 in the hole"}]}, {"n": "5", "cNum": "14", "sc": "4", "pDay": "-1", "pTot": "-4", "shots": [{"n": "1", "pid": "0", "time": "", "putt": "", "t": "S", "prv": "n", "tee": "y", "cup": "n", "from": "OTB", "to": "ELF", "asc": "1", "dist": "10357", "left": "5942", "x": "5446.993", "y": "10615.434", "z": "985.687", "club": "CDR", "con": "", "shotText": "Shot 1 288 yds to left fairway, 165 yds to hole"}, {"n": "2", "pid": "0", "time": "", "putt": "", "t": "S", "prv": "n", "tee": "n", "cup": "n", "from": "OFW", "to": "OGR", "asc": "1", "dist": "5363", "left": "685", "x": "5797.788", "y": "10338.521", "z": "986.236", "club": "CUK", "con": "", "shotText": "Shot 2 149 yds to green, 57 ft to hole"}, {"n": "3", "pid": "0", "time": "", "putt": "1", "t": "S", "prv": "n", "tee": "n", "cup": "n", "from": "OGR", "to": "OGR", "asc": "1", "dist": "680", "left": "10", "x": "5814.167", "y": "10284.265", "z": "987.127", "club": "CUK", "con": "", "shotText": "Shot 3 putt 56 ft 8 in., 10 in. to hole"}, {"n": "4", "pid": "0", "time": "", "putt": "2", "t": "S", "prv": "n", "tee": "n", "cup": "y", "from": "OGR", "to": "hole", "asc": "1", "dist": "10", "left": "0", "x": "0", "y": "0", "z": "0", "club": "CUK", "con": "", "shotText": "Shot 4 in the hole"}]}, {"n": "6", "cNum": "15", "sc": "4", "pDay": "-2", "pTot": "-5", "shots": [{"n": "1", "pid": "0", "time": "", "putt": "", "t": "S", "prv": "n", "tee": "y", "cup": "n", "from": "OTB", "to": "ELF", "asc": "1", "dist": "11019", "left": "9342", "x": "6869.357", "y": "10086.956", "z": "979.624", "club": "CDR", "con": "", "shotText": "Shot 1 306 yds to left fairway, 260 yds to hole"}, {"n": "2", "pid": "0", "time": "", "putt": "", "t": "S", "prv": "n", "tee": "n", "cup": "n", "from": "OFW", "to": "ERF", "asc": "1", "dist": "6648", "left": "2789", "x": "7416.401", "y": "9999.696", "z": "977.024", "club": "CUK", "con": "", "shotText": "Shot 2 185 yds to right fairway, 77 yds to hole"}, {"n": "3", "pid": "0", "time": "", "putt": "", "t": "S", "prv": "n", "tee": "n", "cup": "n", "from": "OFW", "to": "EG6", "asc": "1", "dist": "2915", "left": "420", "x": "7649.085", "y": "10069.488", "z": "977.651", "club": "CUK", "con": "", "shotText": "Shot 3 81 yds to left green side bunker, 35 ft to hole"}, {"n": "4", "pid": "0", "time": "", "putt": "", "t": "S", "prv": "n", "tee": "n", "cup": "y", "from": "OGS", "to": "hole", "asc": "1", "dist": "420", "left": "0", "x": "0", "y": "0", "z": "0", "club": "CUK", "con": "", "shotText": "Shot 4 in the hole"}]}, {"n": "7", "cNum": "16", "sc": "2", "pDay": "-3", "pTot": "-6", "shots": [{"n": "1", "pid": "0", "time": "", "putt": "", "t": "S", "prv": "n", "tee": "y", "cup": "n", "from": "OTB", "to": "OGR", "asc": "1", "dist": "5916", "left": "116", "x": "8139.908", "y": "9789.009", "z": "985.083", "club": "CUK", "con": "", "shotText": "Shot 1 164 yds to green, 10 ft to hole"}, {"n": "2", "pid": "0", "time": "", "putt": "1", "t": "S", "prv": "n", "tee": "n", "cup": "y", "from": "OGR", "to": "hole", "asc": "1", "dist": "116", "left": "0", "x": "0", "y": "0", "z": "0", "club": "CUK", "con": "", "shotText": "Shot 2 in the hole"}]}, {"n": "8", "cNum": "17", "sc": "4", "pDay": "-3", "pTot": "-6", "shots": [{"n": "1", "pid": "0", "time": "", "putt": "", "t": "S", "prv": "n", "tee": "y", "cup": "n", "from": "OTB", "to": "ELR", "asc": "1", "dist": "10798", "left": "1716", "x": "9017.870", "y": "9636.810", "z": "977.143", "club": "CDR", "con": "", "shotText": "Shot 1 300 yds to left rough, 48 yds to hole"}, {"n": "2", "pid": "0", "time": "", "putt": "", "t": "S", "prv": "n", "tee": "n", "cup": "n", "from": "ORO", "to": "OGR", "asc": "1", "dist": "1351", "left": "675", "x": "9110.910", "y": "9573.591", "z": "981.565", "club": "CUK", "con": "", "shotText": "Shot 2 38 yds to green, 56 ft to hole"}, {"n": "3", "pid": "0", "time": "", "putt": "1", "t": "S", "prv": "n", "tee": "n", "cup": "n", "from": "OGR", "to": "OGR", "asc": "1", "dist": "689", "left": "73", "x": "9161.619", "y": "9600.602", "z": "981.148", "club": "CUK", "con": "", "shotText": "Shot 3 putt 57 ft 5 in., 6 ft 1 in. to hole"}, {"n": "4", "pid": "0", "time": "", "putt": "2", "t": "S", "prv": "n", "tee": "n", "cup": "y", "from": "OGR", "to": "hole", "asc": "1", "dist": "73", "left": "0", "x": "0", "y": "0", "z": "0", "club": "CUK", "con": "", "shotText": "Shot 4 in the hole"}]}, {"n": "9", "cNum": "18", "sc": "4", "pDay": "-3", "pTot": "-6", "shots": [{"n": "1", "pid": "0", "time": "", "putt": "", "t": "S", "prv": "n", "tee": "y", "cup": "n", "from": "OTB", "to": "ERF", "asc": "1", "dist": "11145", "left": "5241", "x": "9578.329", "y": "10198.298", "z": "979.979", "club": "CDR", "con": "", "shotText": "Shot 1 310 yds to right fairway, 146 yds to hole"}, {"n": "2", "pid": "0", "time": "", "putt": "", "t": "S", "prv": "n", "tee": "n", "cup": "n", "from": "OFW", "to": "OGR", "asc": "1", "dist": "5370", "left": "129", "x": "9552.475", "y": "10645.039", "z": "986.099", "club": "CUK", "con": "", "shotText": "Shot 2 149 yds to green, 11 ft to hole"}, {"n": "3", "pid": "0", "time": "", "putt": "1", "t": "S", "prv": "n", "tee": "n", "cup": "n", "from": "OGR", "to": "OGR", "asc": "1", "dist": "136", "left": "5", "x": "9555.542", "y": "10634.114", "z": "985.801", "club": "CUK", "con": "", "shotText": "Shot 3 putt 11 ft 4 in., 5 in. to hole"}, {"n": "4", "pid": "0", "time": "", "putt": "2", "t": "S", "prv": "n", "tee": "n", "cup": "y", "from": "OGR", "to": "hole", "asc": "1", "dist": "5", "left": "0", "x": "0", "y": "0", "z": "0", "club": "CUK", "con": "", "shotText": "Shot 4 in the hole"}]}, {"n": "10", "cNum": "1", "sc": "3", "pDay": "-4", "pTot": "-7", "shots": [{"n": "1", "pid": "0", "time": "", "putt": "", "t": "S", "prv": "n", "tee": "y", "cup": "n", "from": "OTB", "to": "ELR", "asc": "1", "dist": "9401", "left": "4867", "x": "8760.354", "y": "11616.710", "z": "1000.363", "club": "CFW", "con": "", "shotText": "Shot 1 261 yds to left rough, 135 yds to hole"}, {"n": "2", "pid": "0", "time": "", "putt": "", "t": "S", "prv": "n", "tee": "n", "cup": "n", "from": "ORO", "to": "OGR", "asc": "1", "dist": "4849", "left": "154", "x": "8587.052", "y": "11981.720", "z": "1005.151", "club": "CUK", "con": "", "shotText": "Shot 2 135 yds to green, 13 ft to hole"}, {"n": "3", "pid": "0", "time": "", "putt": "1", "t": "S", "prv": "n", "tee": "n", "cup": "y", "from": "OGR", "to": "hole", "asc": "1", "dist": "154", "left": "0", "x": "0", "y": "0", "z": "0", "club": "CUK", "con": "", "shotText": "Shot 3 in the hole"}]}, {"n": "11", "cNum": "2", "sc": "4", "pDay": "-4", "pTot": "-7", "shots": [{"n": "1", "pid": "0", "time": "", "putt": "", "t": "S", "prv": "n", "tee": "y", "cup": "n", "from": "OTB", "to": "ERF", "asc": "1", "dist": "10321", "left": "4966", "x": "8707.524", "y": "11238.975", "z": "997.687", "club": "CDR", "con": "", "shotText": "Shot 1 287 yds to right fairway, 138 yds to hole"}, {"n": "2", "pid": "0", "time": "", "putt": "", "t": "S", "prv": "n", "tee": "n", "cup": "n", "from": "OFW", "to": "ELF", "asc": "1", "dist": "4759", "left": "442", "x": "8916.255", "y": "10901.934", "z": "986.523", "club": "CUK", "con": "", "shotText": "Shot 2 132 yds to left fairway, 37 ft to hole"}, {"n": "3", "pid": "0", "time": "", "putt": "", "t": "S", "prv": "n", "tee": "n", "cup": "n", "from": "OFW", "to": "OGR", "asc": "1", "dist": "446", "left": "9", "x": "8895.602", "y": "10871.130", "z": "988.565", "club": "CUK", "con": "", "shotText": "Shot 3 37 ft to green, 9 in. to hole"}, {"n": "4", "pid": "0", "time": "", "putt": "1", "t": "S", "prv": "n", "tee": "n", "cup": "y", "from": "OGR", "to": "hole", "asc": "1", "dist": "9", "left": "0", "x": "0", "y": "0", "z": "0", "club": "CUK", "con": "", "shotText": "Shot 4 in the hole"}]}, {"n": "12", "cNum": "3", "sc": "5", "pDay": "-4", "pTot": "-7", "shots": [{"n": "1", "pid": "0", "time": "", "putt": "", "t": "S", "prv": "n", "tee": "y", "cup": "n", "from": "OTB", "to": "OST", "asc": "1", "dist": "10744", "left": "9880", "x": "7730.642", "y": "11055.589", "z": "986.584", "club": "CDR", "con": "", "shotText": "Shot 1 298 yds to fairway bunker, 274 yds to hole"}, {"n": "2", "pid": "0", "time": "", "putt": "", "t": "S", "prv": "n", "tee": "n", "cup": "n", "from": "OST", "to": "ERF", "asc": "1", "dist": "5216", "left": "4665", "x": "7328.741", "y": "11221.172", "z": "987.182", "club": "CUK", "con": "", "shotText": "Shot 2 145 yds to right fairway, 130 yds to hole"}, {"n": "3", "pid": "0", "time": "", "putt": "", "t": "S", "prv": "n", "tee": "n", "cup": "n", "from": "OFW", "to": "OGR", "asc": "1", "dist": "4791", "left": "123", "x": "6964.531", "y": "11384.577", "z": "994.654", "club": "CUK", "con": "", "shotText": "Shot 3 133 yds to green, 10 ft to hole"}, {"n": "4", "pid": "0", "time": "", "putt": "1", "t": "S", "prv": "n", "tee": "n", "cup": "n", "from": "OGR", "to": "OGR", "asc": "1", "dist": "151", "left": "25", "x": "6974.426", "y": "11376.787", "z": "994.454", "club": "CUK", "con": "", "shotText": "Shot 4 putt 12 ft 7 in., 2 ft 1 in. to hole"}, {"n": "5", "pid": "0", "time": "", "putt": "2", "t": "S", "prv": "n", "tee": "n", "cup": "y", "from": "OGR", "to": "hole", "asc": "1", "dist": "25", "left": "0", "x": "0", "y": "0", "z": "0", "club": "CUK", "con": "", "shotText": "Shot 5 in the hole"}]}, {"n": "13", "cNum": "4", "sc": "3", "pDay": "-4", "pTot": "-7", "shots": [{"n": "1", "pid": "0", "time": "", "putt": "", "t": "S", "prv": "n", "tee": "y", "cup": "n", "from": "OTB", "to": "OGR", "asc": "1", "dist": "5927", "left": "154", "x": "6893.023", "y": "11900.006", "z": "997.795", "club": "CUK", "con": "", "shotText": "Shot 1 165 yds to green, 13 ft to hole"}, {"n": "2", "pid": "0", "time": "", "putt": "1", "t": "S", "prv": "n", "tee": "n", "cup": "n", "from": "OGR", "to": "OGR", "asc": "1", "dist": "180", "left": "28", "x": "6889.339", "y": "11885.473", "z": "997.220", "club": "CUK", "con": "", "shotText": "Shot 2 putt 15 ft 0 in., 2 ft 4 in. to hole"}, {"n": "3", "pid": "0", "time": "", "putt": "2", "t": "S", "prv": "n", "tee": "n", "cup": "y", "from": "OGR", "to": "hole", "asc": "1", "dist": "28", "left": "0", "x": "0", "y": "0", "z": "0", "club": "CUK", "con": "", "shotText": "Shot 3 in the hole"}]}, {"n": "14", "cNum": "5", "sc": "4", "pDay": "-4", "pTot": "-7", "shots": [{"n": "1", "pid": "0", "time": "", "putt": "", "t": "S", "prv": "n", "tee": "y", "cup": "n", "from": "OTB", "to": "ONA", "asc": "1", "dist": "10656", "left": "6271", "x": "6217.250", "y": "11642.000", "z": "992.300", "club": "CDR", "con": "", "shotText": "Shot 1 296 yds to native area, 174 yds to hole"}, {"n": "2", "pid": "0", "time": "", "putt": "", "t": "S", "prv": "n", "tee": "n", "cup": "n", "from": "ONA", "to": "OGR", "asc": "1", "dist": "5860", "left": "790", "x": "5758.853", "y": "11473.554", "z": "991.844", "club": "CUK", "con": "", "shotText": "Shot 2 163 yds to green, 66 ft to hole"}, {"n": "3", "pid": "0", "time": "", "putt": "1", "t": "S", "prv": "n", "tee": "n", "cup": "n", "from": "OGR", "to": "OGR", "asc": "1", "dist": "839", "left": "57", "x": "5752.306", "y": "11403.985", "z": "992.566", "club": "CUK", "con": "", "shotText": "Shot 3 putt 69 ft 11 in., 4 ft 9 in. to hole"}, {"n": "4", "pid": "0", "time": "", "putt": "2", "t": "S", "prv": "n", "tee": "n", "cup": "y", "from": "OGR", "to": "hole", "asc": "1", "dist": "57", "left": "0", "x": "0", "y": "0", "z": "0", "club": "CUK", "con": "", "shotText": "Shot 4 in the hole"}]}, {"n": "15", "cNum": "6", "sc": "4", "pDay": "-4", "pTot": "-7", "shots": [{"n": "1", "pid": "0", "time": "", "putt": "", "t": "S", "prv": "n", "tee": "y", "cup": "n", "from": "OTB", "to": "ERR", "asc": "1", "dist": "10822", "left": "5440", "x": "6164.397", "y": "10776.913", "z": "982.951", "club": "CDR", "con": "", "shotText": "Shot 1 301 yds to right rough, 151 yds to hole"}, {"n": "2", "pid": "0", "time": "", "putt": "", "t": "S", "prv": "n", "tee": "n", "cup": "n", "from": "ORO", "to": "OGR", "asc": "1", "dist": "4882", "left": "606", "x": "6570.360", "y": "10749.703", "z": "983.423", "club": "CUK", "con": "", "shotText": "Shot 2 136 yds to green, 51 ft to hole"}, {"n": "3", "pid": "0", "time": "", "putt": "1", "t": "S", "prv": "n", "tee": "n", "cup": "n", "from": "OGR", "to": "OGR", "asc": "1", "dist": "559", "left": "47", "x": "6614.069", "y": "10765.796", "z": "984.417", "club": "CUK", "con": "", "shotText": "Shot 3 putt 46 ft 7 in., 3 ft 11 in. to hole"}, {"n": "4", "pid": "0", "time": "", "putt": "2", "t": "S", "prv": "n", "tee": "n", "cup": "y", "from": "OGR", "to": "hole", "asc": "1", "dist": "47", "left": "0", "x": "0", "y": "0", "z": "0", "club": "CUK", "con": "", "shotText": "Shot 4 in the hole"}]}, {"n": "16", "cNum": "7", "sc": "3", "pDay": "-4", "pTot": "-7", "shots": [{"n": "1", "pid": "0", "time": "", "putt": "", "t": "S", "prv": "n", "tee": "y", "cup": "n", "from": "OTB", "to": "OGR", "asc": "1", "dist": "8134", "left": "723", "x": "6297.008", "y": "11457.658", "z": "989.865", "club": "CUK", "con": "", "shotText": "Shot 1 226 yds to green, 60 ft to hole"}, {"n": "2", "pid": "0", "time": "", "putt": "1", "t": "S", "prv": "n", "tee": "n", "cup": "n", "from": "OGR", "to": "OGR", "asc": "1", "dist": "783", "left": "56", "x": "6357.227", "y": "11482.832", "z": "989.930", "club": "CUK", "con": "", "shotText": "Shot 2 putt 65 ft 3 in., 4 ft 8 in. to hole"}, {"n": "3", "pid": "0", "time": "", "putt": "2", "t": "S", "prv": "n", "tee": "n", "cup": "y", "from": "OGR", "to": "hole", "asc": "1", "dist": "56", "left": "0", "x": "0", "y": "0", "z": "0", "club": "CUK", "con": "", "shotText": "Shot 3 in the hole"}]}, {"n": "17", "cNum": "8", "sc": "4", "pDay": "-4", "pTot": "-7", "shots": [{"n": "1", "pid": "0", "time": "", "putt": "", "t": "S", "prv": "n", "tee": "y", "cup": "n", "from": "OTB", "to": "ERF", "asc": "1", "dist": "10644", "left": "7132", "x": "6986.257", "y": "10976.031", "z": "982.761", "club": "CDR", "con": "", "shotText": "Shot 1 296 yds to right fairway, 198 yds to hole"}, {"n": "2", "pid": "0", "time": "", "putt": "", "t": "S", "prv": "n", "tee": "n", "cup": "n", "from": "OFW", "to": "OGR", "asc": "1", "dist": "6826", "left": "305", "x": "7487.861", "y": "10707.705", "z": "981.374", "club": "CUK", "con": "", "shotText": "Shot 2 190 yds to green, 25 ft to hole"}, {"n": "3", "pid": "0", "time": "", "putt": "1", "t": "S", "prv": "n", "tee": "n", "cup": "n", "from": "OGR", "to": "OGR", "asc": "1", "dist": "323", "left": "21", "x": "7510.690", "y": "10693.465", "z": "981.861", "club": "CUK", "con": "", "shotText": "Shot 3 putt 26 ft 11 in., 21 in. to hole"}, {"n": "4", "pid": "0", "time": "", "putt": "2", "t": "S", "prv": "n", "tee": "n", "cup": "y", "from": "OGR", "to": "hole", "asc": "1", "dist": "21", "left": "0", "x": "0", "y": "0", "z": "0", "club": "CUK", "con": "", "shotText": "Shot 4 in the hole"}]}, {"n": "18", "cNum": "9", "sc": "4", "pDay": "-4", "pTot": "-7", "shots": [{"n": "1", "pid": "0", "time": "", "putt": "", "t": "S", "prv": "n", "tee": "y", "cup": "n", "from": "OTB", "to": "ERF", "asc": "1", "dist": "10781", "left": "5463", "x": "8328.423", "y": "10744.057", "z": "985.804", "club": "CDR", "con": "", "shotText": "Shot 1 299 yds to right fairway, 152 yds to hole"}, {"n": "2", "pid": "0", "time": "", "putt": "", "t": "S", "prv": "n", "tee": "n", "cup": "n", "from": "OFW", "to": "OGR", "asc": "1", "dist": "5701", "left": "233", "x": "8789.532", "y": "10629.636", "z": "988.045", "club": "CUK", "con": "", "shotText": "Shot 2 158 yds to green, 19 ft to hole"}, {"n": "3", "pid": "0", "time": "", "putt": "1", "t": "S", "prv": "n", "tee": "n", "cup": "n", "from": "OGR", "to": "OGR", "asc": "1", "dist": "243", "left": "6", "x": "8770.185", "y": "10635.681", "z": "987.703", "club": "CUK", "con": "", "shotText": "Shot 3 putt 20 ft 3 in., 6 in. to hole"}, {"n": "4", "pid": "0", "time": "", "putt": "2", "t": "S", "prv": "n", "tee": "n", "cup": "y", "from": "OGR", "to": "hole", "asc": "1", "dist": "6", "left": "0", "x": "0", "y": "0", "z": "0", "club": "CUK", "con": "", "shotText": "Shot 4 in the hole"}]}]}]}}