{"p": {"msgId": "221887", "id": "26758", "rnds": [{"n": "1", "holes": [{"n": "1", "cNum": "1", "sc": "3", "pDay": "-1", "pTot": "-1", "shots": [{"n": "1", "pid": "0", "time": "", "putt": "", "t": "S", "prv": "n", "tee": "y", "cup": "n", "from": "OTB", "to": "ELF", "asc": "1", "dist": "10537", "left": "3707", "x": "8771.572", "y": "11724.635", "z": "1003.514", "club": "CFW", "con": "", "shotText": "Shot 1 293 yds to left fairway, 103 yds to hole"}, {"n": "2", "pid": "0", "time": "", "putt": "", "t": "S", "prv": "n", "tee": "n", "cup": "n", "from": "OFW", "to": "OGR", "asc": "1", "dist": "4029", "left": "318", "x": "8567.894", "y": "11991.535", "z": "1004.642", "club": "CUK", "con": "", "shotText": "Shot 2 112 yds to green, 27 ft to hole"}, {"n": "3", "pid": "0", "time": "", "putt": "1", "t": "S", "prv": "n", "tee": "n", "cup": "y", "from": "OGR", "to": "hole", "asc": "1", "dist": "318", "left": "0", "x": "0", "y": "0", "z": "0", "club": "CUK", "con": "", "shotText": "Shot 3 in the hole"}]}, {"n": "2", "cNum": "2", "sc": "3", "pDay": "-2", "pTot": "-2", "shots": [{"n": "1", "pid": "0", "time": "", "putt": "", "t": "S", "prv": "n", "tee": "y", "cup": "n", "from": "OTB", "to": "ELF", "asc": "1", "dist": "9748", "left": "5297", "x": "8712.272", "y": "11283.736", "z": "999.987", "club": "CDR", "con": "", "shotText": "Shot 1 271 yds to left fairway, 147 yds to hole"}, {"n": "2", "pid": "0", "time": "", "putt": "", "t": "S", "prv": "n", "tee": "n", "cup": "n", "from": "OFW", "to": "OGR", "asc": "1", "dist": "5317", "left": "178", "x": "8890.307", "y": "10878.188", "z": "988.576", "club": "CUK", "con": "", "shotText": "Shot 2 148 yds to green, 15 ft to hole"}, {"n": "3", "pid": "0", "time": "", "putt": "1", "t": "S", "prv": "n", "tee": "n", "cup": "y", "from": "OGR", "to": "hole", "asc": "1", "dist": "178", "left": "0", "x": "0", "y": "0", "z": "0", "club": "CUK", "con": "", "shotText": "Shot 3 in the hole"}]}, {"n": "3", "cNum": "3", "sc": "5", "pDay": "-2", "pTot": "-2", "shots": [{"n": "1", "pid": "0", "time": "", "putt": "", "t": "S", "prv": "n", "tee": "y", "cup": "n", "from": "OTB", "to": "ELF", "asc": "1", "dist": "10855", "left": "8654", "x": "7742.632", "y": "11084.587", "z": "987.795", "club": "CDR", "con": "", "shotText": "Shot 1 302 yds to left fairway, 240 yds to hole"}, {"n": "2", "pid": "0", "time": "", "putt": "", "t": "S", "prv": "n", "tee": "n", "cup": "n", "from": "OFW", "to": "ERI", "asc": "1", "dist": "8810", "left": "1074", "x": "7096.831", "y": "11433.803", "z": "990.294", "club": "CUK", "con": "", "shotText": "Shot 2 245 yds to right intermediate, 90 ft to hole"}, {"n": "3", "pid": "0", "time": "", "putt": "", "t": "S", "prv": "n", "tee": "n", "cup": "n", "from": "OIR", "to": "ERF", "asc": "1", "dist": "603", "left": "504", "x": "7072.207", "y": "11390.052", "z": "992.654", "club": "CUK", "con": "", "shotText": "Shot 3 50 ft to right fairway, 42 ft to hole"}, {"n": "4", "pid": "0", "time": "", "putt": "", "t": "S", "prv": "n", "tee": "n", "cup": "n", "from": "OCO", "to": "OGR", "asc": "1", "dist": "533", "left": "24", "x": "7070.879", "y": "11345.651", "z": "991.548", "club": "CUK", "con": "", "shotText": "Shot 4 44 ft to green, 2 ft to hole"}, {"n": "5", "pid": "0", "time": "", "putt": "1", "t": "S", "prv": "n", "tee": "n", "cup": "y", "from": "OGR", "to": "hole", "asc": "1", "dist": "24", "left": "0", "x": "0", "y": "0", "z": "0", "club": "CUK", "con": "", "shotText": "Shot 5 in the hole"}]}, {"n": "4", "cNum": "4", "sc": "3", "pDay": "-2", "pTot": "-2", "shots": [{"n": "1", "pid": "0", "time": "", "putt": "", "t": "S", "prv": "n", "tee": "y", "cup": "n", "from": "OTB", "to": "OGR", "asc": "1", "dist": "5860", "left": "286", "x": "6888.551", "y": "11898.895", "z": "997.629", "club": "CUK", "con": "", "shotText": "Shot 1 163 yds to green, 24 ft to hole"}, {"n": "2", "pid": "0", "time": "", "putt": "1", "t": "S", "prv": "n", "tee": "n", "cup": "n", "from": "OGR", "to": "OGR", "asc": "1", "dist": "298", "left": "10", "x": "6870.026", "y": "11882.401", "z": "997.340", "club": "CUK", "con": "", "shotText": "Shot 2 putt 24 ft 10 in., 10 in. to hole"}, {"n": "3", "pid": "0", "time": "", "putt": "2", "t": "S", "prv": "n", "tee": "n", "cup": "y", "from": "OGR", "to": "hole", "asc": "1", "dist": "10", "left": "0", "x": "0", "y": "0", "z": "0", "club": "CUK", "con": "", "shotText": "Shot 3 in the hole"}]}, {"n": "5", "cNum": "5", "sc": "4", "pDay": "-2", "pTot": "-2", "shots": [{"n": "1", "pid": "0", "time": "", "putt": "", "t": "S", "prv": "n", "tee": "y", "cup": "n", "from": "OTB", "to": "ERR", "asc": "1", "dist": "10509", "left": "6118", "x": "6125.756", "y": "11770.462", "z": "996.083", "club": "CDR", "con": "", "shotText": "Shot 1 292 yds to right rough, 170 yds to hole"}, {"n": "2", "pid": "0", "time": "", "putt": "", "t": "S", "prv": "n", "tee": "n", "cup": "n", "from": "ORO", "to": "ERF", "asc": "1", "dist": "6381", "left": "284", "x": "5711.661", "y": "11436.887", "z": "992.880", "club": "CUK", "con": "", "shotText": "Shot 2 177 yds to right fairway, 24 ft to hole"}, {"n": "3", "pid": "0", "time": "", "putt": "", "t": "S", "prv": "n", "tee": "n", "cup": "n", "from": "OCO", "to": "OGR", "asc": "1", "dist": "313", "left": "24", "x": "5722.880", "y": "11460.424", "z": "992.249", "club": "CUK", "con": "", "shotText": "Shot 3 26 ft to green, 2 ft to hole"}, {"n": "4", "pid": "0", "time": "", "putt": "1", "t": "S", "prv": "n", "tee": "n", "cup": "y", "from": "OGR", "to": "hole", "asc": "1", "dist": "24", "left": "0", "x": "0", "y": "0", "z": "0", "club": "CUK", "con": "", "shotText": "Shot 4 in the hole"}]}, {"n": "6", "cNum": "6", "sc": "4", "pDay": "-2", "pTot": "-2", "shots": [{"n": "1", "pid": "0", "time": "", "putt": "", "t": "S", "prv": "n", "tee": "y", "cup": "n", "from": "OTB", "to": "ERF", "asc": "1", "dist": "9987", "left": "5889", "x": "6128.267", "y": "10852.371", "z": "982.131", "club": "CDR", "con": "", "shotText": "Shot 1 277 yds to right fairway, 164 yds to hole"}, {"n": "2", "pid": "0", "time": "", "putt": "", "t": "S", "prv": "n", "tee": "n", "cup": "n", "from": "OFW", "to": "OGR", "asc": "1", "dist": "6211", "left": "323", "x": "6643.189", "y": "10800.356", "z": "985.686", "club": "CUK", "con": "", "shotText": "Shot 2 173 yds to green, 27 ft to hole"}, {"n": "3", "pid": "0", "time": "", "putt": "1", "t": "S", "prv": "n", "tee": "n", "cup": "n", "from": "OGR", "to": "OGR", "asc": "1", "dist": "358", "left": "32", "x": "6614.328", "y": "10808.027", "z": "985.384", "club": "CUK", "con": "", "shotText": "Shot 3 putt 29 ft 10 in., 2 ft 8 in. to hole"}, {"n": "4", "pid": "0", "time": "", "putt": "2", "t": "S", "prv": "n", "tee": "n", "cup": "y", "from": "OGR", "to": "hole", "asc": "1", "dist": "32", "left": "0", "x": "0", "y": "0", "z": "0", "club": "CUK", "con": "", "shotText": "Shot 4 in the hole"}]}, {"n": "7", "cNum": "7", "sc": "2", "pDay": "-3", "pTot": "-3", "shots": [{"n": "1", "pid": "0", "time": "", "putt": "", "t": "S", "prv": "n", "tee": "y", "cup": "n", "from": "OTB", "to": "OGR", "asc": "1", "dist": "7268", "left": "110", "x": "6343.576", "y": "11461.782", "z": "989.787", "club": "CUK", "con": "", "shotText": "Shot 1 202 yds to green, 9 ft to hole"}, {"n": "2", "pid": "0", "time": "", "putt": "1", "t": "S", "prv": "n", "tee": "n", "cup": "y", "from": "OGR", "to": "hole", "asc": "1", "dist": "110", "left": "0", "x": "0", "y": "0", "z": "0", "club": "CUK", "con": "", "shotText": "Shot 2 in the hole"}]}, {"n": "8", "cNum": "8", "sc": "4", "pDay": "-3", "pTot": "-3", "shots": [{"n": "1", "pid": "0", "time": "", "putt": "", "t": "S", "prv": "n", "tee": "y", "cup": "n", "from": "OTB", "to": "ERR", "asc": "1", "dist": "10594", "left": "6730", "x": "6955.496", "y": "10935.974", "z": "984.411", "club": "CDR", "con": "", "shotText": "Shot 1 294 yds to right rough, 187 yds to hole"}, {"n": "2", "pid": "0", "time": "", "putt": "", "t": "S", "prv": "n", "tee": "n", "cup": "n", "from": "ORO", "to": "OGR", "asc": "1", "dist": "7015", "left": "287", "x": "7504.198", "y": "10734.219", "z": "981.792", "club": "CUK", "con": "", "shotText": "Shot 2 195 yds to green, 24 ft to hole"}, {"n": "3", "pid": "0", "time": "", "putt": "1", "t": "S", "prv": "n", "tee": "n", "cup": "n", "from": "OGR", "to": "OGR", "asc": "1", "dist": "315", "left": "24", "x": "7478.105", "y": "10737.120", "z": "981.161", "club": "CUK", "con": "", "shotText": "Shot 3 putt 26 ft 3 in., 2 ft 0 in. to hole"}, {"n": "4", "pid": "0", "time": "", "putt": "2", "t": "S", "prv": "n", "tee": "n", "cup": "y", "from": "OGR", "to": "hole", "asc": "1", "dist": "24", "left": "0", "x": "0", "y": "0", "z": "0", "club": "CUK", "con": "", "shotText": "Shot 4 in the hole"}]}, {"n": "9", "cNum": "9", "sc": "4", "pDay": "-3", "pTot": "-3", "shots": [{"n": "1", "pid": "0", "time": "", "putt": "", "t": "S", "prv": "n", "tee": "y", "cup": "n", "from": "OTB", "to": "ERF", "asc": "1", "dist": "10835", "left": "5554", "x": "8326.109", "y": "10729.510", "z": "985.541", "club": "CDR", "con": "", "shotText": "Shot 1 301 yds to right fairway, 154 yds to hole"}, {"n": "2", "pid": "0", "time": "", "putt": "", "t": "S", "prv": "n", "tee": "n", "cup": "n", "from": "OFW", "to": "OGR", "asc": "1", "dist": "5714", "left": "695", "x": "8795.444", "y": "10649.156", "z": "987.874", "club": "CUK", "con": "", "shotText": "Shot 2 159 yds to green, 58 ft to hole"}, {"n": "3", "pid": "0", "time": "", "putt": "1", "t": "S", "prv": "n", "tee": "n", "cup": "n", "from": "OGR", "to": "OGR", "asc": "1", "dist": "683", "left": "36", "x": "8773.016", "y": "10596.844", "z": "987.433", "club": "CUK", "con": "", "shotText": "Shot 3 putt 56 ft 11 in., 3 ft 0 in. to hole"}, {"n": "4", "pid": "0", "time": "", "putt": "2", "t": "S", "prv": "n", "tee": "n", "cup": "y", "from": "OGR", "to": "hole", "asc": "1", "dist": "36", "left": "0", "x": "0", "y": "0", "z": "0", "club": "CUK", "con": "", "shotText": "Shot 4 in the hole"}]}, {"n": "10", "cNum": "10", "sc": "4", "pDay": "-3", "pTot": "-3", "shots": [{"n": "1", "pid": "0", "time": "", "putt": "", "t": "S", "prv": "n", "tee": "y", "cup": "n", "from": "OTB", "to": "ELF", "asc": "1", "dist": "10667", "left": "3328", "x": "8689.803", "y": "9794.547", "z": "978.660", "club": "CDR", "con": "", "shotText": "Shot 1 296 yds to left fairway, 92 yds to hole"}, {"n": "2", "pid": "0", "time": "", "putt": "", "t": "S", "prv": "n", "tee": "n", "cup": "n", "from": "OFW", "to": "OGR", "asc": "1", "dist": "3255", "left": "76", "x": "8418.615", "y": "9796.952", "z": "983.917", "club": "CUK", "con": "", "shotText": "Shot 2 90 yds to green, 6 ft to hole"}, {"n": "3", "pid": "0", "time": "", "putt": "1", "t": "S", "prv": "n", "tee": "n", "cup": "n", "from": "OGR", "to": "OGR", "asc": "1", "dist": "88", "left": "20", "x": "8412.150", "y": "9793.451", "z": "984.016", "club": "CUK", "con": "", "shotText": "Shot 3 putt 7 ft 4 in., 20 in. to hole"}, {"n": "4", "pid": "0", "time": "", "putt": "2", "t": "S", "prv": "n", "tee": "n", "cup": "y", "from": "OGR", "to": "hole", "asc": "1", "dist": "20", "left": "0", "x": "0", "y": "0", "z": "0", "club": "CUK", "con": "", "shotText": "Shot 4 in the hole"}]}, {"n": "11", "cNum": "11", "sc": "4", "pDay": "-3", "pTot": "-3", "shots": [{"n": "1", "pid": "0", "time": "", "putt": "", "t": "S", "prv": "n", "tee": "y", "cup": "n", "from": "OTB", "to": "ELI", "asc": "1", "dist": "11020", "left": "6670", "x": "7444.140", "y": "10255.500", "z": "978.792", "club": "CDR", "con": "", "shotText": "Shot 1 306 yds to left intermediate, 185 yds to hole"}, {"n": "2", "pid": "0", "time": "", "putt": "", "t": "S", "prv": "n", "tee": "n", "cup": "n", "from": "OIR", "to": "OGR", "asc": "1", "dist": "6151", "left": "547", "x": "7087.460", "y": "10623.580", "z": "982.153", "club": "CUK", "con": "", "shotText": "Shot 2 171 yds to green, 46 ft to hole"}, {"n": "3", "pid": "0", "time": "", "putt": "1", "t": "S", "prv": "n", "tee": "n", "cup": "n", "from": "OGR", "to": "OGR", "asc": "1", "dist": "498", "left": "55", "x": "7068.164", "y": "10660.288", "z": "982.632", "club": "CUK", "con": "", "shotText": "Shot 3 putt 41 ft 6 in., 4 ft 7 in. to hole"}, {"n": "4", "pid": "0", "time": "", "putt": "2", "t": "S", "prv": "n", "tee": "n", "cup": "y", "from": "OGR", "to": "hole", "asc": "1", "dist": "55", "left": "0", "x": "0", "y": "0", "z": "0", "club": "CUK", "con": "", "shotText": "Shot 4 in the hole"}]}, {"n": "12", "cNum": "12", "sc": "4", "pDay": "-2", "pTot": "-2", "shots": [{"n": "1", "pid": "0", "time": "", "putt": "", "t": "S", "prv": "n", "tee": "y", "cup": "n", "from": "OTB", "to": "OGR", "asc": "1", "dist": "7137", "left": "760", "x": "6471.656", "y": "10294.407", "z": "979.904", "club": "CUK", "con": "", "shotText": "Shot 1 198 yds to green, 63 ft to hole"}, {"n": "2", "pid": "0", "time": "", "putt": "1", "t": "S", "prv": "n", "tee": "n", "cup": "n", "from": "OGR", "to": "OGR", "asc": "1", "dist": "805", "left": "57", "x": "6530.073", "y": "10327.389", "z": "979.780", "club": "CUK", "con": "", "shotText": "Shot 2 putt 67 ft 1 in., 4 ft 9 in. to hole"}, {"n": "3", "pid": "0", "time": "", "putt": "2", "t": "S", "prv": "n", "tee": "n", "cup": "n", "from": "OGR", "to": "OGR", "asc": "1", "dist": "82", "left": "25", "x": "6529.514", "y": "10320.550", "z": "979.897", "club": "CUK", "con": "", "shotText": "Shot 3 putt 6 ft 10 in., 2 ft 1 in. to hole"}, {"n": "4", "pid": "0", "time": "", "putt": "3", "t": "S", "prv": "n", "tee": "n", "cup": "y", "from": "OGR", "to": "hole", "asc": "1", "dist": "25", "left": "0", "x": "0", "y": "0", "z": "0", "club": "CUK", "con": "", "shotText": "Shot 4 in the hole"}]}, {"n": "13", "cNum": "13", "sc": "4", "pDay": "-3", "pTot": "-3", "shots": [{"n": "1", "pid": "0", "time": "", "putt": "", "t": "S", "prv": "n", "tee": "y", "cup": "n", "from": "OTB", "to": "ERF", "asc": "1", "dist": "10545", "left": "9082", "x": "5672.599", "y": "10948.103", "z": "981.710", "club": "CDR", "con": "", "shotText": "Shot 1 293 yds to right fairway, 252 yds to hole"}, {"n": "2", "pid": "0", "time": "", "putt": "", "t": "S", "prv": "n", "tee": "n", "cup": "n", "from": "OFW", "to": "OGR", "asc": "1", "dist": "9218", "left": "572", "x": "5161.778", "y": "11521.800", "z": "987.149", "club": "CUK", "con": "", "shotText": "Shot 2 256 yds to green, 48 ft to hole"}, {"n": "3", "pid": "0", "time": "", "putt": "1", "t": "S", "prv": "n", "tee": "n", "cup": "n", "from": "OGR", "to": "OGR", "asc": "1", "dist": "573", "left": "13", "x": "5205.110", "y": "11541.953", "z": "987.476", "club": "CUK", "con": "", "shotText": "Shot 3 putt 47 ft 9 in., 13 in. to hole"}, {"n": "4", "pid": "0", "time": "", "putt": "2", "t": "S", "prv": "n", "tee": "n", "cup": "y", "from": "OGR", "to": "hole", "asc": "1", "dist": "13", "left": "0", "x": "0", "y": "0", "z": "0", "club": "CUK", "con": "", "shotText": "Shot 4 in the hole"}]}, {"n": "14", "cNum": "14", "sc": "4", "pDay": "-3", "pTot": "-3", "shots": [{"n": "1", "pid": "0", "time": "", "putt": "", "t": "S", "prv": "n", "tee": "y", "cup": "n", "from": "OTB", "to": "ELF", "asc": "1", "dist": "10894", "left": "5241", "x": "5468.278", "y": "10580.581", "z": "984.934", "club": "CDR", "con": "", "shotText": "Shot 1 303 yds to left fairway, 146 yds to hole"}, {"n": "2", "pid": "0", "time": "", "putt": "", "t": "S", "prv": "n", "tee": "n", "cup": "n", "from": "OFW", "to": "OGR", "asc": "1", "dist": "5202", "left": "156", "x": "5826.660", "y": "10336.700", "z": "986.618", "club": "CUK", "con": "", "shotText": "Shot 2 145 yds to green, 13 ft to hole"}, {"n": "3", "pid": "0", "time": "", "putt": "1", "t": "S", "prv": "n", "tee": "n", "cup": "n", "from": "OGR", "to": "OGR", "asc": "1", "dist": "181", "left": "22", "x": "5822.424", "y": "10322.187", "z": "986.520", "club": "CUK", "con": "", "shotText": "Shot 3 putt 15 ft 1 in., 22 in. to hole"}, {"n": "4", "pid": "0", "time": "", "putt": "2", "t": "S", "prv": "n", "tee": "n", "cup": "y", "from": "OGR", "to": "hole", "asc": "1", "dist": "22", "left": "0", "x": "0", "y": "0", "z": "0", "club": "CUK", "con": "", "shotText": "Shot 4 in the hole"}]}, {"n": "15", "cNum": "15", "sc": "5", "pDay": "-3", "pTot": "-3", "shots": [{"n": "1", "pid": "0", "time": "", "putt": "", "t": "S", "prv": "n", "tee": "y", "cup": "n", "from": "OTB", "to": "ERR", "asc": "1", "dist": "12268", "left": "8160", "x": "6949.147", "y": "9948.936", "z": "981.288", "club": "CDR", "con": "", "shotText": "Shot 1 341 yds to right rough, 227 yds to hole"}, {"n": "2", "pid": "0", "time": "", "putt": "", "t": "S", "prv": "n", "tee": "n", "cup": "n", "from": "ORO", "to": "ERF", "asc": "1", "dist": "4096", "left": "4161", "x": "7282.088", "y": "10023.904", "z": "977.489", "club": "CUK", "con": "", "shotText": "Shot 2 114 yds to right fairway, 116 yds to hole"}, {"n": "3", "pid": "0", "time": "", "putt": "", "t": "S", "prv": "n", "tee": "n", "cup": "n", "from": "OFW", "to": "OGR", "asc": "1", "dist": "3864", "left": "450", "x": "7604.090", "y": "10023.925", "z": "980.217", "club": "CUK", "con": "", "shotText": "Shot 3 107 yds to green, 38 ft to hole"}, {"n": "4", "pid": "0", "time": "", "putt": "1", "t": "S", "prv": "n", "tee": "n", "cup": "n", "from": "OGR", "to": "OGR", "asc": "1", "dist": "400", "left": "50", "x": "7625.044", "y": "9998.023", "z": "980.797", "club": "CUK", "con": "", "shotText": "Shot 4 putt 33 ft 4 in., 4 ft 2 in. to hole"}, {"n": "5", "pid": "0", "time": "", "putt": "2", "t": "S", "prv": "n", "tee": "n", "cup": "y", "from": "OGR", "to": "hole", "asc": "1", "dist": "50", "left": "0", "x": "0", "y": "0", "z": "0", "club": "CUK", "con": "", "shotText": "Shot 5 in the hole"}]}, {"n": "16", "cNum": "16", "sc": "3", "pDay": "-3", "pTot": "-3", "shots": [{"n": "1", "pid": "0", "time": "", "putt": "", "t": "S", "prv": "n", "tee": "y", "cup": "n", "from": "OTB", "to": "OGR", "asc": "1", "dist": "6139", "left": "305", "x": "8147.159", "y": "9802.327", "z": "985.081", "club": "CUK", "con": "", "shotText": "Shot 1 171 yds to green, 25 ft to hole"}, {"n": "2", "pid": "0", "time": "", "putt": "1", "t": "S", "prv": "n", "tee": "n", "cup": "n", "from": "OGR", "to": "OGR", "asc": "1", "dist": "307", "left": "9", "x": "8170.023", "y": "9813.893", "z": "985.253", "club": "CUK", "con": "", "shotText": "Shot 2 putt 25 ft 7 in., 9 in. to hole"}, {"n": "3", "pid": "0", "time": "", "putt": "2", "t": "S", "prv": "n", "tee": "n", "cup": "y", "from": "OGR", "to": "hole", "asc": "1", "dist": "9", "left": "0", "x": "0", "y": "0", "z": "0", "club": "CUK", "con": "", "shotText": "Shot 3 in the hole"}]}, {"n": "17", "cNum": "17", "sc": "4", "pDay": "-3", "pTot": "-3", "shots": [{"n": "1", "pid": "0", "time": "", "putt": "", "t": "S", "prv": "n", "tee": "y", "cup": "n", "from": "OTB", "to": "ELR", "asc": "1", "dist": "10139", "left": "1788", "x": "8951.714", "y": "9664.168", "z": "977.535", "club": "CDR", "con": "", "shotText": "Shot 1 282 yds to left rough, 50 yds to hole"}, {"n": "2", "pid": "0", "time": "", "putt": "", "t": "S", "prv": "n", "tee": "n", "cup": "n", "from": "ORO", "to": "ERF", "asc": "1", "dist": "2395", "left": "602", "x": "9095.755", "y": "9526.048", "z": "981.172", "club": "CUK", "con": "", "shotText": "Shot 2 67 yds to right fairway, 50 ft to hole"}, {"n": "3", "pid": "0", "time": "", "putt": "", "t": "S", "prv": "n", "tee": "n", "cup": "n", "from": "OFW", "to": "OGR", "asc": "1", "dist": "680", "left": "73", "x": "9053.952", "y": "9564.254", "z": "980.654", "club": "CUK", "con": "", "shotText": "Shot 3 57 ft to green, 6 ft to hole"}, {"n": "4", "pid": "0", "time": "", "putt": "1", "t": "S", "prv": "n", "tee": "n", "cup": "y", "from": "OGR", "to": "hole", "asc": "1", "dist": "73", "left": "0", "x": "0", "y": "0", "z": "0", "club": "CUK", "con": "", "shotText": "Shot 4 in the hole"}]}, {"n": "18", "cNum": "18", "sc": "4", "pDay": "-3", "pTot": "-3", "shots": [{"n": "1", "pid": "0", "time": "", "putt": "", "t": "S", "prv": "n", "tee": "y", "cup": "n", "from": "OTB", "to": "ERF", "asc": "1", "dist": "11187", "left": "4916", "x": "9588.233", "y": "10201.510", "z": "980.359", "club": "CDR", "con": "", "shotText": "Shot 1 311 yds to right fairway, 137 yds to hole"}, {"n": "2", "pid": "0", "time": "", "putt": "", "t": "S", "prv": "n", "tee": "n", "cup": "n", "from": "OFW", "to": "OGR", "asc": "1", "dist": "4744", "left": "206", "x": "9518.738", "y": "10590.647", "z": "984.869", "club": "CUK", "con": "", "shotText": "Shot 2 132 yds to green, 17 ft to hole"}, {"n": "3", "pid": "0", "time": "", "putt": "1", "t": "S", "prv": "n", "tee": "n", "cup": "n", "from": "OGR", "to": "OGR", "asc": "1", "dist": "231", "left": "22", "x": "9504.738", "y": "10603.905", "z": "985.010", "club": "CUK", "con": "", "shotText": "Shot 3 putt 19 ft 3 in., 22 in. to hole"}, {"n": "4", "pid": "0", "time": "", "putt": "2", "t": "S", "prv": "n", "tee": "n", "cup": "y", "from": "OGR", "to": "hole", "asc": "1", "dist": "22", "left": "0", "x": "0", "y": "0", "z": "0", "club": "CUK", "con": "", "shotText": "Shot 4 in the hole"}]}]}, {"n": "2", "holes": [{"n": "1", "cNum": "10", "sc": "4", "pDay": "0", "pTot": "-3", "shots": [{"n": "1", "pid": "0", "time": "", "putt": "", "t": "S", "prv": "n", "tee": "y", "cup": "n", "from": "OTB", "to": "OST", "asc": "1", "dist": "9190", "left": "5027", "x": "8776.750", "y": "9886.110", "z": "979.377", "club": "CDR", "con": "", "shotText": "Shot 1 255 yds to fairway bunker, 140 yds to hole"}, {"n": "2", "pid": "0", "time": "", "putt": "", "t": "S", "prv": "n", "tee": "n", "cup": "n", "from": "OST", "to": "ERR", "asc": "1", "dist": "5309", "left": "298", "x": "8337.581", "y": "9833.123", "z": "984.938", "club": "CUK", "con": "", "shotText": "Shot 2 147 yds to right rough, 25 ft to hole"}, {"n": "3", "pid": "0", "time": "", "putt": "", "t": "S", "prv": "n", "tee": "n", "cup": "n", "from": "ORO", "to": "OGR", "asc": "1", "dist": "285", "left": "119", "x": "8360.965", "y": "9836.908", "z": "983.791", "club": "CUK", "con": "", "shotText": "Shot 3 24 ft to green, 10 ft to hole"}, {"n": "4", "pid": "0", "time": "", "putt": "1", "t": "S", "prv": "n", "tee": "n", "cup": "y", "from": "OGR", "to": "hole", "asc": "1", "dist": "119", "left": "0", "x": "0", "y": "0", "z": "0", "club": "CUK", "con": "", "shotText": "Shot 4 in the hole"}]}, {"n": "2", "cNum": "11", "sc": "3", "pDay": "-1", "pTot": "-4", "shots": [{"n": "1", "pid": "0", "time": "", "putt": "", "t": "S", "prv": "n", "tee": "y", "cup": "n", "from": "OTB", "to": "ERF", "asc": "1", "dist": "9762", "left": "6968", "x": "7559.562", "y": "10267.333", "z": "979.769", "club": "CDR", "con": "", "shotText": "Shot 1 271 yds to right fairway, 194 yds to hole"}, {"n": "2", "pid": "0", "time": "", "putt": "", "t": "S", "prv": "n", "tee": "n", "cup": "n", "from": "OFW", "to": "OGR", "asc": "1", "dist": "7092", "left": "147", "x": "7083.580", "y": "10617.658", "z": "982.048", "club": "CUK", "con": "", "shotText": "Shot 2 197 yds to green, 12 ft to hole"}, {"n": "3", "pid": "0", "time": "", "putt": "1", "t": "S", "prv": "n", "tee": "n", "cup": "y", "from": "OGR", "to": "hole", "asc": "1", "dist": "147", "left": "0", "x": "0", "y": "0", "z": "0", "club": "CUK", "con": "", "shotText": "Shot 3 in the hole"}]}, {"n": "3", "cNum": "12", "sc": "3", "pDay": "-1", "pTot": "-4", "shots": [{"n": "1", "pid": "0", "time": "", "putt": "", "t": "S", "prv": "n", "tee": "y", "cup": "n", "from": "OTB", "to": "OGR", "asc": "1", "dist": "7275", "left": "399", "x": "6484.910", "y": "10297.210", "z": "979.988", "club": "CUK", "con": "", "shotText": "Shot 1 202 yds to green, 33 ft to hole"}, {"n": "2", "pid": "0", "time": "", "putt": "1", "t": "S", "prv": "n", "tee": "n", "cup": "n", "from": "OGR", "to": "OGR", "asc": "1", "dist": "409", "left": "12", "x": "6457.688", "y": "10276.649", "z": "979.785", "club": "CUK", "con": "", "shotText": "Shot 2 putt 34 ft 1 in., 12 in. to hole"}, {"n": "3", "pid": "0", "time": "", "putt": "2", "t": "S", "prv": "n", "tee": "n", "cup": "y", "from": "OGR", "to": "hole", "asc": "1", "dist": "12", "left": "0", "x": "0", "y": "0", "z": "0", "club": "CUK", "con": "", "shotText": "Shot 3 in the hole"}]}, {"n": "4", "cNum": "13", "sc": "5", "pDay": "-1", "pTot": "-4", "shots": [{"n": "1", "pid": "0", "time": "", "putt": "", "t": "S", "prv": "n", "tee": "y", "cup": "n", "from": "OTB", "to": "ERF", "asc": "1", "dist": "9934", "left": "10219", "x": "5725.505", "y": "10924.440", "z": "981.847", "club": "CDR", "con": "", "shotText": "Shot 1 276 yds to right fairway, 284 yds to hole"}, {"n": "2", "pid": "0", "time": "", "putt": "", "t": "S", "prv": "n", "tee": "n", "cup": "n", "from": "OFW", "to": "EG5", "asc": "1", "dist": "8468", "left": "1771", "x": "5229.602", "y": "11426.475", "z": "982.047", "club": "CUK", "con": "", "shotText": "Shot 2 235 yds to front left green side bunker, 49 yds to hole"}, {"n": "3", "pid": "0", "time": "", "putt": "", "t": "S", "prv": "n", "tee": "n", "cup": "n", "from": "OGS", "to": "OGR", "asc": "1", "dist": "1045", "left": "740", "x": "5187.025", "y": "11502.349", "z": "986.612", "club": "CUK", "con": "", "shotText": "Shot 3 87 ft to green, 62 ft to hole"}, {"n": "4", "pid": "0", "time": "", "putt": "1", "t": "S", "prv": "n", "tee": "n", "cup": "n", "from": "OGR", "to": "OGR", "asc": "1", "dist": "735", "left": "26", "x": "5142.775", "y": "11544.717", "z": "987.625", "club": "CUK", "con": "", "shotText": "Shot 4 putt 61 ft 3 in., 2 ft 2 in. to hole"}, {"n": "5", "pid": "0", "time": "", "putt": "2", "t": "S", "prv": "n", "tee": "n", "cup": "y", "from": "OGR", "to": "hole", "asc": "1", "dist": "26", "left": "0", "x": "0", "y": "0", "z": "0", "club": "CUK", "con": "", "shotText": "Shot 5 in the hole"}]}, {"n": "5", "cNum": "14", "sc": "3", "pDay": "-2", "pTot": "-5", "shots": [{"n": "1", "pid": "0", "time": "", "putt": "", "t": "S", "prv": "n", "tee": "y", "cup": "n", "from": "OTB", "to": "ELF", "asc": "1", "dist": "11000", "left": "4670", "x": "5483.089", "y": "10571.149", "z": "984.750", "club": "CDR", "con": "", "shotText": "Shot 1 306 yds to left fairway, 130 yds to hole"}, {"n": "2", "pid": "0", "time": "", "putt": "", "t": "S", "prv": "n", "tee": "n", "cup": "n", "from": "OFW", "to": "OGR", "asc": "1", "dist": "4766", "left": "163", "x": "5775.792", "y": "10302.735", "z": "986.389", "club": "CUK", "con": "", "shotText": "Shot 2 132 yds to green, 14 ft to hole"}, {"n": "3", "pid": "0", "time": "", "putt": "1", "t": "S", "prv": "n", "tee": "n", "cup": "y", "from": "OGR", "to": "hole", "asc": "1", "dist": "163", "left": "0", "x": "0", "y": "0", "z": "0", "club": "CUK", "con": "", "shotText": "Shot 3 in the hole"}]}, {"n": "6", "cNum": "15", "sc": "5", "pDay": "-2", "pTot": "-5", "shots": [{"n": "1", "pid": "0", "time": "", "putt": "", "t": "S", "prv": "n", "tee": "y", "cup": "n", "from": "OTB", "to": "ERF", "asc": "1", "dist": "11591", "left": "8094", "x": "6924.901", "y": "9989.514", "z": "980.553", "club": "CDR", "con": "", "shotText": "Shot 1 322 yds to right fairway, 225 yds to hole"}, {"n": "2", "pid": "0", "time": "", "putt": "", "t": "S", "prv": "n", "tee": "n", "cup": "n", "from": "OFW", "to": "ERF", "asc": "1", "dist": "4863", "left": "3233", "x": "7328.933", "y": "10020.344", "z": "977.496", "club": "CUK", "con": "", "shotText": "Shot 2 135 yds to right fairway, 90 yds to hole"}, {"n": "3", "pid": "0", "time": "", "putt": "", "t": "S", "prv": "n", "tee": "n", "cup": "n", "from": "OFW", "to": "OGR", "asc": "1", "dist": "3302", "left": "63", "x": "7603.919", "y": "10029.270", "z": "980.231", "club": "CUK", "con": "", "shotText": "Shot 3 92 yds to green, 5 ft to hole"}, {"n": "4", "pid": "0", "time": "", "putt": "1", "t": "S", "prv": "n", "tee": "n", "cup": "n", "from": "OGR", "to": "OGR", "asc": "1", "dist": "108", "left": "39", "x": "7594.963", "y": "10028.628", "z": "980.002", "club": "CUK", "con": "", "shotText": "Shot 4 putt 9 ft 0 in., 3 ft 3 in. to hole"}, {"n": "5", "pid": "0", "time": "", "putt": "2", "t": "S", "prv": "n", "tee": "n", "cup": "y", "from": "OGR", "to": "hole", "asc": "1", "dist": "39", "left": "0", "x": "0", "y": "0", "z": "0", "club": "CUK", "con": "", "shotText": "Shot 5 in the hole"}]}, {"n": "7", "cNum": "16", "sc": "3", "pDay": "-2", "pTot": "-5", "shots": [{"n": "1", "pid": "0", "time": "", "putt": "", "t": "S", "prv": "n", "tee": "y", "cup": "n", "from": "OTB", "to": "OGR", "asc": "1", "dist": "5911", "left": "400", "x": "8151.246", "y": "9791.602", "z": "985.298", "club": "CUK", "con": "", "shotText": "Shot 1 164 yds to green, 33 ft to hole"}, {"n": "2", "pid": "0", "time": "", "putt": "1", "t": "S", "prv": "n", "tee": "n", "cup": "n", "from": "OGR", "to": "OGR", "asc": "1", "dist": "425", "left": "20", "x": "8128.006", "y": "9764.928", "z": "984.620", "club": "CUK", "con": "", "shotText": "Shot 2 putt 35 ft 5 in., 20 in. to hole"}, {"n": "3", "pid": "0", "time": "", "putt": "2", "t": "S", "prv": "n", "tee": "n", "cup": "y", "from": "OGR", "to": "hole", "asc": "1", "dist": "20", "left": "0", "x": "0", "y": "0", "z": "0", "club": "CUK", "con": "", "shotText": "Shot 3 in the hole"}]}, {"n": "8", "cNum": "17", "sc": "3", "pDay": "-3", "pTot": "-6", "shots": [{"n": "1", "pid": "0", "time": "", "putt": "", "t": "S", "prv": "n", "tee": "y", "cup": "n", "from": "OTB", "to": "ERF", "asc": "1", "dist": "10670", "left": "1236", "x": "8993.466", "y": "9554.602", "z": "978.218", "club": "CDR", "con": "", "shotText": "Shot 1 296 yds to right fairway, 34 yds to hole"}, {"n": "2", "pid": "0", "time": "", "putt": "", "t": "S", "prv": "n", "tee": "n", "cup": "n", "from": "OFW", "to": "OGR", "asc": "1", "dist": "1247", "left": "12", "x": "9074.837", "y": "9619.223", "z": "980.246", "club": "CUK", "con": "", "shotText": "Shot 2 35 yds to green, 12 in. to hole"}, {"n": "3", "pid": "0", "time": "", "putt": "1", "t": "S", "prv": "n", "tee": "n", "cup": "y", "from": "OGR", "to": "hole", "asc": "1", "dist": "12", "left": "0", "x": "0", "y": "0", "z": "0", "club": "CUK", "con": "", "shotText": "Shot 3 in the hole"}]}, {"n": "9", "cNum": "18", "sc": "5", "pDay": "-2", "pTot": "-5", "shots": [{"n": "1", "pid": "0", "time": "", "putt": "", "t": "S", "prv": "n", "tee": "y", "cup": "n", "from": "OTB", "to": "ERF", "asc": "1", "dist": "10729", "left": "5121", "x": "9600.705", "y": "10161.582", "z": "981.458", "club": "CDR", "con": "", "shotText": "Shot 1 298 yds to right fairway, 142 yds to hole"}, {"n": "2", "pid": "0", "time": "", "putt": "", "t": "S", "prv": "n", "tee": "n", "cup": "n", "from": "OFW", "to": "EG2", "asc": "1", "dist": "4831", "left": "427", "x": "9566.543", "y": "10562.738", "z": "979.767", "club": "CUK", "con": "", "shotText": "Shot 2 134 yds to right green side bunker, 36 ft to hole"}, {"n": "3", "pid": "0", "time": "", "putt": "", "t": "S", "prv": "n", "tee": "n", "cup": "n", "from": "OGS", "to": "OGR", "asc": "1", "dist": "515", "left": "85", "x": "9533.629", "y": "10589.735", "z": "984.979", "club": "CUK", "con": "", "shotText": "Shot 3 43 ft to green, 7 ft to hole"}, {"n": "4", "pid": "0", "time": "", "putt": "1", "t": "S", "prv": "n", "tee": "n", "cup": "n", "from": "OGR", "to": "OGR", "asc": "1", "dist": "115", "left": "29", "x": "9538.153", "y": "10581.282", "z": "984.794", "club": "CUK", "con": "", "shotText": "Shot 4 putt 9 ft 7 in., 2 ft 5 in. to hole"}, {"n": "5", "pid": "0", "time": "", "putt": "2", "t": "S", "prv": "n", "tee": "n", "cup": "y", "from": "OGR", "to": "hole", "asc": "1", "dist": "29", "left": "0", "x": "0", "y": "0", "z": "0", "club": "CUK", "con": "", "shotText": "Shot 5 in the hole"}]}, {"n": "10", "cNum": "1", "sc": "4", "pDay": "-2", "pTot": "-5", "shots": [{"n": "1", "pid": "0", "time": "", "putt": "", "t": "S", "prv": "n", "tee": "y", "cup": "n", "from": "OTB", "to": "ERF", "asc": "1", "dist": "10435", "left": "4826", "x": "8820.417", "y": "11729.115", "z": "1003.824", "club": "CDR", "con": "", "shotText": "Shot 1 290 yds to right fairway, 134 yds to hole"}, {"n": "2", "pid": "0", "time": "", "putt": "", "t": "S", "prv": "n", "tee": "n", "cup": "n", "from": "OFW", "to": "OGR", "asc": "1", "dist": "4879", "left": "253", "x": "8558.046", "y": "12039.697", "z": "1005.732", "club": "CUK", "con": "", "shotText": "Shot 2 136 yds to green, 21 ft to hole"}, {"n": "3", "pid": "0", "time": "", "putt": "1", "t": "S", "prv": "n", "tee": "n", "cup": "n", "from": "OGR", "to": "OGR", "asc": "1", "dist": "246", "left": "7", "x": "8576.263", "y": "12049.111", "z": "1006.002", "club": "CUK", "con": "", "shotText": "Shot 3 putt 20 ft 6 in., 7 in. to hole"}, {"n": "4", "pid": "0", "time": "", "putt": "2", "t": "S", "prv": "n", "tee": "n", "cup": "y", "from": "OGR", "to": "hole", "asc": "1", "dist": "7", "left": "0", "x": "0", "y": "0", "z": "0", "club": "CUK", "con": "", "shotText": "Shot 4 in the hole"}]}, {"n": "11", "cNum": "2", "sc": "4", "pDay": "-2", "pTot": "-5", "shots": [{"n": "1", "pid": "0", "time": "", "putt": "", "t": "S", "prv": "n", "tee": "y", "cup": "n", "from": "OTB", "to": "OST", "asc": "1", "dist": "9663", "left": "5013", "x": "8630.226", "y": "11266.106", "z": "999.410", "club": "CDR", "con": "", "shotText": "Shot 1 268 yds to fairway bunker, 139 yds to hole"}, {"n": "2", "pid": "0", "time": "", "putt": "", "t": "S", "prv": "n", "tee": "n", "cup": "n", "from": "OST", "to": "ELF", "asc": "1", "dist": "5063", "left": "417", "x": "8904.767", "y": "10945.960", "z": "988.217", "club": "CUK", "con": "", "shotText": "Shot 2 141 yds to left fairway, 35 ft to hole"}, {"n": "3", "pid": "0", "time": "", "putt": "", "t": "S", "prv": "n", "tee": "n", "cup": "n", "from": "OFW", "to": "OGR", "asc": "1", "dist": "436", "left": "28", "x": "8872.814", "y": "10928.690", "z": "988.453", "club": "CUK", "con": "", "shotText": "Shot 3 36 ft to green, 2 ft to hole"}, {"n": "4", "pid": "0", "time": "", "putt": "1", "t": "S", "prv": "n", "tee": "n", "cup": "y", "from": "OGR", "to": "hole", "asc": "1", "dist": "28", "left": "0", "x": "0", "y": "0", "z": "0", "club": "CUK", "con": "", "shotText": "Shot 4 in the hole"}]}, {"n": "12", "cNum": "3", "sc": "5", "pDay": "-2", "pTot": "-5", "shots": [{"n": "1", "pid": "0", "time": "", "putt": "", "t": "S", "prv": "n", "tee": "y", "cup": "n", "from": "OTB", "to": "ERI", "asc": "1", "dist": "10345", "left": "9624", "x": "7792.241", "y": "11143.394", "z": "986.714", "club": "CDR", "con": "", "shotText": "Shot 1 287 yds to right intermediate, 267 yds to hole"}, {"n": "2", "pid": "0", "time": "", "putt": "", "t": "S", "prv": "n", "tee": "n", "cup": "n", "from": "OIR", "to": "ERF", "asc": "1", "dist": "6290", "left": "3366", "x": "7281.641", "y": "11262.044", "z": "986.837", "club": "CUK", "con": "", "shotText": "Shot 2 175 yds to right fairway, 94 yds to hole"}, {"n": "3", "pid": "0", "time": "", "putt": "", "t": "S", "prv": "n", "tee": "n", "cup": "n", "from": "OFW", "to": "OGR", "asc": "1", "dist": "3452", "left": "179", "x": "7022.148", "y": "11385.993", "z": "993.801", "club": "CUK", "con": "", "shotText": "Shot 3 96 yds to green, 15 ft to hole"}, {"n": "4", "pid": "0", "time": "", "putt": "1", "t": "S", "prv": "n", "tee": "n", "cup": "n", "from": "OGR", "to": "OGR", "asc": "1", "dist": "237", "left": "54", "x": "7024.195", "y": "11366.309", "z": "993.716", "club": "CUK", "con": "", "shotText": "Shot 4 putt 19 ft 9 in., 4 ft 6 in. to hole"}, {"n": "5", "pid": "0", "time": "", "putt": "2", "t": "S", "prv": "n", "tee": "n", "cup": "y", "from": "OGR", "to": "hole", "asc": "1", "dist": "54", "left": "0", "x": "0", "y": "0", "z": "0", "club": "CUK", "con": "", "shotText": "Shot 5 in the hole"}]}, {"n": "13", "cNum": "4", "sc": "3", "pDay": "-2", "pTot": "-5", "shots": [{"n": "1", "pid": "0", "time": "", "putt": "", "t": "S", "prv": "n", "tee": "y", "cup": "n", "from": "OTB", "to": "OGR", "asc": "1", "dist": "6305", "left": "168", "x": "6882.347", "y": "11924.913", "z": "998.465", "club": "CUK", "con": "", "shotText": "Shot 1 175 yds to green, 14 ft to hole"}, {"n": "2", "pid": "0", "time": "", "putt": "1", "t": "S", "prv": "n", "tee": "n", "cup": "n", "from": "OGR", "to": "OGR", "asc": "1", "dist": "185", "left": "17", "x": "6889.042", "y": "11938.802", "z": "998.438", "club": "CUK", "con": "", "shotText": "Shot 2 putt 15 ft 5 in., 17 in. to hole"}, {"n": "3", "pid": "0", "time": "", "putt": "2", "t": "S", "prv": "n", "tee": "n", "cup": "y", "from": "OGR", "to": "hole", "asc": "1", "dist": "17", "left": "0", "x": "0", "y": "0", "z": "0", "club": "CUK", "con": "", "shotText": "Shot 3 in the hole"}]}, {"n": "14", "cNum": "5", "sc": "3", "pDay": "-3", "pTot": "-6", "shots": [{"n": "1", "pid": "0", "time": "", "putt": "", "t": "S", "prv": "n", "tee": "y", "cup": "n", "from": "OTB", "to": "ELF", "asc": "1", "dist": "10088", "left": "6150", "x": "6186.300", "y": "11738.182", "z": "994.958", "club": "CDR", "con": "", "shotText": "Shot 1 280 yds to left fairway, 171 yds to hole"}, {"n": "2", "pid": "0", "time": "", "putt": "", "t": "S", "prv": "n", "tee": "n", "cup": "n", "from": "OFW", "to": "OGR", "asc": "1", "dist": "6260", "left": "123", "x": "5771.712", "y": "11421.533", "z": "992.021", "club": "CUK", "con": "", "shotText": "Shot 2 174 yds to green, 10 ft to hole"}, {"n": "3", "pid": "0", "time": "", "putt": "1", "t": "S", "prv": "n", "tee": "n", "cup": "y", "from": "OGR", "to": "hole", "asc": "1", "dist": "123", "left": "0", "x": "0", "y": "0", "z": "0", "club": "CUK", "con": "", "shotText": "Shot 3 in the hole"}]}, {"n": "15", "cNum": "6", "sc": "4", "pDay": "-3", "pTot": "-6", "shots": [{"n": "1", "pid": "0", "time": "", "putt": "", "t": "S", "prv": "n", "tee": "y", "cup": "n", "from": "OTB", "to": "ELI", "asc": "1", "dist": "10253", "left": "4826", "x": "6189.451", "y": "10874.280", "z": "982.175", "club": "CDR", "con": "", "shotText": "Shot 1 285 yds to left intermediate, 134 yds to hole"}, {"n": "2", "pid": "0", "time": "", "putt": "", "t": "S", "prv": "n", "tee": "n", "cup": "n", "from": "OIR", "to": "OGR", "asc": "1", "dist": "5443", "left": "785", "x": "6629.195", "y": "10763.262", "z": "984.537", "club": "CUK", "con": "", "shotText": "Shot 2 151 yds to green, 65 ft to hole"}, {"n": "3", "pid": "0", "time": "", "putt": "1", "t": "S", "prv": "n", "tee": "n", "cup": "n", "from": "OGR", "to": "OGR", "asc": "1", "dist": "794", "left": "12", "x": "6567.405", "y": "10739.646", "z": "983.458", "club": "CUK", "con": "", "shotText": "Shot 3 putt 66 ft 2 in., 12 in. to hole"}, {"n": "4", "pid": "0", "time": "", "putt": "2", "t": "S", "prv": "n", "tee": "n", "cup": "y", "from": "OGR", "to": "hole", "asc": "1", "dist": "12", "left": "0", "x": "0", "y": "0", "z": "0", "club": "CUK", "con": "", "shotText": "Shot 4 in the hole"}]}, {"n": "16", "cNum": "7", "sc": "4", "pDay": "-2", "pTot": "-5", "shots": [{"n": "1", "pid": "0", "time": "", "putt": "", "t": "S", "prv": "n", "tee": "y", "cup": "n", "from": "OTB", "to": "ERR", "asc": "1", "dist": "6704", "left": "863", "x": "6393.439", "y": "11431.777", "z": "986.987", "club": "CUK", "con": "", "shotText": "Shot 1 186 yds to right rough, 72 ft to hole"}, {"n": "2", "pid": "0", "time": "", "putt": "", "t": "S", "prv": "n", "tee": "n", "cup": "n", "from": "ORO", "to": "OGR", "asc": "1", "dist": "997", "left": "129", "x": "6312.184", "y": "11414.688", "z": "989.230", "club": "CUK", "con": "", "shotText": "Shot 2 83 ft to green, 11 ft to hole"}, {"n": "3", "pid": "0", "time": "", "putt": "1", "t": "S", "prv": "n", "tee": "n", "cup": "n", "from": "OGR", "to": "OGR", "asc": "1", "dist": "159", "left": "24", "x": "6324.655", "y": "11419.042", "z": "989.152", "club": "CUK", "con": "", "shotText": "Shot 3 putt 13 ft 3 in., 2 ft 0 in. to hole"}, {"n": "4", "pid": "0", "time": "", "putt": "2", "t": "S", "prv": "n", "tee": "n", "cup": "y", "from": "OGR", "to": "hole", "asc": "1", "dist": "24", "left": "0", "x": "0", "y": "0", "z": "0", "club": "CUK", "con": "", "shotText": "Shot 4 in the hole"}]}, {"n": "17", "cNum": "8", "sc": "4", "pDay": "-2", "pTot": "-5", "shots": [{"n": "1", "pid": "0", "time": "", "putt": "", "t": "S", "prv": "n", "tee": "y", "cup": "n", "from": "OTB", "to": "ELF", "asc": "1", "dist": "10740", "left": "6279", "x": "7037.159", "y": "10994.267", "z": "981.347", "club": "CDR", "con": "", "shotText": "Shot 1 298 yds to left fairway, 174 yds to hole"}, {"n": "2", "pid": "0", "time": "", "putt": "", "t": "S", "prv": "n", "tee": "n", "cup": "n", "from": "OFW", "to": "OGR", "asc": "1", "dist": "6218", "left": "576", "x": "7491.005", "y": "10744.220", "z": "981.626", "club": "CUK", "con": "", "shotText": "Shot 2 173 yds to green, 48 ft to hole"}, {"n": "3", "pid": "0", "time": "", "putt": "1", "t": "S", "prv": "n", "tee": "n", "cup": "n", "from": "OGR", "to": "OGR", "asc": "1", "dist": "580", "left": "10", "x": "7471.368", "y": "10700.051", "z": "981.136", "club": "CUK", "con": "", "shotText": "Shot 3 putt 48 ft 4 in., 10 in. to hole"}, {"n": "4", "pid": "0", "time": "", "putt": "2", "t": "S", "prv": "n", "tee": "n", "cup": "y", "from": "OGR", "to": "hole", "asc": "1", "dist": "10", "left": "0", "x": "0", "y": "0", "z": "0", "club": "CUK", "con": "", "shotText": "Shot 4 in the hole"}]}, {"n": "18", "cNum": "9", "sc": "5", "pDay": "-1", "pTot": "-4", "shots": [{"n": "1", "pid": "0", "time": "", "putt": "", "t": "S", "prv": "n", "tee": "y", "cup": "n", "from": "OTB", "to": "ERF", "asc": "1", "dist": "11711", "left": "4900", "x": "8407.395", "y": "10729.492", "z": "985.047", "club": "CDR", "con": "", "shotText": "Shot 1 325 yds to right fairway, 136 yds to hole"}, {"n": "2", "pid": "0", "time": "", "putt": "", "t": "S", "prv": "n", "tee": "n", "cup": "n", "from": "OFW", "to": "ELF", "asc": "1", "dist": "4390", "left": "584", "x": "8770.318", "y": "10683.155", "z": "985.007", "club": "CUK", "con": "", "shotText": "Shot 2 122 yds to left fairway, 49 ft to hole"}, {"n": "3", "pid": "0", "time": "", "putt": "", "t": "S", "prv": "n", "tee": "n", "cup": "n", "from": "OFW", "to": "ELF", "asc": "1", "dist": "891", "left": "303", "x": "8829.328", "y": "10638.157", "z": "987.083", "club": "CUK", "con": "", "shotText": "Shot 3 74 ft to left fairway, 25 ft to hole"}, {"n": "4", "pid": "0", "time": "", "putt": "", "t": "S", "prv": "n", "tee": "n", "cup": "n", "from": "OFW", "to": "OGR", "asc": "1", "dist": "167", "left": "136", "x": "8818.284", "y": "10646.641", "z": "987.831", "club": "CUK", "con": "", "shotText": "Shot 4 14 ft to green, 11 ft to hole"}, {"n": "5", "pid": "0", "time": "", "putt": "1", "t": "S", "prv": "n", "tee": "n", "cup": "y", "from": "OGR", "to": "hole", "asc": "1", "dist": "136", "left": "0", "x": "0", "y": "0", "z": "0", "club": "CUK", "con": "", "shotText": "Shot 5 in the hole"}]}]}, {"n": "3", "holes": [{"n": "1", "cNum": "1", "sc": "3", "pDay": "-1", "pTot": "-5", "shots": [{"n": "1", "pid": "0", "time": "", "putt": "", "t": "S", "prv": "n", "tee": "y", "cup": "n", "from": "OTB", "to": "ERF", "asc": "1", "dist": "10062", "left": "5397", "x": "8825.222", "y": "11693.820", "z": "1003.197", "club": "CDR", "con": "", "shotText": "Shot 1 280 yds to right fairway, 150 yds to hole"}, {"n": "2", "pid": "0", "time": "", "putt": "", "t": "S", "prv": "n", "tee": "n", "cup": "n", "from": "OFW", "to": "OGR", "asc": "1", "dist": "5388", "left": "119", "x": "8552.477", "y": "12050.448", "z": "1005.953", "club": "CUK", "con": "", "shotText": "Shot 2 150 yds to green, 10 ft to hole"}, {"n": "3", "pid": "0", "time": "", "putt": "1", "t": "S", "prv": "n", "tee": "n", "cup": "y", "from": "OGR", "to": "hole", "asc": "1", "dist": "119", "left": "0", "x": "0", "y": "0", "z": "0", "club": "CUK", "con": "", "shotText": "Shot 3 in the hole"}]}, {"n": "2", "cNum": "2", "sc": "4", "pDay": "-1", "pTot": "-5", "shots": [{"n": "1", "pid": "0", "time": "", "putt": "", "t": "S", "prv": "n", "tee": "y", "cup": "n", "from": "OTB", "to": "ERF", "asc": "1", "dist": "10909", "left": "3955", "x": "8724.323", "y": "11190.839", "z": "994.348", "club": "CDR", "con": "", "shotText": "Shot 1 303 yds to right fairway, 110 yds to hole"}, {"n": "2", "pid": "0", "time": "", "putt": "", "t": "S", "prv": "n", "tee": "n", "cup": "n", "from": "OFW", "to": "OGR", "asc": "1", "dist": "4009", "left": "278", "x": "8878.378", "y": "10894.465", "z": "988.474", "club": "CUK", "con": "", "shotText": "Shot 2 111 yds to green, 23 ft to hole"}, {"n": "3", "pid": "0", "time": "", "putt": "1", "t": "S", "prv": "n", "tee": "n", "cup": "n", "from": "OGR", "to": "OGR", "asc": "1", "dist": "295", "left": "13", "x": "8854.508", "y": "10888.746", "z": "989.037", "club": "CUK", "con": "", "shotText": "Shot 3 putt 24 ft 7 in., 13 in. to hole"}, {"n": "4", "pid": "0", "time": "", "putt": "2", "t": "S", "prv": "n", "tee": "n", "cup": "y", "from": "OGR", "to": "hole", "asc": "1", "dist": "13", "left": "0", "x": "0", "y": "0", "z": "0", "club": "CUK", "con": "", "shotText": "Shot 4 in the hole"}]}, {"n": "3", "cNum": "3", "sc": "5", "pDay": "-1", "pTot": "-5", "shots": [{"n": "1", "pid": "0", "time": "", "putt": "", "t": "S", "prv": "n", "tee": "y", "cup": "n", "from": "OTB", "to": "ELR", "asc": "1", "dist": "9314", "left": "10402", "x": "7851.070", "y": "10981.487", "z": "988.277", "club": "CDR", "con": "", "shotText": "Shot 1 259 yds to left rough, 289 yds to hole"}, {"n": "2", "pid": "0", "time": "", "putt": "", "t": "S", "prv": "n", "tee": "n", "cup": "n", "from": "ORO", "to": "ERF", "asc": "1", "dist": "7214", "left": "3221", "x": "7299.389", "y": "11220.233", "z": "987.177", "club": "CUK", "con": "", "shotText": "Shot 2 200 yds to right fairway, 89 yds to hole"}, {"n": "3", "pid": "0", "time": "", "putt": "", "t": "S", "prv": "n", "tee": "n", "cup": "n", "from": "OFW", "to": "OGR", "asc": "1", "dist": "3323", "left": "113", "x": "7065.030", "y": "11367.678", "z": "991.991", "club": "CUK", "con": "", "shotText": "Shot 3 92 yds to green, 9 ft to hole"}, {"n": "4", "pid": "0", "time": "", "putt": "1", "t": "S", "prv": "n", "tee": "n", "cup": "n", "from": "OGR", "to": "OGR", "asc": "1", "dist": "135", "left": "21", "x": "7076.196", "y": "11366.175", "z": "991.910", "club": "CUK", "con": "", "shotText": "Shot 4 putt 11 ft 3 in., 21 in. to hole"}, {"n": "5", "pid": "0", "time": "", "putt": "2", "t": "S", "prv": "n", "tee": "n", "cup": "y", "from": "OGR", "to": "hole", "asc": "1", "dist": "21", "left": "0", "x": "0", "y": "0", "z": "0", "club": "CUK", "con": "", "shotText": "Shot 5 in the hole"}]}, {"n": "4", "cNum": "4", "sc": "3", "pDay": "-1", "pTot": "-5", "shots": [{"n": "1", "pid": "0", "time": "", "putt": "", "t": "S", "prv": "n", "tee": "y", "cup": "n", "from": "OTB", "to": "OGR", "asc": "1", "dist": "6322", "left": "331", "x": "6881.793", "y": "11941.501", "z": "998.639", "club": "CUK", "con": "", "shotText": "Shot 1 176 yds to green, 28 ft to hole"}, {"n": "2", "pid": "0", "time": "", "putt": "1", "t": "S", "prv": "n", "tee": "n", "cup": "n", "from": "OGR", "to": "OGR", "asc": "1", "dist": "323", "left": "14", "x": "6855.185", "y": "11937.256", "z": "999.327", "club": "CUK", "con": "", "shotText": "Shot 2 putt 26 ft 11 in., 14 in. to hole"}, {"n": "3", "pid": "0", "time": "", "putt": "2", "t": "S", "prv": "n", "tee": "n", "cup": "y", "from": "OGR", "to": "hole", "asc": "1", "dist": "14", "left": "0", "x": "0", "y": "0", "z": "0", "club": "CUK", "con": "", "shotText": "Shot 3 in the hole"}]}, {"n": "5", "cNum": "5", "sc": "4", "pDay": "-1", "pTot": "-5", "shots": [{"n": "1", "pid": "0", "time": "", "putt": "", "t": "S", "prv": "n", "tee": "y", "cup": "n", "from": "OTB", "to": "ERF", "asc": "1", "dist": "10584", "left": "5419", "x": "6157.934", "y": "11736.620", "z": "994.601", "club": "CDR", "con": "", "shotText": "Shot 1 294 yds to right fairway, 151 yds to hole"}, {"n": "2", "pid": "0", "time": "", "putt": "", "t": "S", "prv": "n", "tee": "n", "cup": "n", "from": "OFW", "to": "OGR", "asc": "1", "dist": "5604", "left": "180", "x": "5772.103", "y": "11473.576", "z": "991.781", "club": "CUK", "con": "", "shotText": "Shot 2 156 yds to green, 15 ft to hole"}, {"n": "3", "pid": "0", "time": "", "putt": "1", "t": "S", "prv": "n", "tee": "n", "cup": "n", "from": "OGR", "to": "OGR", "asc": "1", "dist": "193", "left": "10", "x": "5784.392", "y": "11483.951", "z": "991.626", "club": "CUK", "con": "", "shotText": "Shot 3 putt 16 ft 1 in., 10 in. to hole"}, {"n": "4", "pid": "0", "time": "", "putt": "2", "t": "S", "prv": "n", "tee": "n", "cup": "y", "from": "OGR", "to": "hole", "asc": "1", "dist": "10", "left": "0", "x": "0", "y": "0", "z": "0", "club": "CUK", "con": "", "shotText": "Shot 4 in the hole"}]}, {"n": "6", "cNum": "6", "sc": "4", "pDay": "-1", "pTot": "-5", "shots": [{"n": "1", "pid": "0", "time": "", "putt": "", "t": "S", "prv": "n", "tee": "y", "cup": "n", "from": "OTB", "to": "ELF", "asc": "1", "dist": "10291", "left": "5282", "x": "6180.164", "y": "10844.230", "z": "981.966", "club": "CDR", "con": "", "shotText": "Shot 1 286 yds to left fairway, 147 yds to hole"}, {"n": "2", "pid": "0", "time": "", "putt": "", "t": "S", "prv": "n", "tee": "n", "cup": "n", "from": "OFW", "to": "OGR", "asc": "1", "dist": "5244", "left": "378", "x": "6609.691", "y": "10763.907", "z": "984.382", "club": "CUK", "con": "", "shotText": "Shot 2 146 yds to green, 32 ft to hole"}, {"n": "3", "pid": "0", "time": "", "putt": "1", "t": "S", "prv": "n", "tee": "n", "cup": "n", "from": "OGR", "to": "OGR", "asc": "1", "dist": "321", "left": "59", "x": "6605.627", "y": "10737.506", "z": "985.123", "club": "CUK", "con": "", "shotText": "Shot 3 putt 26 ft 9 in., 4 ft 11 in. to hole"}, {"n": "4", "pid": "0", "time": "", "putt": "2", "t": "S", "prv": "n", "tee": "n", "cup": "y", "from": "OGR", "to": "hole", "asc": "1", "dist": "59", "left": "0", "x": "0", "y": "0", "z": "0", "club": "CUK", "con": "", "shotText": "Shot 4 in the hole"}]}, {"n": "7", "cNum": "7", "sc": "3", "pDay": "-1", "pTot": "-5", "shots": [{"n": "1", "pid": "0", "time": "", "putt": "", "t": "S", "prv": "n", "tee": "y", "cup": "n", "from": "OTB", "to": "OGR", "asc": "1", "dist": "8197", "left": "225", "x": "6301.144", "y": "11459.771", "z": "990.032", "club": "CUK", "con": "", "shotText": "Shot 1 228 yds to green, 19 ft to hole"}, {"n": "2", "pid": "0", "time": "", "putt": "1", "t": "S", "prv": "n", "tee": "n", "cup": "n", "from": "OGR", "to": "OGR", "asc": "1", "dist": "258", "left": "29", "x": "6292.045", "y": "11440.329", "z": "989.640", "club": "CUK", "con": "", "shotText": "Shot 2 putt 21 ft 6 in., 2 ft 5 in. to hole"}, {"n": "3", "pid": "0", "time": "", "putt": "2", "t": "S", "prv": "n", "tee": "n", "cup": "y", "from": "OGR", "to": "hole", "asc": "1", "dist": "29", "left": "0", "x": "0", "y": "0", "z": "0", "club": "CUK", "con": "", "shotText": "Shot 3 in the hole"}]}, {"n": "8", "cNum": "8", "sc": "3", "pDay": "-2", "pTot": "-6", "shots": [{"n": "1", "pid": "0", "time": "", "putt": "", "t": "S", "prv": "n", "tee": "y", "cup": "n", "from": "OTB", "to": "ELR", "asc": "1", "dist": "9774", "left": "6665", "x": "6999.741", "y": "11074.535", "z": "982.192", "club": "CDR", "con": "", "shotText": "Shot 1 272 yds to left rough, 185 yds to hole"}, {"n": "2", "pid": "0", "time": "", "putt": "", "t": "S", "prv": "n", "tee": "n", "cup": "n", "from": "ORO", "to": "OGR", "asc": "1", "dist": "6700", "left": "196", "x": "7457.569", "y": "10754.926", "z": "980.669", "club": "CUK", "con": "", "shotText": "Shot 2 186 yds to green, 16 ft to hole"}, {"n": "3", "pid": "0", "time": "", "putt": "1", "t": "S", "prv": "n", "tee": "n", "cup": "y", "from": "OGR", "to": "hole", "asc": "1", "dist": "196", "left": "0", "x": "0", "y": "0", "z": "0", "club": "CUK", "con": "", "shotText": "Shot 3 in the hole"}]}, {"n": "9", "cNum": "9", "sc": "4", "pDay": "-2", "pTot": "-6", "shots": [{"n": "1", "pid": "0", "time": "", "putt": "", "t": "S", "prv": "n", "tee": "y", "cup": "n", "from": "OTB", "to": "ELF", "asc": "1", "dist": "10295", "left": "6291", "x": "8283.916", "y": "10763.928", "z": "985.915", "club": "CDR", "con": "", "shotText": "Shot 1 286 yds to left fairway, 175 yds to hole"}, {"n": "2", "pid": "0", "time": "", "putt": "", "t": "S", "prv": "n", "tee": "n", "cup": "n", "from": "OFW", "to": "OGR", "asc": "1", "dist": "6009", "left": "302", "x": "8761.639", "y": "10613.700", "z": "987.409", "club": "CUK", "con": "", "shotText": "Shot 2 167 yds to green, 25 ft to hole"}, {"n": "3", "pid": "0", "time": "", "putt": "1", "t": "S", "prv": "n", "tee": "n", "cup": "n", "from": "OGR", "to": "OGR", "asc": "1", "dist": "332", "left": "27", "x": "8782.430", "y": "10595.493", "z": "987.525", "club": "CUK", "con": "", "shotText": "Shot 3 putt 27 ft 8 in., 2 ft 3 in. to hole"}, {"n": "4", "pid": "0", "time": "", "putt": "2", "t": "S", "prv": "n", "tee": "n", "cup": "y", "from": "OGR", "to": "hole", "asc": "1", "dist": "27", "left": "0", "x": "0", "y": "0", "z": "0", "club": "CUK", "con": "", "shotText": "Shot 4 in the hole"}]}, {"n": "10", "cNum": "10", "sc": "4", "pDay": "-2", "pTot": "-6", "shots": [{"n": "1", "pid": "0", "time": "", "putt": "", "t": "S", "prv": "n", "tee": "y", "cup": "n", "from": "OTB", "to": "OST", "asc": "1", "dist": "9523", "left": "4484", "x": "8725.440", "y": "9898.889", "z": "979.016", "club": "CDR", "con": "", "shotText": "Shot 1 265 yds to fairway bunker, 125 yds to hole"}, {"n": "2", "pid": "0", "time": "", "putt": "", "t": "S", "prv": "n", "tee": "n", "cup": "n", "from": "OST", "to": "EG6", "asc": "1", "dist": "4090", "left": "435", "x": "8409.360", "y": "9771.449", "z": "982.835", "club": "CUK", "con": "", "shotText": "Shot 2 114 yds to left green side bunker, 36 ft to hole"}, {"n": "3", "pid": "0", "time": "", "putt": "", "t": "S", "prv": "n", "tee": "n", "cup": "n", "from": "OGS", "to": "OGR", "asc": "1", "dist": "451", "left": "44", "x": "8371.794", "y": "9770.459", "z": "984.110", "club": "CUK", "con": "", "shotText": "Shot 3 38 ft to green, 4 ft to hole"}, {"n": "4", "pid": "0", "time": "", "putt": "1", "t": "S", "prv": "n", "tee": "n", "cup": "y", "from": "OGR", "to": "hole", "asc": "1", "dist": "44", "left": "0", "x": "0", "y": "0", "z": "0", "club": "CUK", "con": "", "shotText": "Shot 4 in the hole"}]}, {"n": "11", "cNum": "11", "sc": "9", "pDay": "3", "pTot": "-1", "shots": [{"n": "1", "pid": "0", "time": "", "putt": "", "t": "S", "prv": "n", "tee": "y", "cup": "n", "from": "OTB", "to": "ONA", "asc": "1", "dist": "10507", "left": "5543", "x": "7493.129", "y": "10425.842", "z": "981.238", "club": "CDR", "con": "", "shotText": "Shot 1 292 yds to native area, 154 yds to hole"}, {"n": "2", "pid": "0", "time": "", "putt": "", "t": "S", "prv": "n", "tee": "n", "cup": "n", "from": "ONA", "to": "ONA", "asc": "1", "dist": "859", "left": "4690", "x": "7427.243", "y": "10453.715", "z": "979.470", "club": "CUK", "con": "", "shotText": "Shot 2 72 ft to native area, 130 yds to hole"}, {"n": "3", "pid": "0", "time": "", "putt": "", "t": "S", "prv": "n", "tee": "n", "cup": "n", "from": "ONA", "to": "ONA", "asc": "1", "dist": "1", "left": "4689", "x": "7427.16", "y": "10453.80", "z": "979.47", "club": "CUK", "con": "", "shotText": "Shot 3 1 in. to native area, 130 yds to hole"}, {"n": "4", "pid": "0", "time": "", "putt": "", "t": "S", "prv": "n", "tee": "n", "cup": "n", "from": "ONA", "to": "ONA", "asc": "1", "dist": "1", "left": "4687", "x": "7427.09", "y": "10453.90", "z": "979.47", "club": "CUK", "con": "", "shotText": "Shot 4 1 in. to native area, 130 yds to hole"}, {"n": "5", "pid": "0", "time": "", "putt": "", "t": "S", "prv": "n", "tee": "n", "cup": "n", "from": "ONA", "to": "ERR", "asc": "1", "dist": "518", "left": "4711", "x": "7405.180", "y": "10416.800", "z": "981.645", "club": "CUK", "con": "", "shotText": "Shot 5 43 ft to right rough, 131 yds to hole"}, {"n": "6", "pid": "0", "time": "", "putt": "", "t": "S", "prv": "n", "tee": "n", "cup": "n", "from": "ORO", "to": "ELF", "asc": "1", "dist": "4105", "left": "645", "x": "7120.123", "y": "10605.839", "z": "981.469", "club": "CUK", "con": "", "shotText": "Shot 6 114 yds to left fairway, 54 ft to hole"}, {"n": "7", "pid": "0", "time": "", "putt": "", "t": "S", "prv": "n", "tee": "n", "cup": "n", "from": "OFW", "to": "OGR", "asc": "1", "dist": "649", "left": "82", "x": "7083.357", "y": "10645.458", "z": "982.361", "club": "CUK", "con": "", "shotText": "Shot 7 54 ft to green, 7 ft to hole"}, {"n": "8", "pid": "0", "time": "", "putt": "1", "t": "S", "prv": "n", "tee": "n", "cup": "n", "from": "OGR", "to": "OGR", "asc": "1", "dist": "120", "left": "33", "x": "7091.608", "y": "10651.097", "z": "982.516", "club": "CUK", "con": "", "shotText": "Shot 8 putt 10 ft 0 in., 2 ft 9 in. to hole"}, {"n": "9", "pid": "0", "time": "", "putt": "2", "t": "S", "prv": "n", "tee": "n", "cup": "y", "from": "OGR", "to": "hole", "asc": "1", "dist": "33", "left": "0", "x": "0", "y": "0", "z": "0", "club": "CUK", "con": "", "shotText": "Shot 9 in the hole"}]}, {"n": "12", "cNum": "12", "sc": "3", "pDay": "3", "pTot": "-1", "shots": [{"n": "1", "pid": "0", "time": "", "putt": "", "t": "S", "prv": "n", "tee": "y", "cup": "n", "from": "OTB", "to": "OGR", "asc": "1", "dist": "6705", "left": "160", "x": "6513.683", "y": "10303.606", "z": "980.168", "club": "CUK", "con": "", "shotText": "Shot 1 186 yds to green, 13 ft to hole"}, {"n": "2", "pid": "0", "time": "", "putt": "1", "t": "S", "prv": "n", "tee": "n", "cup": "n", "from": "OGR", "to": "OGR", "asc": "1", "dist": "185", "left": "21", "x": "6508.134", "y": "10289.266", "z": "980.301", "club": "CUK", "con": "", "shotText": "Shot 2 putt 15 ft 5 in., 21 in. to hole"}, {"n": "3", "pid": "0", "time": "", "putt": "2", "t": "S", "prv": "n", "tee": "n", "cup": "y", "from": "OGR", "to": "hole", "asc": "1", "dist": "21", "left": "0", "x": "0", "y": "0", "z": "0", "club": "CUK", "con": "", "shotText": "Shot 3 in the hole"}]}, {"n": "13", "cNum": "13", "sc": "4", "pDay": "2", "pTot": "-2", "shots": [{"n": "1", "pid": "0", "time": "", "putt": "", "t": "S", "prv": "n", "tee": "y", "cup": "n", "from": "OTB", "to": "ERF", "asc": "1", "dist": "9913", "left": "10015", "x": "5725.270", "y": "10921.683", "z": "981.875", "club": "CDR", "con": "", "shotText": "Shot 1 275 yds to right fairway, 278 yds to hole"}, {"n": "2", "pid": "0", "time": "", "putt": "", "t": "S", "prv": "n", "tee": "n", "cup": "n", "from": "OFW", "to": "EG2", "asc": "1", "dist": "9533", "left": "503", "x": "5232.474", "y": "11544.763", "z": "982.369", "club": "CUK", "con": "", "shotText": "Shot 2 265 yds to right green side bunker, 42 ft to hole"}, {"n": "3", "pid": "0", "time": "", "putt": "", "t": "S", "prv": "n", "tee": "n", "cup": "n", "from": "OGS", "to": "OGR", "asc": "1", "dist": "523", "left": "56", "x": "5195.113", "y": "11566.585", "z": "987.918", "club": "CUK", "con": "", "shotText": "Shot 3 44 ft to green, 5 ft to hole"}, {"n": "4", "pid": "0", "time": "", "putt": "1", "t": "S", "prv": "n", "tee": "n", "cup": "y", "from": "OGR", "to": "hole", "asc": "1", "dist": "56", "left": "0", "x": "0", "y": "0", "z": "0", "club": "CUK", "con": "", "shotText": "Shot 4 in the hole"}]}, {"n": "14", "cNum": "14", "sc": "4", "pDay": "2", "pTot": "-2", "shots": [{"n": "1", "pid": "0", "time": "", "putt": "", "t": "S", "prv": "n", "tee": "y", "cup": "n", "from": "OTB", "to": "ELF", "asc": "1", "dist": "10783", "left": "4676", "x": "5475.880", "y": "10584.755", "z": "984.777", "club": "CDR", "con": "", "shotText": "Shot 1 300 yds to left fairway, 130 yds to hole"}, {"n": "2", "pid": "0", "time": "", "putt": "", "t": "S", "prv": "n", "tee": "n", "cup": "n", "from": "OFW", "to": "ERF", "asc": "1", "dist": "4407", "left": "282", "x": "5754.746", "y": "10345.799", "z": "985.298", "club": "CUK", "con": "", "shotText": "Shot 2 122 yds to right fairway, 24 ft to hole"}, {"n": "3", "pid": "0", "time": "", "putt": "", "t": "S", "prv": "n", "tee": "n", "cup": "n", "from": "OCO", "to": "OGR", "asc": "1", "dist": "264", "left": "24", "x": "5774.578", "y": "10336.238", "z": "986.006", "club": "CUK", "con": "", "shotText": "Shot 3 22 ft to green, 2 ft to hole"}, {"n": "4", "pid": "0", "time": "", "putt": "1", "t": "S", "prv": "n", "tee": "n", "cup": "y", "from": "OGR", "to": "hole", "asc": "1", "dist": "24", "left": "0", "x": "0", "y": "0", "z": "0", "club": "CUK", "con": "", "shotText": "Shot 4 in the hole"}]}, {"n": "15", "cNum": "15", "sc": "5", "pDay": "2", "pTot": "-2", "shots": [{"n": "1", "pid": "0", "time": "", "putt": "", "t": "S", "prv": "n", "tee": "y", "cup": "n", "from": "OTB", "to": "ELF", "asc": "1", "dist": "10929", "left": "9775", "x": "6863.191", "y": "10079.394", "z": "979.619", "club": "CDR", "con": "", "shotText": "Shot 1 304 yds to left fairway, 272 yds to hole"}, {"n": "2", "pid": "0", "time": "", "putt": "", "t": "S", "prv": "n", "tee": "n", "cup": "n", "from": "OFW", "to": "EG6", "asc": "1", "dist": "9181", "left": "1078", "x": "7628.261", "y": "10072.732", "z": "977.533", "club": "CUK", "con": "", "shotText": "Shot 2 255 yds to left green side bunker, 90 ft to hole"}, {"n": "3", "pid": "0", "time": "", "putt": "", "t": "S", "prv": "n", "tee": "n", "cup": "n", "from": "OGS", "to": "OGR", "asc": "1", "dist": "1238", "left": "171", "x": "7685.826", "y": "9987.232", "z": "981.190", "club": "CUK", "con": "", "shotText": "Shot 3 34 yds to green, 14 ft to hole"}, {"n": "4", "pid": "0", "time": "", "putt": "1", "t": "S", "prv": "n", "tee": "n", "cup": "n", "from": "OGR", "to": "OGR", "asc": "1", "dist": "196", "left": "20", "x": "7671.928", "y": "9995.877", "z": "981.606", "club": "CUK", "con": "", "shotText": "Shot 4 putt 16 ft 4 in., 20 in. to hole"}, {"n": "5", "pid": "0", "time": "", "putt": "2", "t": "S", "prv": "n", "tee": "n", "cup": "y", "from": "OGR", "to": "hole", "asc": "1", "dist": "20", "left": "0", "x": "0", "y": "0", "z": "0", "club": "CUK", "con": "", "shotText": "Shot 5 in the hole"}]}, {"n": "16", "cNum": "16", "sc": "3", "pDay": "2", "pTot": "-2", "shots": [{"n": "1", "pid": "0", "time": "", "putt": "", "t": "S", "prv": "n", "tee": "y", "cup": "n", "from": "OTB", "to": "OGR", "asc": "1", "dist": "4511", "left": "130", "x": "8106.836", "y": "9788.749", "z": "984.560", "club": "CUK", "con": "", "shotText": "Shot 1 125 yds to green, 11 ft to hole"}, {"n": "2", "pid": "0", "time": "", "putt": "1", "t": "S", "prv": "n", "tee": "n", "cup": "n", "from": "OGR", "to": "OGR", "asc": "1", "dist": "174", "left": "44", "x": "8119.011", "y": "9796.676", "z": "984.507", "club": "CUK", "con": "", "shotText": "Shot 2 putt 14 ft 6 in., 3 ft 8 in. to hole"}, {"n": "3", "pid": "0", "time": "", "putt": "2", "t": "S", "prv": "n", "tee": "n", "cup": "y", "from": "OGR", "to": "hole", "asc": "1", "dist": "44", "left": "0", "x": "0", "y": "0", "z": "0", "club": "CUK", "con": "", "shotText": "Shot 3 in the hole"}]}, {"n": "17", "cNum": "17", "sc": "4", "pDay": "2", "pTot": "-2", "shots": [{"n": "1", "pid": "0", "time": "", "putt": "", "t": "S", "prv": "n", "tee": "y", "cup": "n", "from": "OTB", "to": "ELR", "asc": "1", "dist": "11048", "left": "1422", "x": "9032.309", "y": "9633.972", "z": "977.413", "club": "CDR", "con": "", "shotText": "Shot 1 307 yds to left rough, 40 yds to hole"}, {"n": "2", "pid": "0", "time": "", "putt": "", "t": "S", "prv": "n", "tee": "n", "cup": "n", "from": "ORO", "to": "OGR", "asc": "1", "dist": "1273", "left": "151", "x": "9112.682", "y": "9564.858", "z": "982.203", "club": "CUK", "con": "", "shotText": "Shot 2 35 yds to green, 13 ft to hole"}, {"n": "3", "pid": "0", "time": "", "putt": "1", "t": "S", "prv": "n", "tee": "n", "cup": "n", "from": "OGR", "to": "OGR", "asc": "1", "dist": "184", "left": "28", "x": "9122.369", "y": "9552.948", "z": "982.322", "club": "CUK", "con": "", "shotText": "Shot 3 putt 15 ft 4 in., 2 ft 4 in. to hole"}, {"n": "4", "pid": "0", "time": "", "putt": "2", "t": "S", "prv": "n", "tee": "n", "cup": "y", "from": "OGR", "to": "hole", "asc": "1", "dist": "28", "left": "0", "x": "0", "y": "0", "z": "0", "club": "CUK", "con": "", "shotText": "Shot 4 in the hole"}]}, {"n": "18", "cNum": "18", "sc": "4", "pDay": "2", "pTot": "-2", "shots": [{"n": "1", "pid": "0", "time": "", "putt": "", "t": "S", "prv": "n", "tee": "y", "cup": "n", "from": "OTB", "to": "OST", "asc": "1", "dist": "11408", "left": "4256", "x": "9630.321", "y": "10215.378", "z": "980.457", "club": "CDR", "con": "", "shotText": "Shot 1 317 yds to fairway bunker, 118 yds to hole"}, {"n": "2", "pid": "0", "time": "", "putt": "", "t": "S", "prv": "n", "tee": "n", "cup": "n", "from": "OST", "to": "ERF", "asc": "1", "dist": "3190", "left": "1073", "x": "9559.834", "y": "10471.678", "z": "979.460", "club": "CUK", "con": "", "shotText": "Shot 2 89 yds to right fairway, 89 ft to hole"}, {"n": "3", "pid": "0", "time": "", "putt": "", "t": "S", "prv": "n", "tee": "n", "cup": "n", "from": "OFW", "to": "OGR", "asc": "1", "dist": "845", "left": "230", "x": "9535.589", "y": "10537.657", "z": "983.865", "club": "CUK", "con": "", "shotText": "Shot 3 70 ft to green, 19 ft to hole"}, {"n": "4", "pid": "0", "time": "", "putt": "1", "t": "S", "prv": "n", "tee": "n", "cup": "y", "from": "OGR", "to": "hole", "asc": "1", "dist": "230", "left": "0", "x": "0", "y": "0", "z": "0", "club": "CUK", "con": "", "shotText": "Shot 4 in the hole"}]}]}, {"n": "4", "holes": [{"n": "1", "cNum": "10", "sc": "4", "pDay": "0", "pTot": "-2", "shots": [{"n": "1", "pid": "0", "time": "", "putt": "", "t": "S", "prv": "n", "tee": "y", "cup": "n", "from": "OTB", "to": "ERF", "asc": "1", "dist": "9783", "left": "4976", "x": "8759.573", "y": "9822.725", "z": "979.697", "club": "CDR", "con": "", "shotText": "Shot 1 272 yds to right fairway, 138 yds to hole"}, {"n": "2", "pid": "0", "time": "", "putt": "", "t": "S", "prv": "n", "tee": "n", "cup": "n", "from": "OFW", "to": "OGR", "asc": "1", "dist": "4699", "left": "329", "x": "8368.155", "y": "9812.144", "z": "984.351", "club": "CUK", "con": "", "shotText": "Shot 2 131 yds to green, 27 ft to hole"}, {"n": "3", "pid": "0", "time": "", "putt": "1", "t": "S", "prv": "n", "tee": "n", "cup": "n", "from": "OGR", "to": "OGR", "asc": "1", "dist": "354", "left": "20", "x": "8344.060", "y": "9795.129", "z": "984.011", "club": "CUK", "con": "", "shotText": "Shot 3 putt 29 ft 6 in., 20 in. to hole"}, {"n": "4", "pid": "0", "time": "", "putt": "2", "t": "S", "prv": "n", "tee": "n", "cup": "y", "from": "OGR", "to": "hole", "asc": "1", "dist": "20", "left": "0", "x": "0", "y": "0", "z": "0", "club": "CUK", "con": "", "shotText": "Shot 4 in the hole"}]}, {"n": "2", "cNum": "11", "sc": "4", "pDay": "0", "pTot": "-2", "shots": [{"n": "1", "pid": "0", "time": "", "putt": "", "t": "S", "prv": "n", "tee": "y", "cup": "n", "from": "OTB", "to": "ERR", "asc": "1", "dist": "9773", "left": "7109", "x": "7584.832", "y": "10330.484", "z": "979.295", "club": "CDR", "con": "", "shotText": "Shot 1 271 yds to right rough, 197 yds to hole"}, {"n": "2", "pid": "0", "time": "", "putt": "", "t": "S", "prv": "n", "tee": "n", "cup": "n", "from": "ORO", "to": "ELF", "asc": "1", "dist": "5899", "left": "1282", "x": "7166.164", "y": "10588.134", "z": "980.093", "club": "CUK", "con": "", "shotText": "Shot 2 164 yds to left fairway, 36 yds to hole"}, {"n": "3", "pid": "0", "time": "", "putt": "", "t": "S", "prv": "n", "tee": "n", "cup": "n", "from": "OFW", "to": "OGR", "asc": "1", "dist": "1298", "left": "47", "x": "7059.162", "y": "10603.835", "z": "981.598", "club": "CUK", "con": "", "shotText": "Shot 3 36 yds to green, 4 ft to hole"}, {"n": "4", "pid": "0", "time": "", "putt": "1", "t": "S", "prv": "n", "tee": "n", "cup": "y", "from": "OGR", "to": "hole", "asc": "1", "dist": "47", "left": "0", "x": "0", "y": "0", "z": "0", "club": "CUK", "con": "", "shotText": "Shot 4 in the hole"}]}, {"n": "3", "cNum": "12", "sc": "3", "pDay": "0", "pTot": "-2", "shots": [{"n": "1", "pid": "0", "time": "", "putt": "", "t": "S", "prv": "n", "tee": "y", "cup": "n", "from": "OTB", "to": "OGR", "asc": "1", "dist": "6521", "left": "346", "x": "6523.438", "y": "10325.707", "z": "979.825", "club": "CUK", "con": "", "shotText": "Shot 1 181 yds to green, 29 ft to hole"}, {"n": "2", "pid": "0", "time": "", "putt": "1", "t": "S", "prv": "n", "tee": "n", "cup": "n", "from": "OGR", "to": "OGR", "asc": "1", "dist": "383", "left": "43", "x": "6491.644", "y": "10328.331", "z": "979.754", "club": "CUK", "con": "", "shotText": "Shot 2 putt 31 ft 11 in., 3 ft 7 in. to hole"}, {"n": "3", "pid": "0", "time": "", "putt": "2", "t": "S", "prv": "n", "tee": "n", "cup": "y", "from": "OGR", "to": "hole", "asc": "1", "dist": "43", "left": "0", "x": "0", "y": "0", "z": "0", "club": "CUK", "con": "", "shotText": "Shot 3 in the hole"}]}, {"n": "4", "cNum": "13", "sc": "5", "pDay": "0", "pTot": "-2", "shots": [{"n": "1", "pid": "0", "time": "", "putt": "", "t": "S", "prv": "n", "tee": "y", "cup": "n", "from": "OTB", "to": "ELR", "asc": "1", "dist": "10914", "left": "9333", "x": "5553.678", "y": "10835.180", "z": "982.282", "club": "CDR", "con": "", "shotText": "Shot 1 303 yds to left rough, 259 yds to hole"}, {"n": "2", "pid": "0", "time": "", "putt": "", "t": "S", "prv": "n", "tee": "n", "cup": "n", "from": "ORO", "to": "ERI", "asc": "1", "dist": "10305", "left": "1078", "x": "5170.700", "y": "11603.800", "z": "986.352", "club": "CUK", "con": "", "shotText": "Shot 2 286 yds to right intermediate, 90 ft to hole"}, {"n": "3", "pid": "0", "time": "", "putt": "", "t": "S", "prv": "n", "tee": "n", "cup": "n", "from": "OIR", "to": "OGR", "asc": "1", "dist": "736", "left": "351", "x": "5177.997", "y": "11542.911", "z": "987.586", "club": "CUK", "con": "", "shotText": "Shot 3 61 ft to green, 29 ft to hole"}, {"n": "4", "pid": "0", "time": "", "putt": "1", "t": "S", "prv": "n", "tee": "n", "cup": "n", "from": "OGR", "to": "OGR", "asc": "1", "dist": "370", "left": "22", "x": "5171.670", "y": "11512.717", "z": "987.002", "club": "CUK", "con": "", "shotText": "Shot 4 putt 30 ft 10 in., 22 in. to hole"}, {"n": "5", "pid": "0", "time": "", "putt": "2", "t": "S", "prv": "n", "tee": "n", "cup": "y", "from": "OGR", "to": "hole", "asc": "1", "dist": "22", "left": "0", "x": "0", "y": "0", "z": "0", "club": "CUK", "con": "", "shotText": "Shot 5 in the hole"}]}, {"n": "5", "cNum": "14", "sc": "5", "pDay": "1", "pTot": "-1", "shots": [{"n": "1", "pid": "0", "time": "", "putt": "", "t": "S", "prv": "n", "tee": "y", "cup": "n", "from": "OTB", "to": "ERF", "asc": "1", "dist": "9912", "left": "6480", "x": "5401.593", "y": "10631.477", "z": "987.086", "club": "CDR", "con": "", "shotText": "Shot 1 275 yds to right fairway, 180 yds to hole"}, {"n": "2", "pid": "0", "time": "", "putt": "", "t": "S", "prv": "n", "tee": "n", "cup": "n", "from": "OFW", "to": "OGR", "asc": "1", "dist": "5671", "left": "810", "x": "5761.074", "y": "10324.657", "z": "985.920", "club": "CUK", "con": "", "shotText": "Shot 2 158 yds to green, 68 ft to hole"}, {"n": "3", "pid": "0", "time": "", "putt": "1", "t": "S", "prv": "n", "tee": "n", "cup": "n", "from": "OGR", "to": "OGR", "asc": "1", "dist": "682", "left": "130", "x": "5805.599", "y": "10289.406", "z": "987.002", "club": "CUK", "con": "", "shotText": "Shot 3 putt 56 ft 10 in., 10 ft 10 in. to hole"}, {"n": "4", "pid": "0", "time": "", "putt": "2", "t": "S", "prv": "n", "tee": "n", "cup": "n", "from": "OGR", "to": "OGR", "asc": "1", "dist": "158", "left": "24", "x": "5817.292", "y": "10283.392", "z": "987.220", "club": "CUK", "con": "", "shotText": "Shot 4 putt 13 ft 2 in., 2 ft 0 in. to hole"}, {"n": "5", "pid": "0", "time": "", "putt": "3", "t": "S", "prv": "n", "tee": "n", "cup": "y", "from": "OGR", "to": "hole", "asc": "1", "dist": "24", "left": "0", "x": "0", "y": "0", "z": "0", "club": "CUK", "con": "", "shotText": "Shot 5 in the hole"}]}, {"n": "6", "cNum": "15", "sc": "4", "pDay": "0", "pTot": "-2", "shots": [{"n": "1", "pid": "0", "time": "", "putt": "", "t": "S", "prv": "n", "tee": "y", "cup": "n", "from": "OTB", "to": "ERF", "asc": "1", "dist": "11589", "left": "8883", "x": "6906.287", "y": "10010.265", "z": "980.187", "club": "CDR", "con": "", "shotText": "Shot 1 322 yds to right fairway, 247 yds to hole"}, {"n": "2", "pid": "0", "time": "", "putt": "", "t": "S", "prv": "n", "tee": "n", "cup": "n", "from": "OFW", "to": "ELF", "asc": "1", "dist": "6166", "left": "2792", "x": "7416.423", "y": "10071.419", "z": "977.063", "club": "CUK", "con": "", "shotText": "Shot 2 171 yds to left fairway, 78 yds to hole"}, {"n": "3", "pid": "0", "time": "", "putt": "", "t": "S", "prv": "n", "tee": "n", "cup": "n", "from": "OFW", "to": "OGR", "asc": "1", "dist": "2933", "left": "170", "x": "7656.139", "y": "10024.188", "z": "982.250", "club": "CUK", "con": "", "shotText": "Shot 3 81 yds to green, 14 ft to hole"}, {"n": "4", "pid": "0", "time": "", "putt": "1", "t": "S", "prv": "n", "tee": "n", "cup": "y", "from": "OGR", "to": "hole", "asc": "1", "dist": "170", "left": "0", "x": "0", "y": "0", "z": "0", "club": "CUK", "con": "", "shotText": "Shot 4 in the hole"}]}, {"n": "7", "cNum": "16", "sc": "3", "pDay": "0", "pTot": "-2", "shots": [{"n": "1", "pid": "0", "time": "", "putt": "", "t": "S", "prv": "n", "tee": "y", "cup": "n", "from": "OTB", "to": "EG4", "asc": "1", "dist": "5149", "left": "804", "x": "8073.960", "y": "9799.750", "z": "977.738", "club": "CUK", "con": "", "shotText": "Shot 1 143 yds to front center green side bunker, 67 ft to hole"}, {"n": "2", "pid": "0", "time": "", "putt": "", "t": "S", "prv": "n", "tee": "n", "cup": "n", "from": "OGS", "to": "OGR", "asc": "1", "dist": "747", "left": "134", "x": "8135.071", "y": "9790.550", "z": "985.007", "club": "CUK", "con": "", "shotText": "Shot 2 62 ft to green, 11 ft to hole"}, {"n": "3", "pid": "0", "time": "", "putt": "1", "t": "S", "prv": "n", "tee": "n", "cup": "y", "from": "OGR", "to": "hole", "asc": "1", "dist": "134", "left": "0", "x": "0", "y": "0", "z": "0", "club": "CUK", "con": "", "shotText": "Shot 3 in the hole"}]}, {"n": "8", "cNum": "17", "sc": "4", "pDay": "0", "pTot": "-2", "shots": [{"n": "1", "pid": "0", "time": "", "putt": "", "t": "S", "prv": "n", "tee": "y", "cup": "n", "from": "OTB", "to": "ERF", "asc": "1", "dist": "10383", "left": "2225", "x": "8981.264", "y": "9547.362", "z": "977.954", "club": "CDR", "con": "", "shotText": "Shot 1 288 yds to right fairway, 62 yds to hole"}, {"n": "2", "pid": "0", "time": "", "putt": "", "t": "S", "prv": "n", "tee": "n", "cup": "n", "from": "OFW", "to": "OGR", "asc": "1", "dist": "1907", "left": "322", "x": "9133.278", "y": "9593.444", "z": "981.477", "club": "CUK", "con": "", "shotText": "Shot 2 53 yds to green, 27 ft to hole"}, {"n": "3", "pid": "0", "time": "", "putt": "1", "t": "S", "prv": "n", "tee": "n", "cup": "n", "from": "OGR", "to": "OGR", "asc": "1", "dist": "384", "left": "59", "x": "9161.375", "y": "9608.808", "z": "981.068", "club": "CUK", "con": "", "shotText": "Shot 3 putt 32 ft 0 in., 4 ft 11 in. to hole"}, {"n": "4", "pid": "0", "time": "", "putt": "2", "t": "S", "prv": "n", "tee": "n", "cup": "y", "from": "OGR", "to": "hole", "asc": "1", "dist": "59", "left": "0", "x": "0", "y": "0", "z": "0", "club": "CUK", "con": "", "shotText": "Shot 4 in the hole"}]}, {"n": "9", "cNum": "18", "sc": "4", "pDay": "0", "pTot": "-2", "shots": [{"n": "1", "pid": "0", "time": "", "putt": "", "t": "S", "prv": "n", "tee": "y", "cup": "n", "from": "OTB", "to": "ERF", "asc": "1", "dist": "10605", "left": "5847", "x": "9587.305", "y": "10148.214", "z": "981.054", "club": "CDR", "con": "", "shotText": "Shot 1 295 yds to right fairway, 162 yds to hole"}, {"n": "2", "pid": "0", "time": "", "putt": "", "t": "S", "prv": "n", "tee": "n", "cup": "n", "from": "OFW", "to": "ERR", "asc": "1", "dist": "6410", "left": "564", "x": "9559.995", "y": "10681.670", "z": "984.171", "club": "CUK", "con": "", "shotText": "Shot 2 178 yds to right rough, 47 ft to hole"}, {"n": "3", "pid": "0", "time": "", "putt": "", "t": "S", "prv": "n", "tee": "n", "cup": "n", "from": "ORO", "to": "OGR", "asc": "1", "dist": "464", "left": "101", "x": "9556.777", "y": "10643.173", "z": "985.980", "club": "CUK", "con": "", "shotText": "Shot 3 39 ft to green, 8 ft to hole"}, {"n": "4", "pid": "0", "time": "", "putt": "1", "t": "S", "prv": "n", "tee": "n", "cup": "y", "from": "OGR", "to": "hole", "asc": "1", "dist": "101", "left": "0", "x": "0", "y": "0", "z": "0", "club": "CUK", "con": "", "shotText": "Shot 4 in the hole"}]}, {"n": "10", "cNum": "1", "sc": "4", "pDay": "0", "pTot": "-2", "shots": [{"n": "1", "pid": "0", "time": "", "putt": "", "t": "S", "prv": "n", "tee": "y", "cup": "n", "from": "OTB", "to": "ERF", "asc": "1", "dist": "10525", "left": "3964", "x": "8813.514", "y": "11737.903", "z": "1004.028", "club": "CFW", "con": "", "shotText": "Shot 1 292 yds to right fairway, 110 yds to hole"}, {"n": "2", "pid": "0", "time": "", "putt": "", "t": "S", "prv": "n", "tee": "n", "cup": "n", "from": "OFW", "to": "OGR", "asc": "1", "dist": "3901", "left": "131", "x": "8594.484", "y": "11978.090", "z": "1005.261", "club": "CUK", "con": "", "shotText": "Shot 2 108 yds to green, 11 ft to hole"}, {"n": "3", "pid": "0", "time": "", "putt": "1", "t": "S", "prv": "n", "tee": "n", "cup": "n", "from": "OGR", "to": "OGR", "asc": "1", "dist": "146", "left": "10", "x": "8598.455", "y": "11989.609", "z": "1005.375", "club": "CUK", "con": "", "shotText": "Shot 3 putt 12 ft 2 in., 10 in. to hole"}, {"n": "4", "pid": "0", "time": "", "putt": "2", "t": "S", "prv": "n", "tee": "n", "cup": "y", "from": "OGR", "to": "hole", "asc": "1", "dist": "10", "left": "0", "x": "0", "y": "0", "z": "0", "club": "CUK", "con": "", "shotText": "Shot 4 in the hole"}]}, {"n": "11", "cNum": "2", "sc": "4", "pDay": "0", "pTot": "-2", "shots": [{"n": "1", "pid": "0", "time": "", "putt": "", "t": "S", "prv": "n", "tee": "y", "cup": "n", "from": "OTB", "to": "ELF", "asc": "1", "dist": "10047", "left": "5233", "x": "8702.916", "y": "11261.546", "z": "998.799", "club": "CDR", "con": "", "shotText": "Shot 1 279 yds to left fairway, 145 yds to hole"}, {"n": "2", "pid": "0", "time": "", "putt": "", "t": "S", "prv": "n", "tee": "n", "cup": "n", "from": "OFW", "to": "OGR", "asc": "1", "dist": "5020", "left": "303", "x": "8872.481", "y": "10879.290", "z": "988.652", "club": "CUK", "con": "", "shotText": "Shot 2 139 yds to green, 25 ft to hole"}, {"n": "3", "pid": "0", "time": "", "putt": "1", "t": "S", "prv": "n", "tee": "n", "cup": "n", "from": "OGR", "to": "OGR", "asc": "1", "dist": "315", "left": "14", "x": "8896.821", "y": "10869.372", "z": "988.527", "club": "CUK", "con": "", "shotText": "Shot 3 putt 26 ft 3 in., 14 in. to hole"}, {"n": "4", "pid": "0", "time": "", "putt": "2", "t": "S", "prv": "n", "tee": "n", "cup": "y", "from": "OGR", "to": "hole", "asc": "1", "dist": "14", "left": "0", "x": "0", "y": "0", "z": "0", "club": "CUK", "con": "", "shotText": "Shot 4 in the hole"}]}, {"n": "12", "cNum": "3", "sc": "6", "pDay": "1", "pTot": "-1", "shots": [{"n": "1", "pid": "0", "time": "", "putt": "", "t": "S", "prv": "n", "tee": "y", "cup": "n", "from": "OTB", "to": "ELF", "asc": "1", "dist": "9754", "left": "10810", "x": "7813.542", "y": "11053.758", "z": "987.715", "club": "CDR", "con": "", "shotText": "Shot 1 271 yds to left fairway, 300 yds to hole"}, {"n": "2", "pid": "0", "time": "", "putt": "", "t": "S", "prv": "n", "tee": "n", "cup": "n", "from": "OFW", "to": "ONA", "asc": "1", "dist": "9488", "left": "1457", "x": "7060.805", "y": "11295.485", "z": "980.954", "club": "CUK", "con": "", "shotText": "Shot 2 264 yds to native area, 40 yds to hole"}, {"n": "3", "pid": "0", "time": "", "putt": "", "t": "S", "prv": "n", "tee": "n", "cup": "n", "from": "ONA", "to": "ELR", "asc": "1", "dist": "1797", "left": "385", "x": "6965.390", "y": "11410.122", "z": "993.896", "club": "CUK", "con": "", "shotText": "Shot 3 50 yds to left rough, 32 ft to hole"}, {"n": "4", "pid": "0", "time": "", "putt": "", "t": "S", "prv": "n", "tee": "n", "cup": "n", "from": "ORO", "to": "OGR", "asc": "1", "dist": "271", "left": "114", "x": "6971.178", "y": "11388.267", "z": "994.676", "club": "CUK", "con": "", "shotText": "Shot 4 23 ft to green, 10 ft to hole"}, {"n": "5", "pid": "0", "time": "", "putt": "1", "t": "S", "prv": "n", "tee": "n", "cup": "n", "from": "OGR", "to": "OGR", "asc": "1", "dist": "128", "left": "10", "x": "6973.904", "y": "11377.938", "z": "994.471", "club": "CUK", "con": "", "shotText": "Shot 5 putt 10 ft 8 in., 10 in. to hole"}, {"n": "6", "pid": "0", "time": "", "putt": "2", "t": "S", "prv": "n", "tee": "n", "cup": "y", "from": "OGR", "to": "hole", "asc": "1", "dist": "10", "left": "0", "x": "0", "y": "0", "z": "0", "club": "CUK", "con": "", "shotText": "Shot 6 in the hole"}]}, {"n": "13", "cNum": "4", "sc": "3", "pDay": "1", "pTot": "-1", "shots": [{"n": "1", "pid": "0", "time": "", "putt": "", "t": "S", "prv": "n", "tee": "y", "cup": "n", "from": "OTB", "to": "OGR", "asc": "1", "dist": "5861", "left": "196", "x": "6873.339", "y": "11894.734", "z": "997.599", "club": "CUK", "con": "", "shotText": "Shot 1 163 yds to green, 16 ft to hole"}, {"n": "2", "pid": "0", "time": "", "putt": "1", "t": "S", "prv": "n", "tee": "n", "cup": "n", "from": "OGR", "to": "OGR", "asc": "1", "dist": "229", "left": "28", "x": "6890.465", "y": "11886.408", "z": "997.212", "club": "CUK", "con": "", "shotText": "Shot 2 putt 19 ft 1 in., 2 ft 4 in. to hole"}, {"n": "3", "pid": "0", "time": "", "putt": "2", "t": "S", "prv": "n", "tee": "n", "cup": "y", "from": "OGR", "to": "hole", "asc": "1", "dist": "28", "left": "0", "x": "0", "y": "0", "z": "0", "club": "CUK", "con": "", "shotText": "Shot 3 in the hole"}]}, {"n": "14", "cNum": "5", "sc": "4", "pDay": "1", "pTot": "-1", "shots": [{"n": "1", "pid": "0", "time": "", "putt": "", "t": "S", "prv": "n", "tee": "y", "cup": "n", "from": "OTB", "to": "ELR", "asc": "1", "dist": "10375", "left": "6506", "x": "6212.162", "y": "11691.549", "z": "994.146", "club": "CDR", "con": "", "shotText": "Shot 1 288 yds to left rough, 181 yds to hole"}, {"n": "2", "pid": "0", "time": "", "putt": "", "t": "S", "prv": "n", "tee": "n", "cup": "n", "from": "ORO", "to": "OGR", "asc": "1", "dist": "6035", "left": "495", "x": "5777.010", "y": "11439.376", "z": "991.997", "club": "CUK", "con": "", "shotText": "Shot 2 168 yds to green, 41 ft to hole"}, {"n": "3", "pid": "0", "time": "", "putt": "1", "t": "S", "prv": "n", "tee": "n", "cup": "n", "from": "OGR", "to": "OGR", "asc": "1", "dist": "499", "left": "24", "x": "5751.306", "y": "11406.652", "z": "992.578", "club": "CUK", "con": "", "shotText": "Shot 3 putt 41 ft 7 in., 2 ft 0 in. to hole"}, {"n": "4", "pid": "0", "time": "", "putt": "2", "t": "S", "prv": "n", "tee": "n", "cup": "y", "from": "OGR", "to": "hole", "asc": "1", "dist": "24", "left": "0", "x": "0", "y": "0", "z": "0", "club": "CUK", "con": "", "shotText": "Shot 4 in the hole"}]}, {"n": "15", "cNum": "6", "sc": "4", "pDay": "1", "pTot": "-1", "shots": [{"n": "1", "pid": "0", "time": "", "putt": "", "t": "S", "prv": "n", "tee": "y", "cup": "n", "from": "OTB", "to": "ERF", "asc": "1", "dist": "10698", "left": "5196", "x": "6186.838", "y": "10811.166", "z": "982.578", "club": "CDR", "con": "", "shotText": "Shot 1 297 yds to right fairway, 144 yds to hole"}, {"n": "2", "pid": "0", "time": "", "putt": "", "t": "S", "prv": "n", "tee": "n", "cup": "n", "from": "OFW", "to": "OGR", "asc": "1", "dist": "4955", "left": "289", "x": "6596.114", "y": "10756.617", "z": "984.223", "club": "CUK", "con": "", "shotText": "Shot 2 138 yds to green, 24 ft to hole"}, {"n": "3", "pid": "0", "time": "", "putt": "1", "t": "S", "prv": "n", "tee": "n", "cup": "n", "from": "OGR", "to": "OGR", "asc": "1", "dist": "311", "left": "17", "x": "6619.413", "y": "10767.912", "z": "984.406", "club": "CUK", "con": "", "shotText": "Shot 3 putt 25 ft 11 in., 17 in. to hole"}, {"n": "4", "pid": "0", "time": "", "putt": "2", "t": "S", "prv": "n", "tee": "n", "cup": "y", "from": "OGR", "to": "hole", "asc": "1", "dist": "17", "left": "0", "x": "0", "y": "0", "z": "0", "club": "CUK", "con": "", "shotText": "Shot 4 in the hole"}]}, {"n": "16", "cNum": "7", "sc": "4", "pDay": "2", "pTot": "0", "shots": [{"n": "1", "pid": "0", "time": "", "putt": "", "t": "S", "prv": "n", "tee": "y", "cup": "n", "from": "OTB", "to": "ERF", "asc": "1", "dist": "7097", "left": "898", "x": "6381.440", "y": "11412.964", "z": "986.278", "club": "CUK", "con": "", "shotText": "Shot 1 197 yds to right fairway, 75 ft to hole"}, {"n": "2", "pid": "0", "time": "", "putt": "", "t": "S", "prv": "n", "tee": "n", "cup": "n", "from": "OFW", "to": "OGR", "asc": "1", "dist": "839", "left": "103", "x": "6348.198", "y": "11474.364", "z": "989.845", "club": "CUK", "con": "", "shotText": "Shot 2 70 ft to green, 9 ft to hole"}, {"n": "3", "pid": "0", "time": "", "putt": "1", "t": "S", "prv": "n", "tee": "n", "cup": "n", "from": "OGR", "to": "OGR", "asc": "1", "dist": "121", "left": "13", "x": "6352.535", "y": "11483.423", "z": "989.941", "club": "CUK", "con": "", "shotText": "Shot 3 putt 10 ft 1 in., 13 in. to hole"}, {"n": "4", "pid": "0", "time": "", "putt": "2", "t": "S", "prv": "n", "tee": "n", "cup": "y", "from": "OGR", "to": "hole", "asc": "1", "dist": "13", "left": "0", "x": "0", "y": "0", "z": "0", "club": "CUK", "con": "", "shotText": "Shot 4 in the hole"}]}, {"n": "17", "cNum": "8", "sc": "4", "pDay": "2", "pTot": "0", "shots": [{"n": "1", "pid": "0", "time": "", "putt": "", "t": "S", "prv": "n", "tee": "y", "cup": "n", "from": "OTB", "to": "ELI", "asc": "1", "dist": "10684", "left": "6872", "x": "7040.558", "y": "11023.206", "z": "980.627", "club": "CDR", "con": "", "shotText": "Shot 1 297 yds to left intermediate, 191 yds to hole"}, {"n": "2", "pid": "0", "time": "", "putt": "", "t": "S", "prv": "n", "tee": "n", "cup": "n", "from": "OIR", "to": "OGR", "asc": "1", "dist": "6757", "left": "257", "x": "7513.068", "y": "10716.965", "z": "982.238", "club": "CUK", "con": "", "shotText": "Shot 2 188 yds to green, 21 ft to hole"}, {"n": "3", "pid": "0", "time": "", "putt": "1", "t": "S", "prv": "n", "tee": "n", "cup": "n", "from": "OGR", "to": "OGR", "asc": "1", "dist": "257", "left": "1", "x": "7510.700", "y": "10695.645", "z": "981.867", "club": "CUK", "con": "", "shotText": "Shot 3 putt 21 ft 5 in., 1 in. to hole"}, {"n": "4", "pid": "0", "time": "", "putt": "2", "t": "S", "prv": "n", "tee": "n", "cup": "y", "from": "OGR", "to": "hole", "asc": "1", "dist": "1", "left": "0", "x": "0", "y": "0", "z": "0", "club": "CUK", "con": "", "shotText": "Shot 4 in the hole"}]}, {"n": "18", "cNum": "9", "sc": "4", "pDay": "2", "pTot": "0", "shots": [{"n": "1", "pid": "0", "time": "", "putt": "", "t": "S", "prv": "n", "tee": "y", "cup": "n", "from": "OTB", "to": "ELF", "asc": "1", "dist": "10795", "left": "5475", "x": "8334.304", "y": "10769.036", "z": "986.562", "club": "CDR", "con": "", "shotText": "Shot 1 300 yds to left fairway, 152 yds to hole"}, {"n": "2", "pid": "0", "time": "", "putt": "", "t": "S", "prv": "n", "tee": "n", "cup": "n", "from": "OFW", "to": "OGR", "asc": "1", "dist": "5776", "left": "376", "x": "8799.859", "y": "10646.944", "z": "987.977", "club": "CUK", "con": "", "shotText": "Shot 2 160 yds to green, 31 ft to hole"}, {"n": "3", "pid": "0", "time": "", "putt": "1", "t": "S", "prv": "n", "tee": "n", "cup": "n", "from": "OGR", "to": "OGR", "asc": "1", "dist": "381", "left": "10", "x": "8770.053", "y": "10635.977", "z": "987.701", "club": "CUK", "con": "", "shotText": "Shot 3 putt 31 ft 9 in., 10 in. to hole"}, {"n": "4", "pid": "0", "time": "", "putt": "2", "t": "S", "prv": "n", "tee": "n", "cup": "y", "from": "OGR", "to": "hole", "asc": "1", "dist": "10", "left": "0", "x": "0", "y": "0", "z": "0", "club": "CUK", "con": "", "shotText": "Shot 4 in the hole"}]}]}]}}